Workbook

Sheet Master Sheet
A1: Product Name | B1: SKU | C1: UPC/EAN | D1: Brand | E1: ASIN | F1: Model No. | G1: Product Name | H1: Description | I1: Color | J1: Fabric | K1: MRP | L1: HSN | M1: GST | N1: Quantity 1st Lot | O1: Sales | P1: FOB 1st Lot | Q1: DP | R1: Gross Weight (kg) | S1: L | T1: W | U1: H | V1: Volumetric Weight | AB1: =SUM(AB2:AB9)*40 -> 640 | AC1: =SUM(AC2:AC9)*40 -> 720 | AD1: =SUM(AD2:AD9)*40 -> 720 | AE1: =SUM(AE2:AE9)*40 -> 720 | AF1: =SUM(AF2:AF9)*40 -> 640 | AG1: =SUM(AG2:AG9)*40 -> 720
A2: Nexlev Falcon Series Gaming Chair with Fabric and Vegan Leather Upholstery - Black | B2: FBA75664 | C2: 8904422500006 | D2: Nexlev | E2: B0B5HCTGN5 | F2: FD-22-BK | G2: Nexlev Falcon Series Gaming Chair with Fabric and Vegan Leather Upholstery - Black | H2: Falcon Series Gaming Chair FD-22-BK | I2: Black | K2: 24999 | L2: 94013900 | M2: 0.18 | N2: 52 | O2: =VLOOKUP(F2,[3]Sheet3!$B$2:$E$9,4,0) -> #N/A | P2: 60.75 | Q2: 7927.713 | R2: 21 | S2: 67 | T2: 33 | U2: 87 | V2: =S2*T2*U2/5000 -> 38.4714 | AB2: 2 | AC2: 3 | AD2: 3 | AE2: 3 | AF2: 2 | AG2: 3
A3: Nexlev Falcon Series Gaming Chair with Fabric and Vegan Leather Upholstery - Red | B3: FBA75665 | C3: 8904422501713 | D3: Nexlev | E3: B0B5HCG8MM | F3: FD-22-RD | G3: Nexlev Falcon Series Gaming Chair with Fabric and Vegan Leather Upholstery - Red | H3: Falcon Series Gaming Chair FD-22-RD | I3: Red | K3: 24999 | L3: 94013900 | M3: 0.18 | N3: 52 | O3: =VLOOKUP(F3,[3]Sheet3!$B$2:$E$9,4,0) -> #N/A | P3: 60.75 | Q3: 7927.713 | R3: 21 | S3: 67 | T3: 33 | U3: 87 | V3: =S3*T3*U3/5000 -> 38.4714 | AB3: 2 | AC3: 3 | AD3: 3 | AE3: 3 | AF3: 2 | AG3: 3
A4: Nexlev Maverick Series Gaming Chair with Fabric Upholstery - Black | B4: FBA75666 | C4: 8904422501720 | D4: Nexlev | E4: B0B5HB1HJH | F4: MF-22-BK | G4: Nexlev Maverick Series Gaming Chair with Fabric Upholstery - Black | H4: Maverick Series Gaming Chair MF-22-BK | I4: Black | J4: Fabric | K4: 29999 | L4: 94013900 | M4: 0.18 | N4: 60 | O4: =VLOOKUP(F4,[3]Sheet3!$B$2:$E$9,4,0) -> #N/A | P4: 81.35 | Q4: 10094.235 | R4: 24 | S4: 83 | T4: 65 | U4: 37 | V4: =S4*T4*U4/5000 -> 39.923 | AB4: 3 | AC4: 3 | AD4: 3 | AE4: 3 | AF4: 3 | AG4: 3
A5: Nexlev Maverick Series Gaming Chair with Fabric Upholstery - Red | B5: FBA75667 | C5: 8904422501737 | D5: Nexlev | E5: B0B5HFGQGM | F5: MF-22-RD | G5: Nexlev Maverick Series Gaming Chair with Fabric Upholstery - Red | H5: Maverick Series Gaming Chair MF-22-RD | I5: Red | J5: Fabric | K5: 29999 | L5: 94013900 | M5: 0.18 | N5: 41 | O5: =VLOOKUP(F5,[3]Sheet3!$B$2:$E$9,4,0) -> #N/A | P5: 81.35 | Q5: 10094.235 | R5: 24 | S5: 83 | T5: 65 | U5: 37 | V5: =S5*T5*U5/5000 -> 39.923 | AB5: 2 | AC5: 2 | AD5: 2 | AE5: 2 | AF5: 2 | AG5: 2
A6: Nexlev Maverick Series Gaming Chair with Fabric Upholstery - Blue | B6: FBA75668 | C6: 8904422501744 | D6: Nexlev | E6: B0B5F78LMB | F6: MF-22-BL | G6: Nexlev Maverick Series Gaming Chair with Fabric Upholstery - Blue | H6: Maverick Series Gaming Chair MF-22-BL | I6: Blue | J6: Fabric | K6: 29999 | L6: 94013900 | M6: 0.18 | N6: 25 | O6: =VLOOKUP(F6,[3]Sheet3!$B$2:$E$9,4,0) -> #N/A | P6: 81.35 | Q6: 10094.235 | R6: 24 | S6: 83 | T6: 65 | U6: 37 | V6: =S6*T6*U6/5000 -> 39.923 | AB6: 1 | AC6: 1 | AD6: 1 | AE6: 1 | AF6: 1 | AG6: 1
A7: Nexlev Maverick Series Gaming Chair with Vegan Leather Upholstery - Black | B7: FBA75669 | C7: 8904422501751 | D7: Nexlev | E7: B0B5HFG6W7 | F7: ML-22-BK | G7: Nexlev Maverick Series Gaming Chair with Vegan Leather Upholstery - Black | H7: Maverick Series Gaming Chair ML-22-BK | I7: Black | J7: Leather | K7: 29999 | L7: 94013900 | M7: 0.18 | N7: 60 | O7: =VLOOKUP(F7,[3]Sheet3!$B$2:$E$9,4,0) -> #N/A | P7: 81.35 | Q7: 10094.235 | R7: 24 | S7: 83 | T7: 65 | U7: 37 | V7: =S7*T7*U7/5000 -> 39.923 | AB7: 3 | AC7: 3 | AD7: 3 | AE7: 3 | AF7: 3 | AG7: 3
A8: Nexlev Maverick Series Gaming Chair with Vegan Leather Upholstery - Red | B8: FBA75670 | C8: 8904422501768 | D8: Nexlev | E8: B0B5HDPTLC | F8: ML-22-RD | G8: Nexlev Maverick Series Gaming Chair with Vegan Leather Upholstery - Red | H8: Maverick Series Gaming Chair ML-22-RD | I8: Red | J8: Leather | K8: 29999 | L8: 94013900 | M8: 0.18 | N8: 40 | O8: =VLOOKUP(F8,[3]Sheet3!$B$2:$E$9,4,0) -> #N/A | P8: 81.35 | Q8: 10094.235 | R8: 24 | S8: 83 | T8: 65 | U8: 37 | V8: =S8*T8*U8/5000 -> 39.923 | AB8: 2 | AC8: 2 | AD8: 2 | AE8: 2 | AF8: 2 | AG8: 2
A9: Nexlev Maverick Series Gaming Chair with Vegan Leather Upholstery - Blue | B9: FBA75671 | C9: 8904422501775 | D9: Nexlev | E9: B0B5HCN3TJ | F9: ML-22-BL | G9: Nexlev Maverick Series Gaming Chair with Vegan Leather Upholstery - Blue | H9: Maverick Series Gaming Chair ML-22-BL | I9: Blue | J9: Leather | K9: 29999 | L9: 94013900 | M9: 0.18 | N9: 25 | O9: =VLOOKUP(F9,[3]Sheet3!$B$2:$E$9,4,0) -> #N/A | P9: 81.35 | Q9: 10094.235 | R9: 24 | S9: 83 | T9: 65 | U9: 37 | V9: =S9*T9*U9/5000 -> 39.923 | AB9: 1 | AC9: 1 | AD9: 1 | AE9: 1 | AF9: 1 | AG9: 1
A10: Nexlev Chronicle Series Gaming RGB Microphone with Tripod | B10: FBA75955 | C10: 8904422501782 | D10: Nexlev | E10: B0B5LM1FWP | F10: CM-22 | G10: Nexlev Chronicle Series Gaming RGB Microphone with Tripod | H10: Chronicle Series Gaming RGB Microphone CM-22 | I10: Black | K10: 9999 | L10: 85181000 | M10: 0.18 | N10: 29 | Q10: 2386.392 | R10: 0.77 | S10: 24 | T10: 17 | U10: 11 | V10: =S10*T10*U10/5000 -> 0.8976
A11: Nexlev Chronicle Series Gaming RGB Microphone with Shock Mount, Pop Filter, and Metal Stand | B11: FBA75956 | C11: 8904422501799 | D11: Nexlev | E11: B0B5LL2ZQR | F11: CM-22 Pro | G11: Nexlev Chronicle Series Gaming RGB Microphone with Shock Mount, Pop Filter, and Metal Stand | H11: Chronicle Series Gaming RGB Microphone CM-22 Pro | I11: Black | K11: 9999 | L11: 85181000 | M11: 0.18 | N11: 35 | Q11: 2892.036 | R11: 0.91 | S11: 26 | T11: 14 | U11: 11 | V11: =S11*T11*U11/5000 -> 0.8008
A12: Nexlev Falcon Series Footrest (Black) | B12: FBA75963 | C12: 8904422501928 | D12: Nexlev | E12: B0B71QN43M | F12: FD-22-FR | G12: Nexlev Falcon Series Footrest (Black) | H12: Falcon Series Footrest | I12: Black | K12: 6999 | L12: 94013900 | M12: 0.18 | N12: 10 | P12: 12.5 | Q12: 1721.148 | R12: 5.7 | S12: 54 | T12: 18 | U12: 51 | V12: =S12*T12*U12/5000 -> 9.9144 | AB12: 1 | AC12: 1 | AD12: 1 | AE12: 1 | AF12: 1 | AG12: 1
A13: Nexlev Maverick Series Footrest (Black) | B13: FBA75964 | C13: 8904422501935 | D13: Nexlev | E13: B0B71QY1TH | F13: ML-22-FR | G13: Nexlev Maverick Series Footrest (Black) | H13: Maverick Series Footrest | I13: Black | K13: 6999 | L13: 94013900 | M13: 0.18 | N13: 10 | P13: 12.5 | Q13: 1721.148 | R13: 5.7 | S13: 54 | T13: 18 | U13: 51 | V13: =S13*T13*U13/5000 -> 9.9144 | AB13: 1 | AC13: 1 | AD13: 1 | AE13: 1 | AF13: 1 | AG13: 1
A14: Nexlev 350mm Heavy Duty Aluminium Base (350mm aluminium base) | B14: FBA75967 | C14: 8904422501966 | D14: Nexlev | E14: B0BC93W1V1 | F14: AB-350 | G14: Nexlev 350mm Heavy Duty Aluminium Base (350mm aluminium base) | H14: 350mm aluminium base | K14: 6399 | L14: 94019900 | M14: 0.18 | N14: 50 | P14: 11.8 | Q14: 1595.55 | R14: 2.5 | S14: 67 | T14: 10 | U14: 65 | V14: =S14*T14*U14/5000 -> 8.71 | Y14: 278 | AA14: SBOB | AB14: SCCE | AC14: SHYG | AD14: SDEB | AE14: SBLB | AF14: SCJF | AG14: SMAC
A15: Nexlev 350mm Heavy Duty Metal Base (350mm metal base) | B15: FBA75968 | C15: 8904422501973 | D15: Nexlev | E15: B0BC99CYXD | F15: MB-350 | G15: Nexlev 350mm Heavy Duty Metal Base (350mm metal base) | H15: 350mm metal base | K15: 3999 | L15: 94019900 | M15: 0.18 | N15: 25 | P15: 5.9 | Q15: 993.75 | R15: 3.1 | S15: 67 | T15: 10 | U15: 65 | V15: =S15*T15*U15/5000 -> 8.71 | Y15: 278 | AB15: Majukhetra (West Bengal) | AC15: Hyderabad (Telangana) | AD15: Luhari Village (Haryana) | AE15: Kolar (Karnataka) | AF15: Coimbatore (Chennai) | AG15: Kanchipuram (Tamil Nadu)
A16: Nexlev 350mm Heavy Duty Nylon Base (350mm nylon base 2) | B16: FBA75969 | C16: 8904422501980 | D16: Nexlev | E16: B0BC93RS1L | F16: NB-350 | G16: Nexlev 350mm Heavy Duty Nylon Base (350mm nylon base 2) | H16: 350mm nylon base | K16: 2499 | L16: 94019900 | M16: 0.18 | N16: 10 | P16: 3.7 | Q16: 769.35 | R16: 2.65 | S16: 67 | T16: 10 | U16: 65 | V16: =S16*T16*U16/5000 -> 8.71 | Y16: 294 | AB16: Kolkata | AC16: Hyderabad | AD16: Delhi | AE16: Bangalore | AF16: Kerala | AG16: Chennai
A17: Nexlev 4D Armrest for Chairs (4D Armrest) | B17: FBA75965 | C17: 8904422501942 | D17: Nexlev | E17: B0BGXYD1ZP | F17: AR-4D | G17: Nexlev 4D Armrest for Chairs (4D Armrest) | H17: 4D Armrest | K17: 5499 | L17: 94019900 | M17: 0.18 | N17: 25 | P17: 10 | Q17: 1235.325 | R17: 3.5 | S17: 25 | T17: 29 | U17: 33 | V17: =S17*T17*U17/5000 -> 4.785 | Y17: 262
A18: Nexlev 3D Armrest for Chairs (3D Armrest) | B18: FBA75966 | C18: 8904422501959 | D18: Nexlev | E18: B0BGXZB3CM | F18: AR-3D | G18: Nexlev 3D Armrest for Chairs (3D Armrest) | H18: 3D Armrest | K18: 4599 | L18: 94019900 | M18: 0.18 | N18: 10 | P18: 7.9 | Q18: 1021.125 | R18: 2.9 | S18: 25 | T18: 29 | U18: 33 | V18: =S18*T18*U18/5000 -> 4.785 | Y18: 181.05
A19: Nexlev Butterfly Tilt Mechanism (Butterfly Mechanism) | B19: FBA75973 | C19: 8904422502024 | D19: Nexlev | E19: B0BGY2XKZ1 | F19: BM-01 | G19: Nexlev Butterfly Tilt Mechanism (Butterfly Mechanism) | H19: Butterfly Mechanism | K19: 2199 | L19: 94019900 | M19: 0.18 | N19: 10 | P19: 2.7 | Q19: 353.439 | R19: 1.75 | S19: 29 | T19: 23 | U19: 13 | V19: =S19*T19*U19/5000 -> 1.7342 | Y19: 197
A20: Nexlev Frog Tilt Mechanism (Frog Mechanism) | B20: FBA75974 | C20: 8904422502031 | D20: Nexlev | E20: B0BGY4MLKX | F20: FM-01 | G20: Nexlev Frog Tilt Mechanism (Frog Mechanism) | H20: Frog Mechanism | K20: 5699 | L20: 94019900 | M20: 0.18 | N20: 25 | P20: 10.4 | Q20: 1226.04 | R20: 3.9 | S20: 34 | T20: 27 | U20: 20 | V20: =S20*T20*U20/5000 -> 3.672 | Y20: 230
A21: Nexlev 75mm Racing Caster Wheels (75mm racing castor with lock) | B21: FBA75971 | C21: 8904422502000 | D21: Nexlev | E21: B0BGY3223L | F21: RC-75 | G21: Nexlev 75mm Racing Caster Wheels (75mm racing castor with lock) | H21: 75mm racing castor with lock | K21: 2499 | L21: 94019900 | M21: 0.18 | N21: 20 | P21: 3.6 | Q21: 382.752 | R21: 1.15 | S21: 8 | T21: 8 | U21: 27 | V21: =S21*T21*U21/5000 -> 0.3456 | Y21: 131
A22: Nexlev In-Line Rollerblade Casters for Chair (75mm Silicon wheel) | B22: FBA75972 | C22: 8904422502017 | D22: Nexlev | E22: B0BGY61JMN | F22: RB-75 | G22: Nexlev In-Line Rollerblade Casters for Chair (75mm Silicon wheel) | H22: 75mm Silicon wheel | K22: 3999 | L22: 94019900 | M22: 0.18 | N22: 20 | P22: 6.5 | Q22: 678.552 | R22: 1.25 | S22: 8 | T22: 8 | U22: 27 | V22: =S22*T22*U22/5000 -> 0.3456 | Y22: 131
A23: Nexlev 60mm Nylon Caster Wheels (60mm PU castor) | B23: FBA75970 | C23: 8904422501997 | D23: Nexlev | E23: B0BGY6R2YQ | F23: NC-60 | G23: Nexlev 60mm Nylon Caster Wheels (60mm PU castor) | H23: 60mm PU castor | K23: 1499 | L23: 94019900 | M23: 0.18 | N23: 35 | P23: 1.3 | Q23: 148.152 | R23: 0.65 | S23: 8 | T23: 8 | U23: 27 | V23: =S23*T23*U23/5000 -> 0.3456 | Y23: 98
A24: Nexlev Gaming Chair Gaslift 80mm | B24: FBA76595 | D24: Nexlev | F24: GL-80 | G24: Nexlev Gaming Chair Gaslift 80mm | H24: 80mm Gaslift | L24: 94019900 | M24: 0.18 | P24: 2.4 | Q24: 260 | R24: 0.8 | S24: 6 | T24: 6 | U24: 30 | V24: =S24*T24*U24/5000 -> 0.216

Sheet Margin Calculation
D1: Primary Channel | E1: Status | F1: SKU | G1: ASIN | H1: Model | I1: Category L1 | J1: Category L2 | K1: Supplier Model | L1: OEM Name | M1: Description | N1: HSN Code | O1: Gross Weight | P1: L | Q1: W | R1: H | S1: CBM/Unit | T1: Vol. Weight | U1: FOB (USD) | V1: Latest FOB | W1: Freight+Clearance | X1: Duty and Surcharge | Y1: DP | Z1: NLC | AA1: Referral Fee | AB1: Fixed Closing Fee | AC1: Fulfillment Fees | AD1: Total FBA Fee | AE1: AMS | AF1: Coupon | AG1: Returns Loss | AH1: SMM | AI1: 18% GST in SP | AJ1: Business overhead expenses | AK1: Cost of finance | AL1: Margin | AM1: Margin% | AN1: BAU Deal SP | AO1: Other Charges | AP1: Juiter SP | AQ1: inventory | AR1: MRP (4X of nlc) | AS1: Min Price | AT1: Max Price | AU1: Updated MRP | AV1: Gross Margin | AW1: Gross Margin % | AX1: EAN | AY1: Landed $ Rate | AZ1: Factor on landing | BA1: Factor on FOB | BB1: Rating | BC1: No of Reviews
F2: FBA75664 | G2: B0B5HCTGN5 | H2: FD-22-BK | I2: Gaming | L2: Anji Bitai | M2: Nexlev Falcon Series Gaming Chair with Premium Fabric & Vegan Leather, Memory Foam Neckrest & Lumbar Cushion, 3D Armrests, Sturdy Nylon Base, Butterfly Mechanism, & Class 4 Gaslift (Black, FD-22-BK) | O2: 21 | P2: 67 | Q2: 33 | R2: 87 | S2: =(P2*Q2*R2)/1000000 -> 0.192357 | T2: =(P2*Q2*R2)/5000 -> 38.4714 | U2: 36 | W2: =B$27/(B$28/S2) -> 5.6575588 | X2: =(U2+W2)*(B$30+(B$30*B$45)) -> 11.455829 | Y2: =(U2+W2+X2)*B$26 -> 4780.2049 | Z2: =Y2*1.18 -> 5640.6418 | AA2: =AN2*IF(AN2<15001,B$64,B$65) -> 1499.85 | AB2: 47 | AC2: 750 | AD2: =AA2+AB2+AC2 -> 2296.85 | AE2: =AN2*B$66 -> 1499.85 | AF2: =AN2*$B$70 -> 199.98 | AG2: =AN2*B$67 -> 499.95 | AH2: =AN2*$B$74 -> 199.98 | AI2: =AN2-(AN2/1.18) -> 1525.2712 | AJ2: =Z2*5% -> 282.03209 | AK2: =Z2*3% -> 169.21925 | AL2: =AN2-Y2-AD2-AE2-AG2-AI2-AJ2-AK2-AF2-AH2 -> -1454.3374 | AM2: =AL2/AN2 -> -0.14544828 | AN2: 9999 | AR2: 24999 | AV2: =SUM(AN2-AI2)-Y2 -> 3693.5239 | AW2: =AV2/AN2 -> 0.36938933 | AY2: =Y2/U2 -> 132.78347 | AZ2: =AN2/+SUM(Y2/84) -> 175.70711 | BA2: =AN2/U2 -> 277.75
F3: FBA75665 | G3: B0B5HCG8MM | H3: FD-22-RD | I3: Gaming | L3: Anji Bitai | M3: Nexlev Falcon Series Gaming Chair with Premium Fabric & Vegan Leather, Memory Foam Neckrest & Lumbar Cushion, 3D Armrests, Sturdy Nylon Base, Butterfly Mechanism, & Class 4 Gaslift (Red, FD-22-RD) | O3: 21 | P3: 67 | Q3: 33 | R3: 87 | S3: =(P3*Q3*R3)/1000000 -> 0.192357 | T3: =(P3*Q3*R3)/5000 -> 38.4714 | U3: 60.75 | W3: =B$27/(B$28/S3) -> 5.6575588 | X3: =(U3+W3)*(B$30+(B$30*B$45)) -> 18.262079 | Y3: =(U3+W3+X3)*B$26 -> 7620.2674 | Z3: =Y3*1.18 -> 8991.9155 | AA3: =AN3*IF(AN3<15001,B$64,B$65) -> 1509.9 | AB3: 47 | AC3: 750 | AD3: =AA3+AB3+AC3 -> 2306.9 | AE3: =AN3*B$66 -> 2264.85 | AF3: =AN3*$B$70 -> 301.98 | AG3: =AN3*B$67 -> 754.95 | AH3: =AN3*$B$74 -> 301.98 | AI3: =AN3-(AN3/1.18) -> 2303.2373 | AJ3: =Z3*5% -> 449.59578 | AK3: =Z3*3% -> 269.75747 | AL3: =AN3-Y3-AD3-AE3-AG3-AI3-AJ3-AK3-AF3-AH3 -> -1474.5179 | AM3: =AL3/AN3 -> -0.09765666 | AN3: 15099 | AR3: 24999 | AV3: =SUM(AN3-AI3)-Y3 -> 5175.4953 | AW3: =AV3/AN3 -> 0.34277074 | AY3: =Y3/U3 -> 125.4365 | AZ3: =AN3/+SUM(Y3/84) -> 166.43983 | BA3: =AN3/U3 -> 248.54321
F4: FBA75666 | G4: B0B5HB1HJH | H4: MF-22-BK | I4: Gaming | L4: Anji Bitai | M4: Nexlev Maverick Series Gaming Chair with Premium Fabric Upholstery, Memory Foam Lumbar Cushion, 4D Armrests, Heavy Duty Metal Base, Frog Mechanism, & Class 4 Gaslift (Black, MF-22-BK) | O4: 24 | P4: 83 | Q4: 65 | R4: 37 | S4: =(P4*Q4*R4)/1000000 -> 0.199615 | T4: =(P4*Q4*R4)/5000 -> 39.923 | U4: 76.5 | W4: =B$27/(B$28/S4) -> 5.8710294 | X4: =(U4+W4)*(B$30+(B$30*B$45)) -> 22.652033 | Y4: =(U4+W4+X4)*B$26 -> 9452.0756 | Z4: =Y4*1.18 -> 11153.449 | AA4: =AN4*IF(AN4<15001,B$64,B$65) -> 1699.9 | AB4: 47 | AC4: 750 | AD4: =AA4+AB4+AC4 -> 2496.9 | AE4: =AN4*B$66 -> 2549.85 | AF4: =AN4*$B$70 -> 339.98 | AG4: =AN4*B$67 -> 849.95 | AH4: =AN4*$B$74 -> 339.98 | AI4: =AN4-(AN4/1.18) -> 2593.0678 | AJ4: =Z4*5% -> 557.67246 | AK4: =Z4*3% -> 334.60348 | AL4: =AN4-Y4-AD4-AE4-AG4-AI4-AJ4-AK4-AF4-AH4 -> -2515.0794 | AM4: =AL4/AN4 -> -0.14795455 | AN4: 16999 | AR4: 29999 | AV4: =SUM(AN4-AI4)-Y4 -> 4953.8566 | AW4: =AV4/AN4 -> 0.29142047 | AY4: =Y4/U4 -> 123.55654 | AZ4: =AN4/+SUM(Y4/84) -> 151.06904 | BA4: =AN4/U4 -> 222.20915
F5: FBA75667 | G5: B0B5HFGQGM | H5: MF-22-RD | I5: Gaming | L5: Anji Bitai | M5: Nexlev Maverick Series Gaming Chair with Premium Fabric Upholstery, Memory Foam Lumbar Cushion, 4D Armrests, Heavy Duty Metal Base, Frog Mechanism, & Class 4 Gaslift (Red & Black, MF-22-RD) | O5: 24 | P5: 83 | Q5: 65 | R5: 37 | S5: =(P5*Q5*R5)/1000000 -> 0.199615 | T5: =(P5*Q5*R5)/5000 -> 39.923 | U5: 81.35 | W5: =B$27/(B$28/S5) -> 5.8710294 | X5: =(U5+W5)*(B$30+(B$30*B$45)) -> 23.985783 | Y5: =(U5+W5+X5)*B$26 -> 10008.613 | Z5: =Y5*1.18 -> 11810.163 | AA5: =AN5*IF(AN5<15001,B$64,B$65) -> 1699.9 | AB5: 47 | AC5: 750 | AD5: =AA5+AB5+AC5 -> 2496.9 | AE5: =AN5*B$66 -> 2549.85 | AF5: =AN5*$B$70 -> 339.98 | AG5: =AN5*B$67 -> 849.95 | AH5: =AN5*$B$74 -> 339.98 | AI5: =AN5-(AN5/1.18) -> 2593.0678 | AJ5: =Z5*5% -> 590.50817 | AK5: =Z5*3% -> 354.3049 | AL5: =AN5-Y5-AD5-AE5-AG5-AI5-AJ5-AK5-AF5-AH5 -> -3124.154 | AM5: =AL5/AN5 -> -0.18378458 | AN5: 16999 | AR5: 29999 | AV5: =SUM(AN5-AI5)-Y5 -> 4397.3191 | AW5: =AV5/AN5 -> 0.25868104 | AY5: =Y5/U5 -> 123.03151 | AZ5: =AN5/+SUM(Y5/84) -> 142.66872 | BA5: =AN5/U5 -> 208.96128
F6: FBA75668 | G6: B0B5F78LMB | H6: MF-22-BL | I6: Gaming | L6: Anji Bitai | M6: Nexlev Maverick Series Gaming Chair with Premium Fabric, Molded Foam Seat & Back, Memory Foam Lumbar Cushion, 4D Armrests, Sturdy Metal Base, Frog Mechanism, & Class 4 Gaslift (Blue, MF-22-BL) | O6: 24 | P6: 83 | Q6: 65 | R6: 37 | S6: =(P6*Q6*R6)/1000000 -> 0.199615 | T6: =(P6*Q6*R6)/5000 -> 39.923 | U6: 81.35 | W6: =B$27/(B$28/S6) -> 5.8710294 | X6: =(U6+W6)*(B$30+(B$30*B$45)) -> 23.985783 | Y6: =(U6+W6+X6)*B$26 -> 10008.613 | Z6: =Y6*1.18 -> 11810.163 | AA6: =AN6*IF(AN6<15001,B$64,B$65) -> 1699.9 | AB6: 47 | AC6: 750 | AD6: =AA6+AB6+AC6 -> 2496.9 | AE6: =AN6*B$66 -> 2549.85 | AF6: =AN6*$B$70 -> 339.98 | AG6: =AN6*B$67 -> 849.95 | AH6: =AN6*$B$74 -> 339.98 | AI6: =AN6-(AN6/1.18) -> 2593.0678 | AJ6: =Z6*5% -> 590.50817 | AK6: =Z6*3% -> 354.3049 | AL6: =AN6-Y6-AD6-AE6-AG6-AI6-AJ6-AK6-AF6-AH6 -> -3124.154 | AM6: =AL6/AN6 -> -0.18378458 | AN6: 16999 | AR6: 29999 | AV6: =SUM(AN6-AI6)-Y6 -> 4397.3191 | AW6: =AV6/AN6 -> 0.25868104 | AY6: =Y6/U6 -> 123.03151 | AZ6: =AN6/+SUM(Y6/84) -> 142.66872 | BA6: =AN6/U6 -> 208.96128
F7: FBA75669 | G7: B0B5HFG6W7 | H7: ML-22-BK | I7: Gaming | L7: Anji Bitai | M7: Nexlev Maverick Series Gaming Chair with Premium Vegan Leather Upholstery, Memory Foam Lumbar Cushion, 4D Armrests, Sturdy Metal Base, Frog Mechanism, and Class 4 Gaslift (Black, ML-22-BK) | O7: 24 | P7: 83 | Q7: 65 | R7: 37 | S7: =(P7*Q7*R7)/1000000 -> 0.199615 | T7: =(P7*Q7*R7)/5000 -> 39.923 | U7: 81.35 | W7: =B$27/(B$28/S7) -> 5.8710294 | X7: =(U7+W7)*(B$30+(B$30*B$45)) -> 23.985783 | Y7: =(U7+W7+X7)*B$26 -> 10008.613 | Z7: =Y7*1.18 -> 11810.163 | AA7: =AN7*IF(AN7<15001,B$64,B$65) -> 1699.9 | AB7: 47 | AC7: 750 | AD7: =AA7+AB7+AC7 -> 2496.9 | AE7: =AN7*B$66 -> 2549.85 | AF7: =AN7*$B$70 -> 339.98 | AG7: =AN7*B$67 -> 849.95 | AH7: =AN7*$B$74 -> 339.98 | AI7: =AN7-(AN7/1.18) -> 2593.0678 | AJ7: =Z7*5% -> 590.50817 | AK7: =Z7*3% -> 354.3049 | AL7: =AN7-Y7-AD7-AE7-AG7-AI7-AJ7-AK7-AF7-AH7 -> -3124.154 | AM7: =AL7/AN7 -> -0.18378458 | AN7: 16999 | AR7: 29999 | AV7: =SUM(AN7-AI7)-Y7 -> 4397.3191 | AW7: =AV7/AN7 -> 0.25868104 | AY7: =Y7/U7 -> 123.03151 | AZ7: =AN7/+SUM(Y7/84) -> 142.66872 | BA7: =AN7/U7 -> 208.96128
F8: FBA75670 | G8: B0B5HDPTLC | H8: ML-22-RD | I8: Gaming | L8: Anji Bitai | M8: Nexlev Maverick Series Gaming Chair with Premium Vegan Leather Upholstery, Memory Foam Lumbar Cushion, 4D Armrests, Sturdy Metal Base, Frog Mechanism, and Class 4 Gaslift (Red & Black, ML-22-RD) | O8: 24 | P8: 83 | Q8: 65 | R8: 37 | S8: =(P8*Q8*R8)/1000000 -> 0.199615 | T8: =(P8*Q8*R8)/5000 -> 39.923 | U8: 81.35 | W8: =B$27/(B$28/S8) -> 5.8710294 | X8: =(U8+W8)*(B$30+(B$30*B$45)) -> 23.985783 | Y8: =(U8+W8+X8)*B$26 -> 10008.613 | Z8: =Y8*1.18 -> 11810.163 | AA8: =AN8*IF(AN8<15001,B$64,B$65) -> 1699.9 | AB8: 47 | AC8: 750 | AD8: =AA8+AB8+AC8 -> 2496.9 | AE8: =AN8*B$66 -> 2549.85 | AF8: =AN8*$B$70 -> 339.98 | AG8: =AN8*B$67 -> 849.95 | AH8: =AN8*$B$74 -> 339.98 | AI8: =AN8-(AN8/1.18) -> 2593.0678 | AJ8: =Z8*5% -> 590.50817 | AK8: =Z8*3% -> 354.3049 | AL8: =AN8-Y8-AD8-AE8-AG8-AI8-AJ8-AK8-AF8-AH8 -> -3124.154 | AM8: =AL8/AN8 -> -0.18378458 | AN8: 16999 | AR8: 29999 | AV8: =SUM(AN8-AI8)-Y8 -> 4397.3191 | AW8: =AV8/AN8 -> 0.25868104 | AY8: =Y8/U8 -> 123.03151 | AZ8: =AN8/+SUM(Y8/84) -> 142.66872 | BA8: =AN8/U8 -> 208.96128
F9: FBA75671 | G9: B0B5HCN3TJ | H9: C-04 | I9: Gaming | L9: Anji Bitai | M9: Nexlev Maverick Series Gaming Chair with Premium Vegan Leather Upholstery, Memory Foam Lumbar Cushion, 4D Armrests, Sturdy Metal Base, Frog Mechanism, and Class 4 Gaslift (Blue and Black, ML-22-BL) | O9: 24 | P9: 83 | Q9: 65 | R9: 37 | S9: =(P9*Q9*R9)/1000000 -> 0.199615 | T9: =(P9*Q9*R9)/5000 -> 39.923 | U9: 81.35 | W9: =B$27/(B$28/S9) -> 5.8710294 | X9: =(U9+W9)*(B$30+(B$30*B$45)) -> 23.985783 | Y9: =(U9+W9+X9)*B$26 -> 10008.613 | Z9: =Y9*1.18 -> 11810.163 | AA9: =AN9*IF(AN9<15001,B$64,B$65) -> 1699.9 | AB9: 47 | AC9: 750 | AD9: =AA9+AB9+AC9 -> 2496.9 | AE9: =AN9*B$66 -> 2549.85 | AF9: =AN9*$B$70 -> 339.98 | AG9: =AN9*B$67 -> 849.95 | AH9: =AN9*$B$74 -> 339.98 | AI9: =AN9-(AN9/1.18) -> 2593.0678 | AJ9: =Z9*5% -> 590.50817 | AK9: =Z9*3% -> 354.3049 | AL9: =AN9-Y9-AD9-AE9-AG9-AI9-AJ9-AK9-AF9-AH9 -> -3124.154 | AM9: =AL9/AN9 -> -0.18378458 | AN9: 16999 | AR9: 29999 | AV9: =SUM(AN9-AI9)-Y9 -> 4397.3191 | AW9: =AV9/AN9 -> 0.25868104 | AY9: =Y9/U9 -> 123.03151 | AZ9: =AN9/+SUM(Y9/84) -> 142.66872 | BA9: =AN9/U9 -> 208.96128
F10: FBA75955 | G10: B0B5LM1FWP | H10: CM-22 | I10: Gaming | L10: Anji Bitai | M10: Nexlev USB Condenser Microphone Kit With Tripod For Gaming, Streaming & Meeting, Plug & Play, 2-In-1 Cable For Windows, MAC & PS4/5, No-Latency Monitoring, One Button Mute & Volume Control (CM-22) | O10: 0.77 | P10: 24 | Q10: 17 | R10: 11 | S10: =(P10*Q10*R10)/1000000 -> 0.004488 | T10: =(P10*Q10*R10)/5000 -> 0.8976 | U10: 20 | W10: =B$27/(B$28/S10) -> 0.132 | X10: =(U10+W10)*(0.15+(0.15*B$45)) -> 3.32178 | Y10: =(U10+W10+X10)*B$26 -> 2110.8402 | Z10: =Y10*1.18 -> 2490.7914 | AA10: =AN10*IF(AN10<15001,B$64,B$65) -> 524.85 | AB10: 47 | AC10: 131 | AD10: =AA10+AB10+AC10 -> 702.85 | AE10: =AN10*B$66 -> 524.85 | AF10: =AN10*$B$70 -> 69.98 | AG10: =AN10*B$67 -> 174.95 | AH10: =AN10*$B$74 -> 69.98 | AI10: =AN10-(AN10/1.18) -> 533.74576 | AJ10: =Z10*5% -> 124.53957 | AK10: =Z10*3% -> 74.723743 | AL10: =AN10-Y10-AD10-AE10-AG10-AI10-AJ10-AK10-AF10-AH10 -> -887.45928 | AM10: =AL10/AN10 -> -0.25363226 | AN10: 3499 | AR10: 9999 | AV10: =SUM(AN10-AI10)-Y10 -> 854.41404 | AW10: =AV10/AN10 -> 0.24418806 | AY10: =Y10/U10 -> 105.54201 | AZ10: =AN10/+SUM(Y10/84) -> 139.24124 | BA10: =AN10/U10 -> 174.95
F11: FBA75956 | G11: B0B5LL2ZQR | H11: CM-22 Pro | I11: Gaming | L11: Anji Bitai | M11: Nexlev USB Condenser Microphone for YouTube,Gaming, Meeting & Recording on Mac OS,Windows & PS 4/5 with Pop Filter, Shock Mount & Tripod, No Latency Monitoring,Volume Control & Mute Button(CM-22 PRO) | O11: 0.91 | P11: 26 | Q11: 14 | R11: 11 | S11: =(P11*Q11*R11)/1000000 -> 0.004004 | T11: =(P11*Q11*R11)/5000 -> 0.8008 | U11: 25 | W11: =B$27/(B$28/S11) -> 0.11776471 | X11: =(U11+W11)*(0.15+(0.15*B$45)) -> 4.1444312 | Y11: =(U11+W11+X11)*B$26 -> 2633.5976 | Z11: =Y11*1.18 -> 3107.6452 | AA11: =AN11*IF(AN11<15001,B$64,B$65) -> 644.85 | AB11: 47 | AC11: 98 | AD11: =AA11+AB11+AC11 -> 789.85 | AE11: =AN11*B$66 -> 644.85 | AF11: =AN11*$B$70 -> 85.98 | AG11: =AN11*B$67 -> 214.95 | AH11: =AN11*$B$74 -> 85.98 | AI11: =AN11-(AN11/1.18) -> 655.77966 | AJ11: =Z11*5% -> 155.38226 | AK11: =Z11*3% -> 93.229356 | AL11: =AN11-Y11-AD11-AE11-AG11-AI11-AJ11-AK11-AF11-AH11 -> -1060.5989 | AM11: =AL11/AN11 -> -0.24670828 | AN11: 4299 | AR11: 11999 | AV11: =SUM(AN11-AI11)-Y11 -> 1009.6227 | AW11: =AV11/AN11 -> 0.2348506 | AY11: =Y11/U11 -> 105.34391 | AZ11: =AN11/+SUM(Y11/84) -> 137.1189 | BA11: =AN11/U11 -> 171.96
F12: FBA75963 | G12: B0B71QN43M | H12: FD-22-FR | I12: Gaming | L12: Anji Bitai | M12: Nexlev Falcon Series Footrest with Premium Fabric and Vegan Leather Upholstery (Black) | O12: 5.7 | P12: 54 | Q12: 18 | R12: 51 | S12: =(P12*Q12*R12)/1000000 -> 0.049572 | T12: =(P12*Q12*R12)/5000 -> 9.9144 | U12: 12.5 | W12: =B$27/(B$28/S12) -> 1.458 | X12: =(U12+W12)*(B$30+(B$30*B$45)) -> 3.83845 | Y12: =(U12+W12+X12)*B$26 -> 1601.6805 | Z12: =Y12*1.18 -> 1889.983 | AA12: =AN12*IF(AN12<15001,B$64,B$65) -> 449.85 | AB12: 47 | AC12: 156 | AD12: =AA12+AB12+AC12 -> 652.85 | AE12: =AN12*B$66 -> 449.85 | AF12: =AN12*$B$70 -> 59.98 | AG12: =AN12*B$67 -> 149.95 | AH12: =AN12*$B$74 -> 59.98 | AI12: =AN12-(AN12/1.18) -> 457.47458 | AJ12: =Z12*5% -> 94.499149 | AK12: =Z12*3% -> 56.69949 | AL12: =AN12-Y12-AD12-AE12-AG12-AI12-AJ12-AK12-AF12-AH12 -> -583.96372 | AM12: =AL12/AN12 -> -0.19471948 | AN12: 2999 | AR12: 6999 | AV12: =SUM(AN12-AI12)-Y12 -> 939.84492 | AW12: =AV12/AN12 -> 0.3133861 | AY12: =Y12/U12 -> 128.13444 | AZ12: =AN12/+SUM(Y12/84) -> 157.2823 | BA12: =AN12/U12 -> 239.92
F13: FBA75964 | G13: B0B71QY1TH | H13: ML-22-FR | I13: Gaming | L13: Anji Bitai | M13: Nexlev Maverick Series Footrest with Vegan Leather Upholstery (Black) | O13: 5.7 | P13: 54 | Q13: 18 | R13: 51 | S13: =(P13*Q13*R13)/1000000 -> 0.049572 | T13: =(P13*Q13*R13)/5000 -> 9.9144 | U13: 12.5 | W13: =B$27/(B$28/S13) -> 1.458 | X13: =(U13+W13)*(B$30+(B$30*B$45)) -> 3.83845 | Y13: =(U13+W13+X13)*B$26 -> 1601.6805 | Z13: =Y13*1.18 -> 1889.983 | AA13: =AN13*IF(AN13<15001,B$64,B$65) -> 449.85 | AB13: 47 | AC13: 202 | AD13: =AA13+AB13+AC13 -> 698.85 | AE13: =AN13*B$66 -> 449.85 | AF13: =AN13*$B$70 -> 59.98 | AG13: =AN13*B$67 -> 149.95 | AH13: =AN13*$B$74 -> 59.98 | AI13: =AN13-(AN13/1.18) -> 457.47458 | AJ13: =Z13*5% -> 94.499149 | AK13: =Z13*3% -> 56.69949 | AL13: =AN13-Y13-AD13-AE13-AG13-AI13-AJ13-AK13-AF13-AH13 -> -629.96372 | AM13: =AL13/AN13 -> -0.21005792 | AN13: 2999 | AR13: 6999 | AV13: =SUM(AN13-AI13)-Y13 -> 939.84492 | AW13: =AV13/AN13 -> 0.3133861 | AY13: =Y13/U13 -> 128.13444 | AZ13: =AN13/+SUM(Y13/84) -> 157.2823 | BA13: =AN13/U13 -> 239.92
F14: FBA75967 | G14: B0BC93W1V1 | H14: AB-350 | I14: Gaming | L14: Anji Bitai | M14: Nexlev 350mm Heavy Duty Aluminium Base | O14: 2.5 | P14: 67 | Q14: 10 | R14: 65 | S14: =(P14*Q14*R14)/1000000 -> 0.04355 | T14: =(P14*Q14*R14)/5000 -> 8.71 | U14: 11.8 | W14: =B$27/(B$28/S14) -> 1.2808824 | X14: =(U14+W14)*(B$30+(B$30*B$45)) -> 3.5972426 | Y14: =(U14+W14+X14)*B$26 -> 1501.0313 | Z14: =Y14*1.18 -> 1771.2169 | AA14: =AN14*IF(AN14<15001,B$64,B$65) -> 524.85 | AB14: 47 | AC14: 278 | AD14: =AA14+AB14+AC14 -> 849.85 | AE14: =AN14*B$66 -> 524.85 | AF14: =AN14*$B$70 -> 69.98 | AG14: =AN14*B$67 -> 174.95 | AH14: =AN14*$B$74 -> 69.98 | AI14: =AN14-(AN14/1.18) -> 533.74576 | AJ14: =Z14*5% -> 88.560844 | AK14: =Z14*3% -> 53.136506 | AL14: =AN14-Y14-AD14-AE14-AG14-AI14-AJ14-AK14-AF14-AH14 -> -367.08436 | AM14: =AL14/AN14 -> -0.10491122 | AN14: 3499 | AR14: 6399 | AV14: =SUM(AN14-AI14)-Y14 -> 1464.223 | AW14: =AV14/AN14 -> 0.41846899 | AY14: =Y14/U14 -> 127.20604 | AZ14: =AN14/+SUM(Y14/84) -> 195.80938 | BA14: =AN14/U14 -> 296.52542
F15: FBA75968 | G15: B0BC99CYXD | H15: MB-350 | I15: Gaming | L15: Anji Bitai | M15: Nexlev 350mm Heavy Duty Metal Base | O15: 3.1 | P15: 67 | Q15: 10 | R15: 65 | S15: =(P15*Q15*R15)/1000000 -> 0.04355 | T15: =(P15*Q15*R15)/5000 -> 8.71 | U15: 5.9 | W15: =B$27/(B$28/S15) -> 1.2808824 | X15: =(U15+W15)*(B$30+(B$30*B$45)) -> 1.9747426 | Y15: =(U15+W15+X15)*B$26 -> 824.00625 | Z15: =Y15*1.18 -> 972.32737 | AA15: =AN15*IF(AN15<15001,B$64,B$65) -> 374.85 | AB15: 47 | AC15: 278 | AD15: =AA15+AB15+AC15 -> 699.85 | AE15: =AN15*B$66 -> 374.85 | AF15: =AN15*$B$70 -> 49.98 | AG15: =AN15*B$67 -> 124.95 | AH15: =AN15*$B$74 -> 49.98 | AI15: =AN15-(AN15/1.18) -> 381.20339 | AJ15: =Z15*5% -> 48.616369 | AK15: =Z15*3% -> 29.169821 | AL15: =AN15-Y15-AD15-AE15-AG15-AI15-AJ15-AK15-AF15-AH15 -> -83.60583 | AM15: =AL15/AN15 -> -0.033455714 | AN15: 2499 | AR15: 3999 | AV15: =SUM(AN15-AI15)-Y15 -> 1293.7904 | AW15: =AV15/AN15 -> 0.51772323 | AY15: =Y15/U15 -> 139.66208 | AZ15: =AN15/+SUM(Y15/84) -> 254.75049 | BA15: =AN15/U15 -> 423.55932
F16: FBA75969 | G16: B0BC93RS1L | H16: NB-350 | I16: Gaming | L16: Anji Bitai | M16: Nexlev 350mm Heavy Duty Base | O16: 2.65 | P16: 67 | Q16: 10 | R16: 65 | S16: =(P16*Q16*R16)/1000000 -> 0.04355 | T16: =(P16*Q16*R16)/5000 -> 8.71 | U16: 3.7 | W16: =B$27/(B$28/S16) -> 1.2808824 | X16: =(U16+W16)*(B$30+(B$30*B$45)) -> 1.3697426 | Y16: =(U16+W16+X16)*B$26 -> 571.55625 | Z16: =Y16*1.18 -> 674.43637 | AA16: =AN16*IF(AN16<15001,B$64,B$65) -> 299.85 | AB16: 47 | AC16: 294 | AD16: =AA16+AB16+AC16 -> 640.85 | AE16: =AN16*B$66 -> 299.85 | AF16: =AN16*$B$70 -> 39.98 | AG16: =AN16*B$67 -> 99.95 | AH16: =AN16*$B$74 -> 39.98 | AI16: =AN16-(AN16/1.18) -> 304.9322 | AJ16: =Z16*5% -> 33.721819 | AK16: =Z16*3% -> 20.233091 | AL16: =AN16-Y16-AD16-AE16-AG16-AI16-AJ16-AK16-AF16-AH16 -> -52.053363 | AM16: =AL16/AN16 -> -0.026039702 | AN16: 1999 | AR16: 2499 | AV16: =SUM(AN16-AI16)-Y16 -> 1122.5115 | AW16: =AV16/AN16 -> 0.56153654 | AY16: =Y16/U16 -> 154.47466 | AZ16: =AN16/+SUM(Y16/84) -> 293.78736 | BA16: =AN16/U16 -> 540.27027
F17: FBA75965 | G17: B0BGXYD1ZP | H17: AR-4D | I17: Gaming | L17: Anji Bitai | M17: The 4D Armrest is adjustable in four dimensions. You can adjust them in height, forward/backward position, left/right as well as rotate them around their axis. | O17: 3.5 | P17: 25 | Q17: 29 | R17: 33 | S17: =(P17*Q17*R17)/1000000 -> 0.023925 | T17: =(P17*Q17*R17)/5000 -> 4.785 | U17: 10 | W17: =B$27/(B$28/S17) -> 0.70367647 | X17: =(U17+W17)*(B$30+(B$30*B$45)) -> 2.943511 | Y17: =(U17+W17+X17)*B$26 -> 1228.2469 | Z17: =Y17*1.18 -> 1449.3313 | AA17: =AN17*IF(AN17<15001,B$64,B$65) -> 419.85 | AB17: 47 | AC17: 262 | AD17: =AA17+AB17+AC17 -> 728.85 | AE17: =AN17*B$66 -> 419.85 | AF17: =AN17*$B$70 -> 55.98 | AG17: =AN17*B$67 -> 139.95 | AH17: =AN17*$B$74 -> 55.98 | AI17: =AN17-(AN17/1.18) -> 426.9661 | AJ17: =Z17*5% -> 72.466566 | AK17: =Z17*3% -> 43.479939 | AL17: =AN17-Y17-AD17-AE17-AG17-AI17-AJ17-AK17-AF17-AH17 -> -372.76948 | AM17: =AL17/AN17 -> -0.13317952 | AN17: 2799 | AR17: 5499 | AV17: =SUM(AN17-AI17)-Y17 -> 1143.787 | AW17: =AV17/AN17 -> 0.40864131 | AY17: =Y17/U17 -> 122.82469 | AZ17: =AN17/+SUM(Y17/84) -> 191.42406 | BA17: =AN17/U17 -> 279.9
F18: FBA75966 | G18: B0BGXZB3CM | H18: AR-3D | I18: Gaming | L18: Anji Bitai | M18: 3D Armrests can be adjusted in height, forward/backward position as well as can be rotated around their axis | O18: 2.9 | P18: 25 | Q18: 29 | R18: 33 | S18: =(P18*Q18*R18)/1000000 -> 0.023925 | T18: =(P18*Q18*R18)/5000 -> 4.785 | U18: 7.9 | W18: =B$27/(B$28/S18) -> 0.70367647 | X18: =(U18+W18)*(B$30+(B$30*B$45)) -> 2.366011 | Y18: =(U18+W18+X18)*B$26 -> 987.27187 | Z18: =Y18*1.18 -> 1164.9808 | AA18: =AN18*IF(AN18<15001,B$64,B$65) -> 344.85 | AB18: 47 | AC18: 181.1 | AD18: =AA18+AB18+AC18 -> 572.95 | AE18: =AN18*B$66 -> 344.85 | AF18: =AN18*$B$70 -> 45.98 | AG18: =AN18*B$67 -> 114.95 | AH18: =AN18*$B$74 -> 45.98 | AI18: =AN18-(AN18/1.18) -> 350.69492 | AJ18: =Z18*5% -> 58.249041 | AK18: =Z18*3% -> 34.949424 | AL18: =AN18-Y18-AD18-AE18-AG18-AI18-AJ18-AK18-AF18-AH18 -> -256.87526 | AM18: =AL18/AN18 -> -0.11173347 | AN18: 2299 | AR18: 4599 | AV18: =SUM(AN18-AI18)-Y18 -> 961.03321 | AW18: =AV18/AN18 -> 0.41802227 | AY18: =Y18/U18 -> 124.97112 | AZ18: =AN18/+SUM(Y18/84) -> 195.60569 | BA18: =AN18/U18 -> 291.01266
F19: FBA75973 | G19: B0BGY2XKZ1 | H19: BM-01 | I19: Gaming | L19: Anji Bitai | M19: The butterfly tilt mechanism is actually an office chair tilt mechanism. Because its shape is like a butterfly with outstretched wings. People tend to use the butterfly tilt mechanism as its common name. | O19: 1.75 | P19: 29 | Q19: 23 | R19: 13 | S19: =(P19*Q19*R19)/1000000 -> 0.008671 | T19: =(P19*Q19*R19)/5000 -> 1.7342 | U19: 2.7 | W19: =B$27/(B$28/S19) -> 0.25502941 | X19: =(U19+W19)*(B$30+(B$30*B$45)) -> 0.81263309 | Y19: =(U19+W19+X19)*B$26 -> 339.08963 | Z19: =Y19*1.18 -> 400.12576 | AA19: =AN19*IF(AN19<15001,B$64,B$65) -> 239.85 | AB19: 47 | AC19: 197 | AD19: =AA19+AB19+AC19 -> 483.85 | AE19: =AN19*B$66 -> 239.85 | AF19: =AN19*$B$70 -> 31.98 | AG19: =AN19*B$67 -> 79.95 | AH19: =AN19*$B$74 -> 31.98 | AI19: =AN19-(AN19/1.18) -> 243.91525 | AJ19: =Z19*5% -> 20.006288 | AK19: =Z19*3% -> 12.003773 | AL19: =AN19-Y19-AD19-AE19-AG19-AI19-AJ19-AK19-AF19-AH19 -> 116.37506 | AM19: =AL19/AN19 -> 0.0727799 | AN19: 1599 | AR19: 2199 | AV19: =SUM(AN19-AI19)-Y19 -> 1015.9951 | AW19: =AV19/AN19 -> 0.63539407 | AY19: =Y19/U19 -> 125.58875 | AZ19: =AN19/+SUM(Y19/84) -> 396.10767 | BA19: =AN19/U19 -> 592.22222
F20: FBA75974 | G20: B0BGY4MLKX | H20: FM-01 | I20: Gaming | L20: Anji Bitai | M20: The Frog Tilt Mechanism adjusts the angle of the seat. This reduces the pressure on the lower back, ensures proper posture, and alleviates blood flow to the legs and feet. When a person sits on a chair with a frog mechanism and leans back, his feet will remain on the ground which makes it more comfortable. | O20: 3.9 | P20: 34 | Q20: 27 | R20: 20 | S20: =(P20*Q20*R20)/1000000 -> 0.01836 | T20: =(P20*Q20*R20)/5000 -> 3.672 | U20: 10.4 | W20: =B$27/(B$28/S20) -> 0.54 | X20: =(U20+W20)*(B$30+(B$30*B$45)) -> 3.0085 | Y20: =(U20+W20+X20)*B$26 -> 1255.365 | Z20: =Y20*1.18 -> 1481.3307 | AA20: =AN20*IF(AN20<15001,B$64,B$65) -> 419.85 | AB20: 47 | AC20: 230 | AD20: =AA20+AB20+AC20 -> 696.85 | AE20: =AN20*B$66 -> 419.85 | AF20: =AN20*$B$70 -> 55.98 | AG20: =AN20*B$67 -> 139.95 | AH20: =AN20*$B$74 -> 55.98 | AI20: =AN20-(AN20/1.18) -> 426.9661 | AJ20: =Z20*5% -> 74.066535 | AK20: =Z20*3% -> 44.439921 | AL20: =AN20-Y20-AD20-AE20-AG20-AI20-AJ20-AK20-AF20-AH20 -> -370.44756 | AM20: =AL20/AN20 -> -0.13234997 | AN20: 2799 | AR20: 5699 | AV20: =SUM(AN20-AI20)-Y20 -> 1116.6689 | AW20: =AV20/AN20 -> 0.3989528 | AY20: =Y20/U20 -> 120.70817 | AZ20: =AN20/+SUM(Y20/84) -> 187.28896 | BA20: =AN20/U20 -> 269.13462
F21: FBA75971 | G21: B0BGY3223L | H21: RC-75 | I21: Gaming | L21: Anji Bitai | M21: 75mm Racing Caster Wheels | O21: 1.15 | P21: 8 | Q21: 8 | R21: 27 | S21: =(P21*Q21*R21)/1000000 -> 0.001728 | T21: =(P21*Q21*R21)/5000 -> 0.3456 | U21: 3.6 | W21: =B$27/(B$28/S21) -> 0.050823529 | X21: =(U21+W21)*(B$30+(B$30*B$45)) -> 1.0039765 | Y21: =(U21+W21+X21)*B$26 -> 418.932 | Z21: =Y21*1.18 -> 494.33976 | AA21: =AN21*IF(AN21<15001,B$64,B$65) -> 164.85 | AB21: 47 | AC21: 131 | AD21: =AA21+AB21+AC21 -> 342.85 | AE21: =AN21*B$66 -> 164.85 | AF21: =AN21*$B$70 -> 21.98 | AG21: =AN21*B$67 -> 54.95 | AH21: =AN21*$B$74 -> 21.98 | AI21: =AN21-(AN21/1.18) -> 167.64407 | AJ21: =Z21*5% -> 24.716988 | AK21: =Z21*3% -> 14.830193 | AL21: =AN21-Y21-AD21-AE21-AG21-AI21-AJ21-AK21-AF21-AH21 -> -133.73325 | AM21: =AL21/AN21 -> -0.1216863 | AN21: 1099 | AR21: 2499 | AV21: =SUM(AN21-AI21)-Y21 -> 512.42393 | AW21: =AV21/AN21 -> 0.46626381 | AY21: =Y21/U21 -> 116.37 | AZ21: =AN21/+SUM(Y21/84) -> 220.36034 | BA21: =AN21/U21 -> 305.27778
F22: FBA75972 | G22: B0BGY61JMN | H22: RB-75 | I22: Gaming | L22: Anji Bitai | M22: In-Line Rollerblade Casters for Chair | O22: 1.25 | P22: 8 | Q22: 8 | R22: 27 | S22: =(P22*Q22*R22)/1000000 -> 0.001728 | T22: =(P22*Q22*R22)/5000 -> 0.3456 | U22: 6.5 | W22: =B$27/(B$28/S22) -> 0.050823529 | X22: =(U22+W22)*(B$30+(B$30*B$45)) -> 1.8014765 | Y22: =(U22+W22+X22)*B$26 -> 751.707 | Z22: =Y22*1.18 -> 887.01426 | AA22: =AN22*IF(AN22<15001,B$64,B$65) -> 239.85 | AB22: 47 | AC22: 131 | AD22: =AA22+AB22+AC22 -> 417.85 | AE22: =AN22*B$66 -> 239.85 | AF22: =AN22*$B$70 -> 31.98 | AG22: =AN22*B$67 -> 79.95 | AH22: =AN22*$B$74 -> 31.98 | AI22: =AN22-(AN22/1.18) -> 243.91525 | AJ22: =Z22*5% -> 44.350713 | AK22: =Z22*3% -> 26.610428 | AL22: =AN22-Y22-AD22-AE22-AG22-AI22-AJ22-AK22-AF22-AH22 -> -269.1934 | AM22: =AL22/AN22 -> -0.16835109 | AN22: 1599 | AR22: 3999 | AV22: =SUM(AN22-AI22)-Y22 -> 603.37775 | AW22: =AV22/AN22 -> 0.37734693 | AY22: =Y22/U22 -> 115.64723 | AZ22: =AN22/+SUM(Y22/84) -> 178.68132 | BA22: =AN22/U22 -> 246
F23: FBA75970 | G23: B0BGY6R2YQ | H23: NC-60 | I23: Gaming | L23: Anji Bitai | M23: 60mm Nylon Caster Wheels | O23: 0.65 | P23: 8 | Q23: 8 | R23: 27 | S23: =(P23*Q23*R23)/1000000 -> 0.001728 | T23: =(P23*Q23*R23)/5000 -> 0.3456 | U23: 1.3 | W23: =B$27/(B$28/S23) -> 0.050823529 | X23: =(U23+W23)*(B$30+(B$30*B$45)) -> 0.37147647 | Y23: =(U23+W23+X23)*B$26 -> 155.007 | Z23: =Y23*1.18 -> 182.90826 | AA23: =AN23*IF(AN23<15001,B$64,B$65) -> 104.85 | AB23: 47 | AC23: 98 | AD23: =AA23+AB23+AC23 -> 249.85 | AE23: =AN23*B$66 -> 104.85 | AF23: =AN23*$B$70 -> 13.98 | AG23: =AN23*B$67 -> 34.95 | AH23: =AN23*$B$74 -> 13.98 | AI23: =AN23-(AN23/1.18) -> 106.62712 | AJ23: =Z23*5% -> 9.145413 | AK23: =Z23*3% -> 5.4872478 | AL23: =AN23-Y23-AD23-AE23-AG23-AI23-AJ23-AK23-AF23-AH23 -> 5.1232206 | AM23: =AL23/AN23 -> 0.007329357 | AN23: 699 | AR23: 1499 | AV23: =SUM(AN23-AI23)-Y23 -> 437.36588 | AW23: =AV23/AN23 -> 0.62570226 | AY23: =Y23/U23 -> 119.23615 | AZ23: =AN23/+SUM(Y23/84) -> 378.7958 | BA23: =AN23/U23 -> 537.69231
F24: FBA76595 | G24: #N/A | H24: GL-80 | I24: Gaming | L24: ROTVAC ENTERPRISE | M24: 80mm Class 4 Gaslift | O24: 0.8 | P24: 6 | Q24: 6 | R24: 30 | S24: =(P24*Q24*R24)/1000000 -> 0.00108 | T24: =(P24*Q24*R24)/5000 -> 0.216 | U24: 2.4 | W24: =B$27/(B$28/S24) -> 0.031764706 | X24: =(U24+W24)*(B$30+(B$30*B$45)) -> 0.66873529 | Y24: =(U24+W24+X24)*B$26 -> 279.045 | Z24: =Y24*1.18 -> 329.2731 | AA24: =AN24*IF(AN24<15001,B$64,B$65) -> 119.85 | AB24: 47 | AC24: 125 | AD24: =AA24+AB24+AC24 -> 291.85 | AE24: =AN24*B$66 -> 119.85 | AF24: =AN24*$B$70 -> 15.98 | AG24: =AN24*B$67 -> 39.95 | AH24: =AN24*$B$74 -> 15.98 | AI24: =AN24-(AN24/1.18) -> 121.88136 | AJ24: =Z24*5% -> 16.463655 | AK24: =Z24*3% -> 9.878193 | AL24: =AN24-Y24-AD24-AE24-AG24-AI24-AJ24-AK24-AF24-AH24 -> -111.8782 | AM24: =AL24/AN24 -> -0.14002278 | AN24: 799 | AV24: =SUM(AN24-AI24)-Y24 -> 398.07364 | AW24: =AV24/AN24 -> 0.49821482 | AY24: =Y24/U24 -> 116.26875 | AZ24: =AN24/+SUM(Y24/84) -> 240.52035 | BA24: =AN24/U24 -> 332.91667
F25: FBA78979 | G25: B0CDPQXPC1 | H25: GS-01 | I25: Home & Kitchen | J25: Fabric Care | K25: QH09 | L25: Zhejiang Huaguang | M25: Nexlev Premium Garment Steamer-Mist | N25: 85167990 | O25: 1.3 | P25: 29.2 | Q25: 22.4 | R25: 13.6 | S25: =(P25*Q25*R25)/1000000 -> 0.008895488 | T25: =(P25*Q25*R25)/5000 -> 1.7790976 | U25: 11.68 | V25: 11.68 | W25: =B$27/(B$28/S25) -> 0.261632 | X25: =(U25+W25)*(B$31+(B$31*B$45)) -> 2.627159 | Y25: =(U25+W25+X25)*B$26 -> 1311.1912 | Z25: =Y25*1.18 -> 1547.2056 | AA25: =AN25*4.5% -> 103.455 | AB25: 51 | AC25: 115 | AD25: =AA25+AB25+AC25 -> 269.455 | AE25: =AN25*B$66 -> 344.85 | AF25: =AN25*$B$70 -> 45.98 | AG25: =AN25*B$67 -> 114.95 | AH25: =AN25*$B$74 -> 45.98 | AI25: =AN25-(AN25/1.18) -> 350.69492 | AJ25: =Z25*5% -> 77.36028 | AK25: =Z25*3% -> 46.416168 | AL25: =AN25-Y25-AD25-AE25-AG25-AI25-AJ25-AK25-AF25-AH25 -> -307.87756 | AM25: =AL25/AN25 -> -0.13391803 | AN25: 2299 | AP25: 2349 | AR25: 5999 | AV25: =SUM(AN25-AI25)-Y25 -> 637.11389 | AW25: =AV25/AN25 -> 0.27712653 | AX25: 8904422503366 | AY25: =Y25/U25 -> 112.25952 | AZ25: =AN25/+SUM(Y25/84) -> 147.28287 | BA25: =AN25/U25 -> 196.83219
A26: Dollar Conversion Rate | B26: 90 | F26: FBA78980 | G26: B0CDPMX152 | H26: GS-02 | I26: Home & Kitchen | J26: Fabric Care | K26: QH09E | L26: Zhejiang Huaguang | M26: Nexlev Garment Steamer - Swift | N26: 85167990 | O26: 1.3 | P26: 29.2 | Q26: 22.4 | R26: 13.6 | S26: =(P26*Q26*R26)/1000000 -> 0.008895488 | T26: =(P26*Q26*R26)/5000 -> 1.7790976 | U26: 9.45 | V26: 9.45 | W26: =B$27/(B$28/S26) -> 0.261632 | X26: =(U26+W26)*(B$31+(B$31*B$45)) -> 2.136559 | Y26: =(U26+W26+X26)*B$26 -> 1066.3372 | Z26: =Y26*1.18 -> 1258.2779 | AA26: =AN26*4.5% -> 92.25 | AB26: 51 | AC26: 115 | AD26: =AA26+AB26+AC26 -> 258.25 | AE26: =AN26*B$66 -> 307.5 | AF26: =AN26*$B$70 -> 41 | AG26: =AN26*B$67 -> 102.5 | AH26: =AN26*$B$74 -> 41 | AI26: =AN26-(AN26/1.18) -> 312.71186 | AJ26: =Z26*5% -> 62.913894 | AK26: =Z26*3% -> 37.748337 | AL26: =AN26-Y26-AD26-AE26-AG26-AI26-AJ26-AK26-AF26-AH26 -> -179.96129 | AM26: =AL26/AN26 -> -0.087785995 | AN26: 2050 | AP26: 2049 | AR26: 4999 | AV26: =SUM(AN26-AI26)-Y26 -> 670.95094 | AW26: =AV26/AN26 -> 0.32729314 | AX26: 8904422503373 | AY26: =Y26/U26 -> 112.83991 | AZ26: =AN26/+SUM(Y26/84) -> 161.48738 | BA26: =AN26/U26 -> 216.93122
A27: 40HQ Freight+Clearance | B27: 2000 | F27: FBA78981 | G27: B0CDPP45BM | H27: SC-01 | I27: Home & Kitchen | J27: Cleaning & Vacumming | K27: C5 | L27: Zhejiang Huaguang | M27: Nexlev Steam Cleaner | N27: 85098000 | O27: 2.1 | P27: 30 | Q27: 19.5 | R27: 21 | S27: =(P27*Q27*R27)/1000000 -> 0.012285 | T27: =(P27*Q27*R27)/5000 -> 2.457 | U27: 13.5 | V27: 13.4 | W27: =B$27/(B$28/S27) -> 0.36132353 | X27: =(U27+W27)*(B$31+(B$31*B$45)) -> 3.0494912 | Y27: =(U27+W27+X27)*B$26 -> 1521.9733 | Z27: =Y27*1.18 -> 1795.9285 | AA27: =AN27*4.5% -> 161.955 | AB27: 51 | AC27: 148 | AD27: =AA27+AB27+AC27 -> 360.955 | AE27: =AN27*B$66 -> 539.85 | AF27: =AN27*$B$70 -> 71.98 | AG27: =AN27*B$67 -> 179.95 | AH27: =AN27*$B$74 -> 71.98 | AI27: =AN27-(AN27/1.18) -> 549 | AJ27: =Z27*5% -> 89.796426 | AK27: =Z27*3% -> 53.877856 | AL27: =SUM(AN27-AI27)-Y27-AD27-AE27-AG27-AJ27-AK27-AF27-AH27 -> 159.63739 | AM27: =AL27/SUM(AN27-AI27) -> 0.052340129 | AN27: 3599 | AP27: 3299 | AR27: 9999 | AV27: =SUM(AN27-AI27)-Y27 -> 1528.0267 | AW27: =AV27/AN27 -> 0.42456979 | AX27: 8904422503380 | AY27: =Y27/U27 -> 112.73876 | AZ27: =AN27/+SUM(Y27/84) -> 198.63423 | BA27: =AN27/U27 -> 266.59259
A28: 40HQ Usable CBM | B28: 68 | F28: FBA78994 | G28: B0CDQ98FDM | H28: NP-01 | I28: Sports, Fitness & Outdoors | J28: Travel Accessories | L28: Guangzhou Jibei | M28: Neck Pillow with Memory Foam and Striped Texture | N28: 94043090 | O28: 0.3 | P28: 21.6 | Q28: 16.6 | R28: 13.9 | S28: =(P28*Q28*R28)/1000000 -> 0.004983984 | T28: =(P28*Q28*R28)/5000 -> 0.9967968 | U28: 2.95 | W28: =B$27/(B$28/S28) -> 0.14658776 | X28: =(U28+W28)*(B$30+(B$30*B$45)) -> 0.85156164 | Y28: =(U28+W28+X28)*B$26 -> 355.33345 | Z28: =Y28*1.12 -> 397.97346 | AA28: =AN28*10% -> 69.9 | AB28: 26 | AC28: 77 | AD28: =AA28+AB28+AC28 -> 172.9 | AE28: =AN28*B$66 -> 104.85 | AF28: =AN28*$B$70 -> 13.98 | AG28: =AN28*B$67 -> 34.95 | AH28: =AN28*$B$74 -> 13.98 | AI28: =AN28-(AN28/1.12) -> 74.892857 | AJ28: =Z28*5% -> 19.898673 | AK28: =Z28*3% -> 11.939204 | AL28: =AN28-Y28-AD28-AE28-AG28-AI28-AJ28-AK28-AF28-AH28 -> -103.72418 | AM28: =AL28/AN28 -> -0.14838938 | AN28: 699 | AP28: 679 | AR28: 1499 | AV28: =SUM(AN28-AI28)-Y28 -> 268.7737 | AW28: =AV28/AN28 -> 0.38451173 | AX28: 8904422503496 | AY28: =Y28/U28 -> 120.45202 | AZ28: =AN28/+SUM(Y28/84) -> 165.24197 | BA28: =AN28/U28 -> 236.94915
A29: Fulfillment Rate/kg | B29: 40 | F29: FBA78995 | G29: B0CDQ55W2M | H29: NP-02 | I29: Sports, Fitness & Outdoors | J29: Travel Accessories | L29: Guangzhou Jibei | M29: Neck Pillow with Memory Foam (Dark Grey) | N29: 94043090 | O29: 0.3 | P29: 21.6 | Q29: 16.6 | R29: 13.9 | S29: =(P29*Q29*R29)/1000000 -> 0.004983984 | T29: =(P29*Q29*R29)/5000 -> 0.9967968 | U29: 2.95 | W29: =B$27/(B$28/S29) -> 0.14658776 | X29: =(U29+W29)*(B$30+(B$30*B$45)) -> 0.85156164 | Y29: =(U29+W29+X29)*B$26 -> 355.33345 | Z29: =Y29*1.12 -> 397.97346 | AA29: =AN29*10% -> 69.9 | AB29: 25 | AC29: 78 | AD29: =AA29+AB29+AC29 -> 172.9 | AE29: =AN29*B$66 -> 104.85 | AF29: =AN29*$B$70 -> 13.98 | AG29: =AN29*B$67 -> 34.95 | AH29: =AN29*$B$74 -> 13.98 | AI29: =AN29-(AN29/1.12) -> 74.892857 | AJ29: =Z29*5% -> 19.898673 | AK29: =Z29*3% -> 11.939204 | AL29: =AN29-Y29-AD29-AE29-AG29-AI29-AJ29-AK29-AF29-AH29 -> -103.72418 | AM29: =AL29/AN29 -> -0.14838938 | AN29: 699 | AP29: 679 | AR29: 1999 | AV29: =SUM(AN29-AI29)-Y29 -> 268.7737 | AW29: =AV29/AN29 -> 0.38451173 | AX29: 8904422503502 | AY29: =Y29/U29 -> 120.45202 | AZ29: =AN29/+SUM(Y29/84) -> 165.24197 | BA29: =AN29/U29 -> 236.94915
A30: Duty - Furniture | B30: 0.25 | F30: FBA78996 | G30: B0CDQ6G4TC | H30: NP-03 | I30: Sports, Fitness & Outdoors | J30: Travel Accessories | K30: W | L30: Guangzhou Jibei | M30: Neck Pillow with Memory Foam (Grey) | N30: 94043090 | O30: 0.3 | P30: 21.6 | Q30: 16.6 | R30: 13.9 | S30: =(P30*Q30*R30)/1000000 -> 0.004983984 | T30: =(P30*Q30*R30)/5000 -> 0.9967968 | U30: 2.95 | W30: =B$27/(B$28/S30) -> 0.14658776 | X30: =(U30+W30)*(B$30+(B$30*B$45)) -> 0.85156164 | Y30: =(U30+W30+X30)*B$26 -> 355.33345 | Z30: =Y30*1.12 -> 397.97346 | AA30: =AN30*10% -> 69.9 | AB30: 25 | AC30: 78 | AD30: =AA30+AB30+AC30 -> 172.9 | AE30: =AN30*B$66 -> 104.85 | AI30: =AN30-(AN30/1.12) -> 74.892857 | AL30: =AN30-Y30-AD30-AE30-AG30-AI30-AJ30-AK30-AF30-AH30 -> -8.9763031 | AM30: =AL30/AN30 -> -0.012841635 | AN30: 699 | AP30: 679 | AR30: 1499 | AV30: =SUM(AN30-AI30)-Y30 -> 268.7737 | AW30: =AV30/AN30 -> 0.38451173 | AX30: 8904422503519 | AY30: =Y30/U30 -> 120.45202 | AZ30: =AN30/+SUM(Y30/84) -> 165.24197 | BA30: =AN30/U30 -> 236.94915
A31: Duty - Small Appliances | B31: 0.2 | F31: FBA78997 | G31: B0CDQ5Y3YB | H31: NP-04 | I31: Sports, Fitness & Outdoors | J31: Travel Accessories | L31: Guangzhou Jibei | M31: Neck Pillow with Memory Foam (Blue) | N31: 94043090 | O31: 0.3 | P31: 21.6 | Q31: 16.6 | R31: 13.9 | S31: =(P31*Q31*R31)/1000000 -> 0.004983984 | T31: =(P31*Q31*R31)/5000 -> 0.9967968 | U31: 2.95 | W31: =B$27/(B$28/S31) -> 0.14658776 | X31: =(U31+W31)*(B$30+(B$30*B$45)) -> 0.85156164 | Y31: =(U31+W31+X31)*B$26 -> 355.33345 | Z31: =Y31*1.12 -> 397.97346 | AA31: =AN31*10% -> 79.9 | AB31: 25 | AC31: 78 | AD31: =AA31+AB31+AC31 -> 182.9 | AE31: =AN31*B$66 -> 119.85 | AF31: =AN31*$B$70 -> 15.98 | AG31: =AN31*B$67 -> 39.95 | AH31: =AN31*$B$74 -> 15.98 | AI31: =AN31-(AN31/1.12) -> 85.607143 | AJ31: =Z31*5% -> 19.898673 | AK31: =Z31*3% -> 11.939204 | AL31: =AN31-Y31-AD31-AE31-AG31-AI31-AJ31-AK31-AF31-AH31 -> -48.438466 | AM31: =AL31/AN31 -> -0.060623862 | AN31: 799 | AP31: 679 | AR31: 1499 | AV31: =SUM(AN31-AI31)-Y31 -> 358.05941 | AW31: =AV31/AN31 -> 0.44813443 | AX31: 8904422503526 | AY31: =Y31/U31 -> 120.45202 | AZ31: =AN31/+SUM(Y31/84) -> 188.88174 | BA31: =AN31/U31 -> 270.84746
F32: FBA78998 | G32: B0CDQ5NBH8 | H32: NP-05 | I32: Sports, Fitness & Outdoors | J32: Travel Accessories | L32: Guangzhou Jibei | M32: Neck Pillow with Memory Foam (Pink) | N32: 94043090 | O32: 0.3 | P32: 21.6 | Q32: 16.6 | R32: 13.9 | S32: =(P32*Q32*R32)/1000000 -> 0.004983984 | T32: =(P32*Q32*R32)/5000 -> 0.9967968 | U32: 3.925 | W32: =B$27/(B$28/S32) -> 0.14658776 | X32: =(U32+W32)*(B$30+(B$30*B$45)) -> 1.1196866 | Y32: =(U32+W32+X32)*B$26 -> 467.2147 | Z32: =Y32*1.12 -> 523.28046 | AA32: =AN32*10% -> 59.9 | AB32: 25 | AC32: 78 | AD32: =AA32+AB32+AC32 -> 162.9 | AE32: =AN32*B$66 -> 89.85 | AF32: =AN32*$B$70 -> 11.98 | AG32: =AN32*B$67 -> 29.95 | AH32: =AN32*$B$74 -> 11.98 | AI32: =AN32-(AN32/1.12) -> 64.178571 | AJ32: =Z32*5% -> 26.164023 | AK32: =Z32*3% -> 15.698414 | AL32: =AN32-Y32-AD32-AE32-AG32-AI32-AJ32-AK32-AF32-AH32 -> -280.9157 | AM32: =AL32/AN32 -> -0.46897446 | AN32: 599 | AR32: 1999 | AV32: =SUM(AN32-AI32)-Y32 -> 67.606733 | AW32: =AV32/AN32 -> 0.112866 | AX32: 8904422503533 | AY32: =Y32/U32 -> 119.03559 | AZ32: =AN32/+SUM(Y32/84) -> 107.69353 | BA32: =AN32/U32 -> 152.61146
F33: FBA78999 | G33: B0CFFQK45G | H33: TR-01 | I33: Sports, Fitness & Outdoors | J33: Travel Accessories | L33: D&H Textile | M33: Nexlev Travel Blanket 50x60" (Black) | N33: 63013000 | O33: 0.54 | P33: 43 | Q33: 15.4 | R33: 13.5 | S33: =(P33*Q33*R33)/1000000 -> 0.0089397 | T33: =(P33*Q33*R33)/5000 -> 1.78794 | U33: 3.93 | W33: =B$27/(B$28/S33) -> 0.26293235 | X33: =(U33+W33)*(B$42+(B$42*B$45)) -> 0.46122256 | Y33: =(U33+W33+X33)*B$26 -> 418.87394 | Z33: =Y33*1.18 -> 494.27125 | AA33: =AN33*9.5% -> 85.405 | AB33: 25 | AC33: 107 | AD33: =AA33+AB33+AC33 -> 217.405 | AE33: =AN33*B$66 -> 134.85 | AF33: =AN33*$B$70 -> 17.98 | AG33: =AN33*B$67 -> 44.95 | AH33: =AN33*$B$74 -> 17.98 | AI33: =AN33-(AN33/1.12) -> 96.321429 | AJ33: =Z33*5% -> 24.713563 | AK33: =Z33*3% -> 14.828138 | AL33: =AN33-Y33-AD33-AE33-AG33-AI33-AJ33-AK33-AF33-AH33 -> -88.902071 | AM33: =AL33/AN33 -> -0.098889956 | AN33: 899 | AR33: 2199 | AV33: =SUM(AN33-AI33)-Y33 -> 383.80463 | AW33: =AV33/AN33 -> 0.42692395 | AX33: 8904422503540 | AY33: =Y33/U33 -> 106.5837 | AZ33: =AN33/+SUM(Y33/84) -> 180.28336 | BA33: =AN33/U33 -> 228.75318
F34: FBA79000 | G34: B0CFH2B2MV | H34: TR-02 | I34: Sports, Fitness & Outdoors | J34: Travel Accessories | L34: D&H Textile | M34: Nexlev Travel Blanket 50x60" (Navy) | N34: 63013000 | O34: 0.54 | P34: 43 | Q34: 15.4 | R34: 13.5 | S34: =(P34*Q34*R34)/1000000 -> 0.0089397 | T34: =(P34*Q34*R34)/5000 -> 1.78794 | U34: 3.98 | W34: =B$27/(B$28/S34) -> 0.26293235 | X34: =(U34+W34)*(B$42+(B$42*B$45)) -> 0.46672256 | Y34: =(U34+W34+X34)*B$26 -> 423.86894 | Z34: =Y34*1.18 -> 500.16535 | AA34: =AN34*9.5% -> 85.405 | AB34: 25 | AC34: 107 | AD34: =AA34+AB34+AC34 -> 217.405 | AE34: =AN34*B$66 -> 134.85 | AF34: =AN34*$B$70 -> 17.98 | AG34: =AN34*B$67 -> 44.95 | AH34: =AN34*$B$74 -> 17.98 | AI34: =AN34-(AN34/1.12) -> 96.321429 | AJ34: =Z34*5% -> 25.008268 | AK34: =Z34*3% -> 15.004961 | AL34: =AN34-Y34-AD34-AE34-AG34-AI34-AJ34-AK34-AF34-AH34 -> -94.368599 | AM34: =AL34/AN34 -> -0.10497063 | AN34: 899 | AR34: 2199 | AV34: =SUM(AN34-AI34)-Y34 -> 378.80963 | AW34: =AV34/AN34 -> 0.42136777 | AX34: 8904422503557 | AY34: =Y34/U34 -> 106.49973 | AZ34: =AN34/+SUM(Y34/84) -> 178.15884 | BA34: =AN34/U34 -> 225.8794
F35: FBA79001 | G35: B0CFH2C369 | H35: TR-03 | I35: Sports, Fitness & Outdoors | J35: Travel Accessories | L35: D&H Textile | M35: Nexlev Travel Blanket 50x60" (Pink) | N35: 63013000 | O35: 0.54 | P35: 43 | Q35: 15.4 | R35: 13.5 | S35: =(P35*Q35*R35)/1000000 -> 0.0089397 | T35: =(P35*Q35*R35)/5000 -> 1.78794 | U35: 3.98 | W35: =B$27/(B$28/S35) -> 0.26293235 | X35: =(U35+W35)*(B$42+(B$42*B$45)) -> 0.46672256 | Y35: =(U35+W35+X35)*B$26 -> 423.86894 | Z35: =Y35*1.18 -> 500.16535 | AA35: =AN35*9.5% -> 85.405 | AB35: 25 | AC35: 107 | AD35: =AA35+AB35+AC35 -> 217.405 | AE35: =AN35*B$66 -> 134.85 | AF35: =AN35*$B$70 -> 17.98 | AG35: =AN35*B$67 -> 44.95 | AH35: =AN35*$B$74 -> 17.98 | AI35: =AN35-(AN35/1.12) -> 96.321429 | AJ35: =Z35*5% -> 25.008268 | AK35: =Z35*3% -> 15.004961 | AL35: =AN35-Y35-AD35-AE35-AG35-AI35-AJ35-AK35-AF35-AH35 -> -94.368599 | AM35: =AL35/AN35 -> -0.10497063 | AN35: 899 | AR35: 2199 | AV35: =SUM(AN35-AI35)-Y35 -> 378.80963 | AW35: =AV35/AN35 -> 0.42136777 | AX35: 8904422503564 | AY35: =Y35/U35 -> 106.49973 | AZ35: =AN35/+SUM(Y35/84) -> 178.15884 | BA35: =AN35/U35 -> 225.8794
F36: FBA79002 | G36: B0CFH5R7Y7 | H36: TR-04 | I36: Sports, Fitness & Outdoors | J36: Travel Accessories | L36: D&H Textile | M36: Nexlev Travel Blanket 50x60" (Grey) | N36: 63013000 | O36: 0.54 | P36: 43 | Q36: 15.4 | R36: 13.5 | S36: =(P36*Q36*R36)/1000000 -> 0.0089397 | T36: =(P36*Q36*R36)/5000 -> 1.78794 | U36: 3.98 | W36: =B$27/(B$28/S36) -> 0.26293235 | X36: =(U36+W36)*(B$42+(B$42*B$45)) -> 0.46672256 | Y36: =(U36+W36+X36)*B$26 -> 423.86894 | Z36: =Y36*1.18 -> 500.16535 | AA36: =AN36*9.5% -> 85.405 | AB36: 25 | AC36: 135 | AD36: =AA36+AB36+AC36 -> 245.405 | AE36: =AN36*B$66 -> 134.85 | AF36: =AN36*$B$70 -> 17.98 | AG36: =AN36*B$67 -> 44.95 | AH36: =AN36*$B$74 -> 17.98 | AI36: =AN36-(AN36/1.12) -> 96.321429 | AJ36: =Z36*5% -> 25.008268 | AK36: =Z36*3% -> 15.004961 | AL36: =AN36-Y36-AD36-AE36-AG36-AI36-AJ36-AK36-AF36-AH36 -> -122.3686 | AM36: =AL36/AN36 -> -0.13611635 | AN36: 899 | AR36: 2199 | AV36: =SUM(AN36-AI36)-Y36 -> 378.80963 | AW36: =AV36/AN36 -> 0.42136777 | AX36: 8904422503571 | AY36: =Y36/U36 -> 106.49973 | AZ36: =AN36/+SUM(Y36/84) -> 178.15884 | BA36: =AN36/U36 -> 225.8794
F37: FBA79003 | G37: B0CFH6C6YM | H37: TR-05 | I37: Sports, Fitness & Outdoors | J37: Travel Accessories | L37: D&H Textile | M37: Nexlev Waterproof Picnic Blanket 40x65" (Grey) | N37: 63013000 | O37: 1.25 | P37: 43 | Q37: 15.4 | R37: 13.5 | S37: =(P37*Q37*R37)/1000000 -> 0.0089397 | T37: =(P37*Q37*R37)/5000 -> 1.78794 | U37: 5.45 | W37: =B$27/(B$28/S37) -> 0.26293235 | X37: =(U37+W37)*(B$42+(B$42*B$45)) -> 0.62842256 | Y37: =(U37+W37+X37)*B$26 -> 570.72194 | Z37: =Y37*1.18 -> 673.45189 | AA37: =AN37*9.5% -> 83.505 | AB37: 25 | AC37: 135 | AD37: =AA37+AB37+AC37 -> 243.505 | AE37: =AN37*B$66 -> 131.85 | AF37: =AN37*$B$70 -> 17.58 | AG37: =AN37*B$67 -> 43.95 | AH37: =AN37*$B$74 -> 17.58 | AI37: =AN37-(AN37/1.12) -> 94.178571 | AJ37: =Z37*5% -> 33.672595 | AK37: =Z37*3% -> 20.203557 | AL37: =AN37-Y37-AD37-AE37-AG37-AI37-AJ37-AK37-AF37-AH37 -> -294.24166 | AM37: =AL37/AN37 -> -0.33474592 | AN37: 879 | AR37: 2999 | AV37: =SUM(AN37-AI37)-Y37 -> 214.09949 | AW37: =AV37/AN37 -> 0.24357166 | AX37: 8904422503588 | AY37: =Y37/U37 -> 104.71962 | AZ37: =AN37/+SUM(Y37/84) -> 129.37298 | BA37: =AN37/U37 -> 161.2844
F38: FBA79217 | G38: B0C7GMKPP3 | H38: WF100Wh-Light | I38: Pet Supplies | J38: Pet Supplies | L38: Molly Tan | M38: NexLev Pet Water Fountain 2L | N38: 84212190 | O38: 0.62 | P38: 16.5 | Q38: 16.5 | R38: 15.5 | S38: =(P38*Q38*R38)/1000000 -> 0.004219875 | T38: =(P38*Q38*R38)/5000 -> 0.843975 | U38: 4.77 | W38: =B$27/(B$28/S38) -> 0.12411397 | X38: =(U38+W38)*(B$44+(B44*B$45)) -> 0.4037644 | Y38: =(U38+W38+X38)*B$26 -> 476.80905 | Z38: =Y38*1.18 -> 562.63468 | AA38: =AN38*12% -> 167.88 | AB38: 47 | AC38: 107 | AD38: =AA38+AB38+AC38 -> 321.88 | AE38: =AN38*B$66 -> 209.85 | AF38: =AN38*$B$70 -> 27.98 | AG38: =AN38*B$67 -> 69.95 | AH38: =AN38*$B$74 -> 27.98 | AI38: =AN38-(AN38/1.12) -> 149.89286 | AJ38: =Z38*5% -> 28.131734 | AK38: =Z38*3% -> 16.87904 | AL38: =AN38-Y38-AD38-AE38-AG38-AI38-AJ38-AK38-AF38-AH38 -> 69.647315 | AM38: =AL38/AN38 -> 0.049783642 | AN38: 1399 | AR38: 2999 | AV38: =SUM(AN38-AI38)-Y38 -> 772.29809 | AW38: =AV38/AN38 -> 0.5520358 | AY38: =Y38/U38 -> 99.959969 | AZ38: =AN38/+SUM(Y38/84) -> 246.46344 | BA38: =AN38/U38 -> 293.2914
F39: FBA79218 | G39: B0CQ2RKB68 | H39: WF100BL-Light | I39: Pet Supplies | J39: Pet Supplies | L39: Molly Tan | M39: Pet Water Fountain WF100BL with Light without Adapter | N39: 84212190 | O39: 0.62 | P39: 16.5 | Q39: 16.5 | R39: 15.5 | S39: =(P39*Q39*R39)/1000000 -> 0.004219875 | T39: =(P39*Q39*R39)/5000 -> 0.843975 | U39: 8.99 | W39: =B$27/(B$28/S39) -> 0.12411397 | X39: =(U39+W39)*(B$44+(B45*B$45)) -> 0.77469969 | Y39: =(U39+W39+X39)*B$26 -> 889.99323 | Z39: =Y39*1.18 -> 1050.192 | AA39: =AN39*12% -> 227.88 | AB39: 47 | AC39: 107 | AD39: =AA39+AB39+AC39 -> 381.88 | AE39: =AN39*B$66 -> 284.85 | AF39: =AN39*$B$70 -> 37.98 | AG39: =AN39*B$67 -> 94.95 | AH39: =AN39*$B$74 -> 37.98 | AI39: =AN39-(AN39/1.12) -> 203.46429 | AJ39: =Z39*5% -> 52.509601 | AK39: =Z39*3% -> 31.50576 | AL39: =AN39-Y39-AD39-AE39-AG39-AI39-AJ39-AK39-AF39-AH39 -> -116.11288 | AM39: =AL39/AN39 -> -0.061144221 | AN39: 1899 | AR39: 2999 | AV39: =SUM(AN39-AI39)-Y39 -> 805.54249 | AW39: =AV39/AN39 -> 0.42419299 | AY39: =Y39/U39 -> 98.998135 | AZ39: =AN39/+SUM(Y39/84) -> 179.23282 | BA39: =AN39/U39 -> 211.23471
F40: FBA79174 | G40: B0CW1JJP9S | H40: DF-01-BK | I40: HPC | J40: Oral Care | K40: Y820 | L40: Shenzhen Yuxinyuan Electronic Technology Co., Ltd. | M40: Nexlev Dental Flosser (Black) | N40: 84244900 | O40: 0.38 | P40: 23.5 | Q40: 8.7 | R40: 7.5 | S40: =(P40*Q40*R40)/1000000 -> 0.001533375 | T40: =(P40*Q40*R40)/5000 -> 0.306675 | U40: 9.17 | W40: =U40*2% -> 0.1834 | X40: =(U40+W40)*(B$43+(B$43*B$45)) -> 0.7716555 | Y40: =(U40+W40+X40)*B$26 -> 911.255 | Z40: =Y40*1.18 -> 1075.2809 | AA40: =AN40*7.5% -> 98.925 | AB40: 51 | AC40: 59 | AD40: =AA40+AB40+AC40 -> 208.925 | AE40: =AN40*B$72 -> 263.8 | AG40: =AN40*B$67 -> 65.95 | AI40: =AN40-(AN40/1.18) -> 201.20339 | AJ40: =Z40*5% -> 53.764045 | AK40: =Z40*3% -> 32.258427 | AL40: =AN40-Y40-AD40-AE40-AG40-AI40-AJ40-AK40-AF40-AH40 -> -418.15586 | AM40: =AL40/AN40 -> -0.31702491 | AN40: 1319 | AP40: 1580 | AR40: 3599 | AV40: =SUM(AN40-AI40)-Y40 -> 206.54162 | AW40: =AV40/AN40 -> 0.15658955 | AX40: 8904422503854 | AY40: =Y40/U40 -> 99.3735 | AZ40: =AN40/+SUM(Y40/84) -> 121.58616 | BA40: =AN40/U40 -> 143.8386
F41: FBA79228 | H41: GS-03 | I41: Fabric Care | K41: Y820 | L41: Shenzhen Yuxinyuan Electronic Technology Co., Ltd. | M41: Nexlev Garment Steamer with Three Brushes | N41: 85167990 | O41: 1.3 | P41: 29.2 | Q41: 22.4 | R41: 13.6 | S41: =(P41*Q41*R41)/1000000 -> 0.008895488 | T41: =(P41*Q41*R41)/5000 -> 1.7790976 | U41: 10.2 | W41: =B$27/(B$28/S41) -> 0.261632 | X41: =(U41+W41)*(B$31+(B$31*B$45)) -> 2.301559 | Y41: =(U41+W41+X41)*B$26 -> 1148.6872 | Z41: =Y41*1.18 -> 1355.4509 | AA41: =AN41*4.5% -> 98.955 | AB41: 51 | AC41: 136 | AD41: =AA41+AB41+AC41 -> 285.955 | AE41: =AN41*B$66 -> 329.85 | AF41: =AN41*$B$70 -> 43.98 | AG41: =AN41*B$67 -> 109.95 | AH41: =AN41*$B$74 -> 43.98 | AI41: =AN41-(AN41/1.18) -> 335.44068 | AJ41: =Z41*5% -> 67.772544 | AK41: =Z41*3% -> 40.663527 | AL41: =AN41-Y41-AD41-AE41-AG41-AI41-AJ41-AK41-AF41-AH41 -> -207.27894 | AM41: =AL41/AN41 -> -0.094260547 | AN41: 2199 | AR41: 4999 | AV41: =SUM(AN41-AI41)-Y41 -> 714.87213 | AW41: =AV41/AN41 -> 0.32508964 | AX41: 8904422503984 | AY41: =Y41/U41 -> 112.61639 | AZ41: =AN41/+SUM(Y41/84) -> 160.80618 | BA41: =AN41/U41 -> 215.58824
A42: Duty - Other Appliances | B42: 0.1 | F42: FBA79229 | G42: B0CQX9ZZMH | H42: GS-04 | I42: Home & Kitchen | J42: Fabric Care | L42: Zhejiang Huaguang | M42: Nexlev Garment Steamer with Touch Screen Breeze | N42: 85167990 | O42: 1.3 | P42: 29.2 | Q42: 22.4 | R42: 13.6 | S42: =(P42*Q42*R42)/1000000 -> 0.008895488 | T42: =(P42*Q42*R42)/5000 -> 1.7790976 | U42: 11.38 | W42: =B$27/(B$28/S42) -> 0.261632 | X42: =(U42+W42)*(B$31+(B$31*B$45)) -> 2.561159 | Y42: =(U42+W42+X42)*B$26 -> 1278.2512 | Z42: =Y42*1.18 -> 1508.3364 | AA42: =AN42*4.5% -> 98.955 | AB42: 51 | AC42: 143 | AD42: =AA42+AB42+AC42 -> 292.955 | AE42: =AN42*B$66 -> 329.85 | AF42: =AN42*$B$70 -> 43.98 | AG42: =AN42*B$67 -> 109.95 | AH42: =AN42*$B$74 -> 43.98 | AI42: =AN42-(AN42/1.18) -> 335.44068 | AJ42: =Z42*5% -> 75.41682 | AK42: =Z42*3% -> 45.250092 | AL42: =AN42-Y42-AD42-AE42-AG42-AI42-AJ42-AK42-AF42-AH42 -> -356.07378 | AM42: =AL42/AN42 -> -0.16192532 | AN42: 2199 | AP42: 2099 | AR42: 5999 | AV42: =SUM(AN42-AI42)-Y42 -> 585.30813 | AW42: =AV42/AN42 -> 0.26617014 | AX42: 8904422503991 | AY42: =Y42/U42 -> 112.32436 | AZ42: =AN42/+SUM(Y42/84) -> 144.50681 | BA42: =AN42/U42 -> 193.23374
A43: Duty - Flosser | B43: 0.075 | F43: FBA79233 | G43: B0CS69T7HF | H43: ET-01-BK | I43: HPC | J43: Oral Care | L43: Ningbo Oral | M43: Electric Toothbrush - Black - Humm | N43: 85098000 | U43: 2.15 | V43: 2.15 | W43: =U43*2% -> 0.043 | X43: =(U43+W43)*(B$31+(B$31*B$45)) -> 0.48246 | Y43: =(U43+W43+X43)*B$26 -> 240.7914 | Z43: =Y43*1.18 -> 284.13385 | AA43: =AN43*4.5% -> 17.955 | AB43: 12 | AC43: 60 | AD43: =AA43+AB43+AC43 -> 89.955 | AE43: =AN43*B$72 -> 79.8 | AF43: =AN43*$B$70 -> 7.98 | AG43: 0 | AH43: =AN43*$B$74 -> 7.98 | AI43: =AN43-(AN43/1.18) -> 60.864407 | AJ43: =Z43*5% -> 14.206693 | AK43: =Z43*3% -> 8.5240156 | AL43: =AN43-Y43-AD43-AE43-AG43-AI43-AJ43-AK43-AF43-AH43 -> -111.10151 | AM43: =AL43/AN43 -> -0.27844991 | AN43: 399 | AR43: 1199 | AV43: =SUM(AN43-AI43)-Y43 -> 97.344193 | AW43: =AV43/AN43 -> 0.24397041 | AX43: 8904422504004 | AY43: =Y43/U43 -> 111.996 | AZ43: =AN43/+SUM(Y43/84) -> 139.19102 | BA43: =AN43/U43 -> 185.5814
A44: Duty - Pet water fountain | B44: 0.075 | F44: FBA79234 | G44: B0CSG2JZ19 | H44: ET-02-GN | I44: HPC | J44: Oral Care | L44: Ningbo Oral | M44: Electric Toothbrush - Green - Humm | N44: 85098000 | U44: 2.15 | V44: 2.15 | W44: =U44*2% -> 0.043 | X44: =(U44+W44)*(B$31+(B$31*B$45)) -> 0.48246 | Y44: =(U44+W44+X44)*B$26 -> 240.7914 | Z44: =Y44*1.18 -> 284.13385 | AA44: =AN44*4.5% -> 15.705 | AB44: 12 | AC44: 60 | AD44: =AA44+AB44+AC44 -> 87.705 | AE44: =AN44*B$72 -> 69.8 | AF44: =AN44*$B$70 -> 6.98 | AG44: 0 | AH44: =AN44*$B$74 -> 6.98 | AI44: =AN44-(AN44/1.18) -> 53.237288 | AJ44: =Z44*5% -> 14.206693 | AK44: =Z44*3% -> 8.5240156 | AL44: =AN44-Y44-AD44-AE44-AG44-AI44-AJ44-AK44-AF44-AH44 -> -139.2244 | AM44: =AL44/AN44 -> -0.39892377 | AN44: 349 | AR44: 1199 | AV44: =SUM(AN44-AI44)-Y44 -> 54.971312 | AW44: =AV44/AN44 -> 0.15751092 | AX44: 8904422504011 | AY44: =Y44/U44 -> 111.996 | AZ44: =AN44/+SUM(Y44/84) -> 121.74853 | BA44: =AN44/U44 -> 162.32558
A45: Surcharge | B45: 0.1 | F45: FBA79258 | G45: B0CSG3FC4G | H45: ET-03-BL | I45: HPC | J45: Oral Care | L45: Ningbo Oral | M45: Electric Toothbrush - Blue-One Mode-Sparkle | N45: 85098000 | U45: 1.48 | V45: 1.48 | W45: =U45*2% -> 0.0296 | X45: =(U45+W45)*(B$31+(B$31*B$45)) -> 0.332112 | Y45: =(U45+W45+X45)*B$26 -> 165.75408 | Z45: =Y45*1.18 -> 195.58981 | AA45: =AN45*4.5% -> 17.955 | AB45: 12 | AC45: 60 | AD45: =AA45+AB45+AC45 -> 89.955 | AE45: =AN45*B$72 -> 79.8 | AF45: =AN45*$B$70 -> 7.98 | AG45: 0 | AH45: =AN45*$B$74 -> 7.98 | AI45: =AN45-(AN45/1.18) -> 60.864407 | AJ45: =Z45*5% -> 9.7794907 | AK45: =Z45*3% -> 5.8676944 | AL45: =AN45-Y45-AD45-AE45-AG45-AI45-AJ45-AK45-AF45-AH45 -> -28.980672 | AM45: =AL45/AN45 -> -0.072633263 | AN45: 399 | AR45: 699 | AV45: =SUM(AN45-AI45)-Y45 -> 172.38151 | AW45: =AV45/AN45 -> 0.43203387 | AX45: 8904422504028 | AY45: =Y45/U45 -> 111.996 | AZ45: =AN45/+SUM(Y45/84) -> 202.20317 | BA45: =AN45/U45 -> 269.59459
F46: FBA79392 | G46: B0D2RRPX6B | H46: DB_BK_BL_GN | I46: HPC | J46: Oral Care | L46: Ningbo Oral | M46: Nexlev ET-01-BK, ET-02-GN & ET-03-BL 3 Brush Combo Blue, Green and Black | N46: 85098000 | U46: =U43+U44+U45 -> 5.78 | W46: =U46*2% -> 0.1156 | X46: =(U46+W46)*(B$31+(B$31*B$45)) -> 1.297032 | Y46: =(U46+W46+X46)*B$26 -> 647.33688 | Z46: 704.5 | AA46: =AN46*4.5% -> 53.865 | AB46: 12 | AC46: 60 | AD46: =AA46+AB46+AC46 -> 125.865 | AE46: =AN46*B$66 -> 179.55 | AF46: =AN46*$B$70 -> 23.94 | AG46: 0 | AH46: =AN46*$B$74 -> 23.94 | AI46: =AN46-(AN46/1.18) -> 182.59322 | AJ46: =Z46*5% -> 35.225 | AK46: =Z46*3% -> 21.135 | AL46: =AN46-Y46-AD46-AE46-AG46-AI46-AJ46-AK46-AF46-AH46 -> -42.5851 | AM46: =AL46/AN46 -> -0.035576525 | AN46: 1197 | AR46: 2399 | AV46: =SUM(AN46-AI46)-Y46 -> 367.0699 | AW46: =AV46/AN46 -> 0.30665823 | AX46: 8904422504370 | AY46: =Y46/U46 -> 111.996 | AZ46: =AN46/+SUM(Y46/84) -> 155.32562 | BA46: =AN46/U46 -> 207.09343
F47: FBA79393 | G47: B0D2RQPPW1 | H47: DB_BK_GN | I47: HPC | J47: Oral Care | L47: Ningbo Oral | M47: Nexlev ET-01-BK, ET-02-GN 2 Brush Combo Black and Green | N47: 85098000 | U47: =U43+U44 -> 4.3 | W47: =U47*2% -> 0.086 | X47: =(U47+W47)*(B$31+(B$31*B$45)) -> 0.96492 | Y47: =(U47+W47+X47)*B$26 -> 481.5828 | Z47: 524 | AA47: =AN47*4.5% -> 40.41 | AB47: 12 | AC47: 60 | AD47: =AA47+AB47+AC47 -> 112.41 | AE47: =AN47*B$66 -> 134.7 | AF47: =AN47*$B$70 -> 17.96 | AG47: 0 | AH47: =AN47*$B$74 -> 17.96 | AI47: =AN47-(AN47/1.18) -> 136.98305 | AJ47: =Z47*5% -> 26.2 | AK47: =Z47*3% -> 15.72 | AL47: =AN47-Y47-AD47-AE47-AG47-AI47-AJ47-AK47-AF47-AH47 -> -45.515851 | AM47: =AL47/AN47 -> -0.050685803 | AN47: 898 | AR47: 1799 | AV47: =SUM(AN47-AI47)-Y47 -> 279.43415 | AW47: =AV47/AN47 -> 0.31117389 | AX47: 8904422504387 | AY47: =Y47/U47 -> 111.996 | AZ47: =AN47/+SUM(Y47/84) -> 156.6335 | BA47: =AN47/U47 -> 208.83721
F48: FBA79394 | G48: B0D2RQ11MT | H48: DB_BL-BK | I48: HPC | J48: Oral Care | L48: Ningbo Oral | M48: Nexlev ET-03-BL, ET-01-BK 2 Different colour brush combo Blue and Black | N48: 85098000 | U48: =U45+U43 -> 3.63 | W48: =U48*2% -> 0.0726 | X48: =(U48+W48)*(B$31+(B$31*B$45)) -> 0.814572 | Y48: =(U48+W48+X48)*B$26 -> 406.54548 | Z48: 442.5 | AA48: =AN48*4.5% -> 33.66 | AB48: 12 | AC48: 60 | AD48: =AA48+AB48+AC48 -> 105.66 | AE48: =AN48*B$66 -> 112.2 | AF48: =AN48*$B$70 -> 14.96 | AG48: 0 | AH48: =AN48*$B$74 -> 14.96 | AI48: =AN48-(AN48/1.18) -> 114.10169 | AJ48: =Z48*5% -> 22.125 | AK48: =Z48*3% -> 13.275 | AL48: =AN48-Y48-AD48-AE48-AG48-AI48-AJ48-AK48-AF48-AH48 -> -55.827175 | AM48: =AL48/AN48 -> -0.074635261 | AN48: 748 | AR48: 1499 | AV48: =SUM(AN48-AI48)-Y48 -> 227.35283 | AW48: =AV48/AN48 -> 0.30394763 | AX48: 8904422504394 | AY48: =Y48/U48 -> 111.996 | AZ48: =AN48/+SUM(Y48/84) -> 154.55097 | BA48: =AN48/U48 -> 206.06061
F49: FBA79395 | G49: B0D2RPMDRD | H49: DB_BL-GN | I49: HPC | J49: Oral Care | L49: Ningbo Oral | M49: Nexlev ET-03-BL, ET-02-GN 2 Different colour brush combo Blue and Green | N49: 85098000 | U49: =U45+U44 -> 3.63 | W49: =U49*2% -> 0.0726 | X49: =(U49+W49)*(B$31+(B$31*B$45)) -> 0.814572 | Y49: =(U49+W49+X49)*B$26 -> 406.54548 | Z49: 442.5 | AA49: =AN49*4.5% -> 33.66 | AB49: 12 | AC49: 60 | AD49: =AA49+AB49+AC49 -> 105.66 | AE49: =AN49*B$66 -> 112.2 | AF49: =AN49*$B$70 -> 14.96 | AG49: 0 | AH49: =AN49*$B$74 -> 14.96 | AI49: =AN49-(AN49/1.18) -> 114.10169 | AJ49: =Z49*5% -> 22.125 | AK49: =Z49*3% -> 13.275 | AL49: =AN49-Y49-AD49-AE49-AG49-AI49-AJ49-AK49-AF49-AH49 -> -55.827175 | AM49: =AL49/AN49 -> -0.074635261 | AN49: 748 | AR49: 1499 | AV49: =SUM(AN49-AI49)-Y49 -> 227.35283 | AW49: =AV49/AN49 -> 0.30394763 | AX49: 8904422504400 | AY49: =Y49/U49 -> 111.996 | AZ49: =AN49/+SUM(Y49/84) -> 154.55097 | BA49: =AN49/U49 -> 206.06061
F50: FBA79396 | G50: B0D2RQ42MM | H50: DB_2BK | I50: HPC | J50: Oral Care | L50: Ningbo Oral | M50: Nexlev ET-01-BK 2 Same colour brush combo of Black | N50: 85098000 | U50: =U43*2 -> 4.3 | W50: =U50*2% -> 0.086 | X50: =(U50+W50)*(B$31+(B$31*B$45)) -> 0.96492 | Y50: =(U50+W50+X50)*B$26 -> 481.5828 | Z50: 524 | AA50: =AN50*4.5% -> 40.41 | AB50: 12 | AC50: 60 | AD50: =AA50+AB50+AC50 -> 112.41 | AE50: =AN50*B$66 -> 134.7 | AF50: =AN50*$B$70 -> 17.96 | AG50: 0 | AH50: =AN50*$B$74 -> 17.96 | AI50: =AN50-(AN50/1.18) -> 136.98305 | AJ50: =Z50*5% -> 26.2 | AK50: =Z50*3% -> 15.72 | AL50: =AN50-Y50-AD50-AE50-AG50-AI50-AJ50-AK50-AF50-AH50 -> -45.515851 | AM50: =AL50/AN50 -> -0.050685803 | AN50: 898 | AR50: 1799 | AV50: =SUM(AN50-AI50)-Y50 -> 279.43415 | AW50: =AV50/AN50 -> 0.31117389 | AX50: 8904422504417 | AY50: =Y50/U50 -> 111.996 | AZ50: =AN50/+SUM(Y50/84) -> 156.6335 | BA50: =AN50/U50 -> 208.83721
F51: FBA79397 | G51: B0D2RNMJTM | H51: DB_2GN | I51: HPC | J51: Oral Care | L51: Ningbo Oral | M51: Nexlev ET-02-GN 2 Same colour brush combo of Green | N51: 85098000 | U51: 4.3 | W51: =U51*2% -> 0.086 | X51: =(U51+W51)*(B$31+(B$31*B$45)) -> 0.96492 | Y51: =(U51+W51+X51)*B$26 -> 481.5828 | Z51: 524 | AA51: =AN51*4.5% -> 40.41 | AB51: 12 | AC51: 60 | AD51: =AA51+AB51+AC51 -> 112.41 | AE51: =AN51*B$66 -> 134.7 | AF51: =AN51*$B$70 -> 17.96 | AG51: 0 | AH51: =AN51*$B$74 -> 17.96 | AI51: =AN51-(AN51/1.18) -> 136.98305 | AJ51: =Z51*5% -> 26.2 | AK51: =Z51*3% -> 15.72 | AL51: =AN51-Y51-AD51-AE51-AG51-AI51-AJ51-AK51-AF51-AH51 -> -45.515851 | AM51: =AL51/AN51 -> -0.050685803 | AN51: 898 | AR51: 1799 | AV51: =SUM(AN51-AI51)-Y51 -> 279.43415 | AW51: =AV51/AN51 -> 0.31117389 | AX51: 8904422504424 | AY51: =Y51/U51 -> 111.996 | AZ51: =AN51/+SUM(Y51/84) -> 156.6335 | BA51: =AN51/U51 -> 208.83721
F52: FBA79398 | G52: B0D2RPTRH5 | H52: DB_2BL | I52: HPC | J52: Oral Care | L52: Ningbo Oral | M52: Nexlev ET-03-BL 2 Same colour brush combo of Blue | N52: 85098000 | U52: =U45*2 -> 2.96 | W52: =U52*2% -> 0.0592 | X52: =(U52+W52)*(B$31+(B$31*B$45)) -> 0.664224 | Y52: =(U52+W52+X52)*B$26 -> 331.50816 | Z52: 360.8 | AA52: =AN52*4.5% -> 26.91 | AB52: 12 | AC52: 60 | AD52: =AA52+AB52+AC52 -> 98.91 | AE52: =AN52*B$66 -> 89.7 | AF52: =AN52*$B$70 -> 11.96 | AG52: 0 | AH52: =AN52*$B$74 -> 11.96 | AI52: =AN52-(AN52/1.18) -> 91.220339 | AJ52: =Z52*5% -> 18.04 | AK52: =Z52*3% -> 10.824 | AL52: =AN52-Y52-AD52-AE52-AG52-AI52-AJ52-AK52-AF52-AH52 -> -66.122499 | AM52: =AL52/AN52 -> -0.11057274 | AN52: 598 | AR52: 1199 | AV52: =SUM(AN52-AI52)-Y52 -> 175.2715 | AW52: =AV52/AN52 -> 0.29309616 | AX52: 8904422504431 | AY52: =Y52/U52 -> 111.996 | AZ52: =AN52/+SUM(Y52/84) -> 151.52568 | BA52: =AN52/U52 -> 202.02703
F53: FBA79399 | G53: B0D2RQHHTX | H53: DB_3BK | I53: HPC | J53: Oral Care | L53: Ningbo Oral | M53: Nexlev ET-01-BK 3 Same colour brush combo of Black | N53: 85098000 | U53: =U43*3 -> 6.45 | W53: =U53*2% -> 0.129 | X53: =(U53+W53)*(B$31+(B$31*B$45)) -> 1.44738 | Y53: =(U53+W53+X53)*B$26 -> 722.3742 | Z53: 786 | AA53: =AN53*4.5% -> 60.615 | AB53: 12 | AC53: 60 | AD53: =AA53+AB53+AC53 -> 132.615 | AE53: =AN53*B$66 -> 202.05 | AF53: =AN53*$B$70 -> 26.94 | AG53: 0 | AH53: =AN53*$B$74 -> 26.94 | AI53: =AN53-(AN53/1.18) -> 205.47458 | AJ53: =Z53*5% -> 39.3 | AK53: =Z53*3% -> 23.58 | AL53: =AN53-Y53-AD53-AE53-AG53-AI53-AJ53-AK53-AF53-AH53 -> -32.273776 | AM53: =AL53/AN53 -> -0.023959745 | AN53: 1347 | AR53: 2699 | AV53: =SUM(AN53-AI53)-Y53 -> 419.15122 | AW53: =AV53/AN53 -> 0.31117389 | AX53: 8904422504448 | AY53: =Y53/U53 -> 111.996 | AZ53: =AN53/+SUM(Y53/84) -> 156.6335 | BA53: =AN53/U53 -> 208.83721
F54: FBA79400 | G54: B0D2RRZ3YD | H54: DB_3GN | I54: HPC | J54: Oral Care | L54: Ningbo Oral | M54: Nexlev ET-02-GN 3 Same colour brush combo of Green | N54: 85098000 | U54: 6.45 | W54: =U54*2% -> 0.129 | X54: =(U54+W54)*(B$31+(B$31*B$45)) -> 1.44738 | Y54: =(U54+W54+X54)*B$26 -> 722.3742 | Z54: 786 | AA54: =AN54*4.5% -> 60.615 | AB54: 12 | AC54: 60 | AD54: =AA54+AB54+AC54 -> 132.615 | AE54: =AN54*B$66 -> 202.05 | AF54: =AN54*$B$70 -> 26.94 | AG54: 0 | AH54: =AN54*$B$74 -> 26.94 | AI54: =AN54-(AN54/1.18) -> 205.47458 | AJ54: =Z54*5% -> 39.3 | AK54: =Z54*3% -> 23.58 | AL54: =AN54-Y54-AD54-AE54-AG54-AI54-AJ54-AK54-AF54-AH54 -> -32.273776 | AM54: =AL54/AN54 -> -0.023959745 | AN54: 1347 | AR54: 2699 | AV54: =SUM(AN54-AI54)-Y54 -> 419.15122 | AW54: =AV54/AN54 -> 0.31117389 | AX54: 8904422504455 | AY54: =Y54/U54 -> 111.996 | AZ54: =AN54/+SUM(Y54/84) -> 156.6335 | BA54: =AN54/U54 -> 208.83721
F55: FBA79401 | G55: B0D2RQW2QW | H55: DB_3BL | I55: HPC | J55: Oral Care | L55: Ningbo Oral | M55: Nexlev ET-03-BL 3 Same colour brush combo of Blue | N55: 85098000 | U55: =U45*3 -> 4.44 | W55: =U55*2% -> 0.0888 | X55: =(U55+W55)*(B$31+(B$31*B$45)) -> 0.996336 | Y55: =(U55+W55+X55)*B$26 -> 497.26224 | Z55: 541.2 | AA55: =AN55*4.5% -> 40.365 | AB55: 12 | AC55: 60 | AD55: =AA55+AB55+AC55 -> 112.365 | AE55: =AN55*B$66 -> 134.55 | AF55: =AN55*$B$70 -> 17.94 | AG55: 0 | AH55: =AN55*$B$74 -> 17.94 | AI55: =AN55-(AN55/1.18) -> 136.83051 | AJ55: =Z55*5% -> 27.06 | AK55: =Z55*3% -> 16.236 | AL55: =AN55-Y55-AD55-AE55-AG55-AI55-AJ55-AK55-AF55-AH55 -> -63.183748 | AM55: =AL55/AN55 -> -0.070438962 | AN55: 897 | AR55: 1799 | AV55: =SUM(AN55-AI55)-Y55 -> 262.90725 | AW55: =AV55/AN55 -> 0.29309616 | AX55: 8904422504462 | AY55: =Y55/U55 -> 111.996 | AZ55: =AN55/+SUM(Y55/84) -> 151.52568 | BA55: =AN55/U55 -> 202.02703
F56: FBA79402 | G56: B0D2RRJRRV | H56: DB_DF_BK | I56: HPC | J56: Oral Care | L56: Ningbo Oral | M56: Nexlev DF-01-BK Flosser & ET-01-BK Black Brush Combo | N56: 85098000 | U56: =U40+U43 -> 11.32 | W56: =U56*2% -> 0.2264 | X56: =(U56+W56)*(B$31+(B$31*B$45)) -> 2.540208 | Y56: =(U56+W56+X56)*B$26 -> 1267.7947 | Z56: 1253.6 | AA56: =AN56*4.5% -> 87.705 | AB56: 12 | AC56: 60 | AD56: =AA56+AB56+AC56 -> 159.705 | AE56: =AN56*B$66 -> 292.35 | AF56: =AN56*$B$70 -> 38.98 | AG56: 0 | AH56: =AN56*$B$74 -> 38.98 | AI56: =AN56-(AN56/1.18) -> 297.30508 | AJ56: =Z56*5% -> 62.68 | AK56: =Z56*3% -> 37.608 | AL56: =AN56-Y56-AD56-AE56-AG56-AI56-AJ56-AK56-AF56-AH56 -> -246.4028 | AM56: =AL56/AN56 -> -0.12642525 | AN56: 1949 | AR56: 3699 | AV56: =SUM(AN56-AI56)-Y56 -> 383.9002 | AW56: =AV56/AN56 -> 0.19697291 | AX56: 8904422504479 | AY56: =Y56/U56 -> 111.996 | AZ56: =AN56/+SUM(Y56/84) -> 129.13447 | BA56: =AN56/U56 -> 172.17314
F57: FBA79403 | G57: B0D2RPTPTD | H57: DB_DF_GN | I57: HPC | J57: Oral Care | L57: Ningbo Oral | M57: Nexlev DF-01-BK Flosser & ET-02-GN Green Brush Combo | N57: 85098000 | U57: =U40+U44 -> 11.32 | W57: =U57*2% -> 0.2264 | X57: =(U57+W57)*(B$31+(B$31*B$45)) -> 2.540208 | Y57: =(U57+W57+X57)*B$26 -> 1267.7947 | Z57: 1253.6 | AA57: =AN57*4.5% -> 87.705 | AB57: 12 | AC57: 60 | AD57: =AA57+AB57+AC57 -> 159.705 | AE57: =AN57*B$66 -> 292.35 | AF57: =AN57*$B$70 -> 38.98 | AG57: 0 | AH57: =AN57*$B$74 -> 38.98 | AI57: =AN57-(AN57/1.18) -> 297.30508 | AJ57: =Z57*5% -> 62.68 | AK57: =Z57*3% -> 37.608 | AL57: =AN57-Y57-AD57-AE57-AG57-AI57-AJ57-AK57-AF57-AH57 -> -246.4028 | AM57: =AL57/AN57 -> -0.12642525 | AN57: 1949 | AR57: 3699 | AV57: =SUM(AN57-AI57)-Y57 -> 383.9002 | AW57: =AV57/AN57 -> 0.19697291 | AX57: 8904422504486 | AY57: =Y57/U57 -> 111.996 | AZ57: =AN57/+SUM(Y57/84) -> 129.13447 | BA57: =AN57/U57 -> 172.17314
F58: FBK79382 | G58: B0D3GYYN67 | H58: ET-01-BK-4B | I58: HPC | J58: Oral Care | L58: Ningbo Oral | M58: Nexlev ET-01-BK-4B Sonic Electric Toothbrush Humm - Black - 4 Brush Heads | N58: 85098000 | U58: 2.25 | W58: =U58*2% -> 0.045 | X58: =(U58+W58)*(B$31+(B$31*B$45)) -> 0.5049 | Y58: =(U58+W58+X58)*B$26 -> 251.991 | Z58: =Y58*1.18 -> 297.34938 | AA58: =AN58*4.5% -> 22.455 | AB58: 12 | AC58: 60 | AD58: =AA58+AB58+AC58 -> 94.455 | AE58: =AN58*B$66 -> 74.85 | AF58: =AN58*$B$70 -> 9.98 | AG58: 0 | AH58: =AN58*$B$74 -> 9.98 | AI58: =AN58-(AN58/1.18) -> 76.118644 | AJ58: =Z58*5% -> 14.867469 | AK58: =Z58*3% -> 8.9204814 | AL58: =AN58-Y58-AD58-AE58-AG58-AI58-AJ58-AK58-AF58-AH58 -> -42.162594 | AM58: =AL58/AN58 -> -0.084494177 | AN58: 499 | AR58: 1249 | AV58: =SUM(AN58-AI58)-Y58 -> 170.89036 | AW58: =AV58/AN58 -> 0.34246564 | AX58: 8904422504509 | AY58: =Y58/U58 -> 111.996 | AZ58: =AN58/+SUM(Y58/84) -> 166.33927 | BA58: =AN58/U58 -> 221.77778
F59: FBK79383 | G59: B0D3H36L1T | H59: ET-01-GN-4B | I59: HPC | J59: Oral Care | L59: Ningbo Oral | M59: Nexlev ET-01-GN-4B Sonic Electric Toothbrush Humm - Green - 4 Brush Heads | N59: 85098000 | U59: 2.25 | W59: =U59*2% -> 0.045 | X59: =(U59+W59)*(B$31+(B$31*B$45)) -> 0.5049 | Y59: =(U59+W59+X59)*B$26 -> 251.991 | Z59: =Y59*1.18 -> 297.34938 | AA59: =AN59*4.5% -> 22.455 | AB59: 12 | AC59: 60 | AD59: =AA59+AB59+AC59 -> 94.455 | AE59: =AN59*B$66 -> 74.85 | AF59: =AN59*$B$70 -> 9.98 | AG59: 0 | AH59: =AN59*$B$74 -> 9.98 | AI59: =AN59-(AN59/1.18) -> 76.118644 | AJ59: =Z59*5% -> 14.867469 | AK59: =Z59*3% -> 8.9204814 | AL59: =AN59-Y59-AD59-AE59-AG59-AI59-AJ59-AK59-AF59-AH59 -> -42.162594 | AM59: =AL59/AN59 -> -0.084494177 | AN59: 499 | AR59: 1249 | AV59: =SUM(AN59-AI59)-Y59 -> 170.89036 | AW59: =AV59/AN59 -> 0.34246564 | AX59: 8904422504516 | AY59: =Y59/U59 -> 111.996 | AZ59: =AN59/+SUM(Y59/84) -> 166.33927 | BA59: =AN59/U59 -> 221.77778
F60: FBA79375 | G60: B0D2P6KF4N | H60: ET-03-BL_NE | I60: HPC | J60: Oral Care | L60: Ningbo Oral | M60: ET-03-BL_NE Nexlev Smart Smile Electric Toothbrush Skyblue | N60: 85098000 | U60: 1.48 | W60: =U60*2% -> 0.0296 | X60: =(U60+W60)*(B$31+(B$31*B$45)) -> 0.332112 | Y60: =(U60+W60+X60)*B$26 -> 165.75408 | Z60: =Y60*1.18 -> 195.58981 | AA60: =AN60*5.5% -> 21.945 | AB60: 21 | AC60: 58 | AD60: =AA60+AB60+AC60 -> 100.945 | AE60: =AN60*B$66 -> 59.85 | AF60: =AN60*$B$70 -> 7.98 | AG60: 0 | AH60: =AN60*$B$74 -> 7.98 | AI60: =AN60-(AN60/1.18) -> 60.864407 | AJ60: =Z60*5% -> 9.7794907 | AK60: =Z60*3% -> 5.8676944 | AL60: =AN60-Y60-AD60-AE60-AG60-AI60-AJ60-AK60-AF60-AH60 -> -20.020672 | AM60: =AL60/AN60 -> -0.050177123 | AN60: 399 | AP60: 299 | AR60: 699 | AV60: =SUM(AN60-AI60)-Y60 -> 172.38151 | AW60: =AV60/AN60 -> 0.43203387 | AX60: 8904422504523 | AY60: =Y60/U60 -> 111.996 | AZ60: =AN60/+SUM(Y60/84) -> 202.20317 | BA60: =AN60/U60 -> 269.59459
F61: FBA79373 | G61: B0D2P5TGWK | H61: ET-01-BK_NE | I61: HPC | J61: Oral Care | L61: Ningbo Oral | M61: ET-01-BK_NE Nexlev Smart Smile Electric Toothbrush Black | N61: 85098000 | U61: 2.25 | W61: =U61*2% -> 0.045 | X61: =(U61+W61)*(B$31+(B$31*B$45)) -> 0.5049 | Y61: =(U61+W61+X61)*B$26 -> 251.991 | Z61: =Y61*1.18 -> 297.34938 | AA61: =AN61*5.5% -> 16.445 | AB61: 21 | AC61: 59 | AD61: =AA61+AB61+AC61 -> 96.445 | AE61: =AN61*B$66 -> 44.85 | AG61: 0 | AI61: =AN61-(AN61/1.18) -> 45.610169 | AL61: =AN61-Y61-AD61-AE61-AG61-AI61-AJ61-AK61-AF61-AH61 -> -139.89617 | AM61: =AL61/AN61 -> -0.46788017 | AN61: 299 | AP61: 399 | AR61: 1199 | AT61: Upto 300 no referral | AV61: =SUM(AN61-AI61)-Y61 -> 1.3988305 | AW61: =AV61/AN61 -> 0.0046783629 | AX61: 8904422504356 | AY61: =Y61/U61 -> 111.996 | AZ61: =AN61/+SUM(Y61/84) -> 99.670226 | BA61: =AN61/U61 -> 132.88889
F62: FBA79374 | G62: B0D2P7WLJB | H62: ET-02-GN_NE | I62: HPC | J62: Oral Care | L62: Ningbo Oral | M62: ET-02-GN_NE Nexlev Smart Smile Electric Toothbrush Green | N62: 85098000 | U62: 2.25 | W62: =U62*2% -> 0.045 | X62: =(U62+W62)*(B$31+(B$31*B$45)) -> 0.5049 | Y62: =(U62+W62+X62)*B$26 -> 251.991 | Z62: =Y62*1.18 -> 297.34938 | AA62: =AN62*5.5% -> 16.445 | AB62: 21 | AC62: 58 | AD62: =AA62+AB62+AC62 -> 95.445 | AE62: =AN62*B$66 -> 44.85 | AG62: 0 | AI62: =AN62-(AN62/1.18) -> 45.610169 | AL62: =AN62-Y62-AD62-AE62-AG62-AI62-AJ62-AK62-AF62-AH62 -> -138.89617 | AM62: =AL62/AN62 -> -0.46453568 | AN62: 299 | AP62: 399 | AR62: 1199 | AT62: Upto 300 no referral | AV62: =SUM(AN62-AI62)-Y62 -> 1.3988305 | AW62: =AV62/AN62 -> 0.0046783629 | AX62: 8904422504363 | AY62: =Y62/U62 -> 111.996 | AZ62: =AN62/+SUM(Y62/84) -> 99.670226 | BA62: =AN62/U62 -> 132.88889
F63: FBA79402 | G63: B0D45PFFM6 | H63: DB_DF_BK | I63: HPC | J63: Oral Care | M63: Nexlev DF-01-BK Flosser & ET-01-BK Black Brush Combo | N63: 85098000 | U63: 1.48 | W63: =U63*2% -> 0.0296 | X63: =(U63+W63)*(B$31+(B$31*B$45)) -> 0.332112 | Y63: =(U63+W63+X63)*B$26 -> 165.75408 | Z63: =Y63*1.18 -> 195.58981 | AA63: =AN63*4.5% -> 83.205 | AB63: 12 | AC63: 60 | AD63: =AA63+AB63+AC63 -> 155.205 | AE63: =AN63*B$66 -> 277.35 | AF63: =AN63*$B$70 -> 36.98 | AG63: 0 | AH63: =AN63*$B$74 -> 36.98 | AI63: =AN63-(AN63/1.18) -> 282.05085 | AJ63: =Z63*5% -> 9.7794907 | AK63: =Z63*3% -> 5.8676944 | AL63: =AN63-Y63-AD63-AE63-AG63-AI63-AJ63-AK63-AF63-AH63 -> 879.03289 | AM63: =AL63/AN63 -> 0.47540989 | AN63: 1849 | AR63: 3699 | AV63: =SUM(AN63-AI63)-Y63 -> 1401.1951 | AW63: =AV63/AN63 -> 0.75781237 | AX63: 8904422504608 | AY63: =Y63/U63 -> 111.996 | AZ63: =AN63/+SUM(Y63/84) -> 937.02671 | BA63: =AN63/U63 -> 1249.3243
A64: Referral Fee (<15001) | B64: 0.15 | F64: FBA79262 | G64: B0CYSMBCB8 | H64: SC-02 | I64: Home & Kitchen | J64: Cleaning & Vacumming | L64: Ningbo Elmar | M64: Steam Cleaner-Shine | N64: 85098000 | U64: 10.35 | V64: 10.3 | W64: =U64*2% -> 0.207 | X64: =(U64+W64)*(B$31+(B$31*B$45)) -> 2.32254 | Y64: =(U64+W64+X64)*B$26 -> 1159.1586 | Z64: =Y64*1.18 -> 1367.8071 | AA64: =AN64*4.5% -> 110.205 | AB64: 51 | AC64: 148 | AD64: =AA64+AB64+AC64 -> 309.205 | AE64: =AN64*B$66 -> 367.35 | AF64: =AN64*$B$70 -> 48.98 | AG64: =AN64*B$67 -> 122.45 | AH64: =AN64*$B$74 -> 48.98 | AI64: =AN64-(AN64/1.18) -> 373.57627 | AJ64: =Z64*5% -> 68.390357 | AK64: =Z64*3% -> 41.034214 | AL64: =SUM(AN64-AI64)-Y64-AD64-AE64-AG64-AJ64-AK64-AF64-AH64 -> -90.124443 | AM64: =AL64/SUM(AN64-AI64) -> -0.043424599 | AN64: 2449 | AP64: 2399 | AR64: 6999 | AV64: =SUM(AN64-AI64)-Y64 -> 916.26513 | AW64: =AV64/AN64 -> 0.37413848 | AX64: 8904422504042 | AY64: =Y64/U64 -> 111.996 | AZ64: =AN64/+SUM(Y64/84) -> 177.47011 | BA64: =AN64/U64 -> 236.61836
A65: Referral Fee (>15000) | B65: 0.1 | F65: FBA79263 | G65: B0CYSLCRQS | H65: MR-01 | I65: Home & Kitchen | J65: Cleaning & Vacumming | L65: Ningbo Elmar | M65: Smart Care Mite Remover (Nexlev Dust Mite UV) | N65: 85086000 | U65: 9.4 | W65: =U65*2% -> 0.188 | X65: =(U65+W65)*(B$42+(B$42*B$45)) -> 1.05468 | Y65: =(U65+W65+X65)*B$26 -> 957.8412 | Z65: =Y65*1.18 -> 1130.2526 | AA65: =AN65*4.5% -> 132.705 | AB65: 51 | AC65: 180 | AD65: =AA65+AB65+AC65 -> 363.705 | AE65: =AN65*B$66 -> 442.35 | AF65: =AN65*$B$70 -> 58.98 | AG65: =AN65*B$67 -> 147.45 | AH65: =AN65*$B$74 -> 58.98 | AI65: =AN65-(AN65/1.18) -> 449.84746 | AJ65: =Z65*5% -> 56.512631 | AK65: =Z65*3% -> 33.907578 | AL65: =SUM(AN65-AI65)-Y65-AD65-AE65-AG65-AJ65-AK65-AF65-AH65 -> 379.42613 | AM65: =AL65/SUM(AN65-AI65) -> 0.15182192 | AN65: 2949 | AP65: 2899 | AR65: 5499 | AV65: =SUM(AN65-AI65)-Y65 -> 1541.3113 | AW65: =AV65/AN65 -> 0.52265559 | AX65: 8904422504080 | AY65: =Y65/U65 -> 101.898 | AZ65: =AN65/+SUM(Y65/84) -> 258.61907 | BA65: =AN65/U65 -> 313.7234
A66: AMS | B66: 0.15 | F66: FBA79436 | G66: B0DGTGKPJR | H66: HF-MR-01 | I66: Home & Kitchen | J66: Cleaning & Vacumming | L66: Ningbo Elmar | M66: Dust Mite Remover Hepa Filter | N66: 84213900 | U66: 0.2 | W66: =U66*2% -> 0.004 | X66: =(U66+W66)*(B$43+(B$43*B$45)) -> 0.01683 | Y66: =(U66+W66+X66)*B$26 -> 19.8747 | Z66: =Y66*1.18 -> 23.452146 | AA66: =AN66*7.5% -> 29.925 | AB66: 25 | AC66: 60 | AD66: =AA66+AB66+AC66 -> 114.925 | AE66: =AN66*B$66 -> 59.85 | AF66: =AN66*$B$70 -> 7.98 | AG66: =AN66*B$67 -> 19.95 | AH66: =AN66*$B$74 -> 7.98 | AI66: =AN66-(AN66/1.18) -> 60.864407 | AJ66: =Z66*5% -> 1.1726073 | AK66: =Z66*3% -> 0.70356438 | AL66: =SUM(AN66-AI66)-Y66-AD66-AE66-AG66-AJ66-AK66-AF66-AH66 -> 105.69972 | AM66: =AL66/SUM(AN66-AI66) -> 0.31259567 | AN66: 399 | AR66: 449 | AV66: =SUM(AN66-AI66)-Y66 -> 318.26089 | AW66: =AV66/AN66 -> 0.79764635 | AX66: 8904422504806 | AY66: =Y66/U66 -> 99.3735 | AZ66: =AN66/+SUM(Y66/84) -> 1686.3651 | BA66: =AN66/U66 -> 1995
A67: Returns and Repairs | B67: 0.05 | F67: FBA79265 | G67: B0D2LHNS9B | H67: CR-01 | I67: HPC | J67: Skin Care | L67: ANIONTE INTERNATIONAL(ZHE JIANG) CO., LTD | M67: Smooth Sole Callus Remover | N67: 82142090 | U67: 4.48 | V67: 4.48 | W67: =U67*2% -> 0.0896 | X67: =(U67+W67)*(B$42+(B$42*B$45)) -> 0.502656 | Y67: =(U67+W67+X67)*B$26 -> 456.50304 | Z67: =Y67*1.18 -> 538.67359 | AA67: =AN67*11% -> 98.89 | AB67: 26 | AC67: 59 | AD67: =AA67+AB67+AC67 -> 183.89 | AE67: =AN67*B$72 -> 179.8 | AF67: =AN67*$B$70 -> 17.98 | AH67: =AN67*$B$74 -> 17.98 | AI67: =AN67-(AN67/1.18) -> 137.13559 | AJ67: =Z67*5% -> 26.933679 | AK67: =Z67*3% -> 16.160208 | AL67: =AN67-Y67-AD67-AE67-AG67-AI67-AJ67-AK67-AF67-AH67 -> -137.38252 | AM67: =AL67/AN67 -> -0.15281704 | AN67: 899 | AP67: 799 | AR67: 1999 | AV67: =SUM(AN67-AI67)-Y67 -> 305.36137 | AW67: =AV67/AN67 -> 0.33966782 | AX67: 8904422504172 | AY67: =Y67/U67 -> 101.898 | AZ67: =AN67/+SUM(Y67/84) -> 165.42278 | BA67: =AN67/U67 -> 200.66964
A68: Overheads | B68: 0.05 | F68: FBA79266 | G68: B0D2LGR3GG | H68: T-01 | I68: HPC | J68: Trimmers & Body Groomers | L68: ANIONTE INTERNATIONAL(ZHE JIANG) CO., LTD | M68: Velvet Vibe Multi-Trimmer | N68: 85101000 | U68: 3.96 | V68: 3.96 | W68: =U68*2% -> 0.0792 | X68: =(U68+W68)*(B$31+(B$31*B$45)) -> 0.888624 | Y68: =(U68+W68+X68)*B$26 -> 443.50416 | Z68: =Y68*1.18 -> 523.33491 | AA68: =AN68*7% -> 69.93 | AB68: 26 | AC68: 59 | AD68: =AA68+AB68+AC68 -> 154.93 | AE68: =AN68*B$72 -> 199.8 | AF68: =AN68*$B$70 -> 19.98 | AG68: 0 | AH68: =AN68*$B$74 -> 19.98 | AI68: =AN68-(AN68/1.18) -> 152.38983 | AJ68: =Z68*5% -> 26.166745 | AK68: =Z68*3% -> 15.700047 | AL68: =AN68-Y68-AD68-AE68-AG68-AI68-AJ68-AK68-AF68-AH68 -> -33.450783 | AM68: =AL68/AN68 -> -0.033484267 | AN68: 999 | AP68: 999 | AR68: 1499 | AV68: =SUM(AN68-AI68)-Y68 -> 403.10601 | AW68: =AV68/AN68 -> 0.40350952 | AX68: 8904422504059 | AY68: =Y68/U68 -> 111.996 | AZ68: =AN68/+SUM(Y68/84) -> 189.2113 | BA68: =AN68/U68 -> 252.27273
A69: Finance | B69: 0.03 | F69: FBA79267 | G69: B0D2LD6BYJ | H69: T-02 | I69: HPC | J69: Trimmers & Body Groomers | L69: ANIONTE INTERNATIONAL(ZHE JIANG) CO., LTD | M69: Velvet Vibe Plus Multi-Trimmer | N69: 85101000 | U69: 4.65 | V69: 4.65 | W69: =U69*2% -> 0.093 | X69: =(U69+W69)*(B$31+(B$31*B$45)) -> 1.04346 | Y69: =(U69+W69+X69)*B$26 -> 520.7814 | Z69: =Y69*1.18 -> 614.52205 | AA69: =AN69*9.5% -> 113.905 | AB69: 51 | AC69: 59 | AD69: =AA69+AB69+AC69 -> 223.905 | AE69: =AN69*B$72 -> 239.8 | AF69: =AN69*$B$70 -> 23.98 | AG69: 0 | AH69: =AN69*$B$74 -> 23.98 | AI69: =AN69-(AN69/1.18) -> 182.89831 | AJ69: =Z69*5% -> 30.726103 | AK69: =Z69*3% -> 18.435662 | AL69: =AN69-Y69-AD69-AE69-AG69-AI69-AJ69-AK69-AF69-AH69 -> -65.506469 | AM69: =AL69/AN69 -> -0.054634253 | AN69: 1199 | AP69: 1099 | AR69: 1899 | AV69: =SUM(AN69-AI69)-Y69 -> 495.32029 | AW69: =AV69/AN69 -> 0.41311117 | AX69: 8904422504066 | AY69: =Y69/U69 -> 111.996 | AZ69: =AN69/+SUM(Y69/84) -> 193.394 | BA69: =AN69/U69 -> 257.84946
A70: Coupon | B70: 0.02 | F70: FBA79268 | G70: B0D383WQPB | H70: GS-05 | I70: Home & Kitchen | J70: Fabric Care | L70: Zhejiang Huaguang | M70: Nexlev Smart Care Travel Steamer - Nomad | N70: 85167990 | U70: 7.5 | V70: 7.5 | W70: =U70*2% -> 0.15 | X70: =(U70+W70)*(B$31+(B$31*B$45)) -> 1.683 | Y70: =(U70+W70+X70)*B$26 -> 839.97 | Z70: =Y70*1.18 -> 991.1646 | AA70: =AN70*4.5% -> 80.955 | AB70: 51 | AC70: 77 | AD70: =AA70+AB70+AC70 -> 208.955 | AE70: =AN70*B$66 -> 269.85 | AF70: =AN70*$B$70 -> 35.98 | AG70: =AN70*B$67 -> 89.95 | AH70: =AN70*$B$74 -> 35.98 | AI70: =AN70-(AN70/1.18) -> 274.42373 | AJ70: =Z70*5% -> 49.55823 | AK70: =Z70*3% -> 29.734938 | AL70: =AN70-Y70-AD70-AE70-AG70-AI70-AJ70-AK70-AF70-AH70 -> -35.401897 | AM70: =AL70/AN70 -> -0.019678653 | AN70: 1799 | AP70: 1799 | AR70: 3999 | AV70: =SUM(AN70-AI70)-Y70 -> 684.60627 | AW70: =AV70/AN70 -> 0.38054823 | AX70: 8904422504097 | AY70: =Y70/U70 -> 111.996 | AZ70: =AN70/+SUM(Y70/84) -> 179.90643 | BA70: =AN70/U70 -> 239.86667
F71: FBA79269 | H71: LR-01 | I71: Home & Kitchen | J71: Fabric Care | M71: Nexlev Fabric Lint Remover | N71: 85167990 | U71: 3.7 | W71: =U71*2% -> 0.074 | X71: =(U71+W71)*(B$31+(B$31*B$45)) -> 0.83028 | Y71: =(U71+W71+X71)*B$26 -> 414.3852 | Z71: =Y71*1.18 -> 488.97454 | AA71: =AN71*6.5% -> 64.935 | AB71: 47 | AC71: 204 | AD71: =AA71+AB71+AC71 -> 315.935 | AE71: =AN71*B$66 -> 149.85 | AF71: =AN71*$B$70 -> 19.98 | AG71: =AN71*B$67 -> 49.95 | AH71: =AN71*$B$74 -> 19.98 | AI71: =AN71-(AN71/1.18) -> 152.38983 | AJ71: =Z71*5% -> 24.448727 | AK71: =Z71*3% -> 14.669236 | AL71: =AN71-Y71-AD71-AE71-AG71-AI71-AJ71-AK71-AF71-AH71 -> -162.58799 | AM71: =AL71/AN71 -> -0.16275074 | AN71: 999 | AP71: 949 | AR71: 1499 | AV71: =SUM(AN71-AI71)-Y71 -> 432.22497 | AW71: =AV71/AN71 -> 0.43265763 | AX71: 8904422504073 | AY71: =Y71/U71 -> 111.996 | AZ71: =AN71/+SUM(Y71/84) -> 202.50723 | BA71: =AN71/U71 -> 270
A72: AMS -HPC | B72: 0.2 | F72: FBA79271 | G72: B0D83Q7L8W | H72: V-01 | I72: HPC | J72: Hair Care | L72: ANIONTE INTERNATIONAL(ZHE JIANG) CO., LTD | M72: Nexlev Volumizer | N72: 85163100 | U72: 5.5 | W72: =U72*2% -> 0.11 | X72: =(U72+W72)*(B$31+(B$31*B$45)) -> 1.2342 | Y72: =(U72+W72+X72)*B$26 -> 615.978 | Z72: =Y72*1.18 -> 726.85404 | AA72: =AN72*9.5% -> 142.405 | AB72: 51 | AC72: 77 | AD72: =AA72+AB72+AC72 -> 270.405 | AE72: =AN72*B$72 -> 299.8 | AF72: =AN72*$B$70 -> 29.98 | AG72: =AN72*B$67 -> 74.95 | AH72: =AN72*$B$74 -> 29.98 | AI72: =AN72-(AN72/1.18) -> 228.66102 | AJ72: =Z72*5% -> 36.342702 | AK72: =Z72*3% -> 21.805621 | AL72: =AN72-Y72-AD72-AE72-AG72-AI72-AJ72-AK72-AF72-AH72 -> -108.90234 | AM72: =AL72/AN72 -> -0.072649993 | AN72: 1499 | AP72: 1399 | AR72: 3499 | AV72: =SUM(AN72-AI72)-Y72 -> 654.36098 | AW72: =AV72/AN72 -> 0.43653168 | AX72: 8904422504103 | AY72: =Y72/U72 -> 111.996 | AZ72: =AN72/+SUM(Y72/84) -> 204.41639 | BA72: =AN72/U72 -> 272.54545
A73: AMS- Hair care | B73: 0.15 | F73: FBK79271 | G73: B0DQ8W1RBV | H73: V-01 Rose Gold | I73: HPC | J73: Hair Care | L73: ANIONTE INTERNATIONAL(ZHE JIANG) CO., LTD | M73: Nexlev Volumizer | N73: 85163100 | U73: 5 | W73: =U73*2% -> 0.1 | X73: =(U73+W73)*(B$31+(B$31*B$45)) -> 1.122 | Y73: =(U73+W73+X73)*B$26 -> 559.98 | Z73: =Y73*1.18 -> 660.7764 | AA73: =AN73*9.5% -> 142.405 | AB73: 51 | AC73: 77 | AD73: =AA73+AB73+AC73 -> 270.405 | AE73: =AN73*B$72 -> 299.8 | AF73: =AN73*$B$70 -> 29.98 | AG73: =AN73*B$67 -> 74.95 | AH73: =AN73*$B$74 -> 29.98 | AI73: =AN73-(AN73/1.18) -> 228.66102 | AJ73: =Z73*5% -> 33.03882 | AK73: =Z73*3% -> 19.823292 | AL73: =AN73-Y73-AD73-AE73-AG73-AI73-AJ73-AK73-AF73-AH73 -> -47.618129 | AM73: =AL73/AN73 -> -0.031766597 | AN73: 1499 | AP73: 1299 | AR73: 3499 | AV73: =SUM(AN73-AI73)-Y73 -> 710.35898 | AW73: =AV73/AN73 -> 0.47388858 | AX73: 8904422504103 | AY73: =Y73/U73 -> 111.996 | AZ73: =AN73/+SUM(Y73/84) -> 224.85803 | BA73: =AN73/U73 -> 299.8
A74: SMM | B74: 0.02 | F74: FBA79272 | G74: B0D2LFMY48 | H74: HS-01 | I74: HPC | J74: Hair Care | L74: ANIONTE INTERNATIONAL(ZHE JIANG) CO., LTD | M74: Hair Straightner - Black | N74: 85163200 | U74: 2.87 | V74: 2.87 | W74: =U74*2% -> 0.0574 | X74: =(U74+W74)*(B$31+(B$31*B$45)) -> 0.644028 | Y74: =(U74+W74+X74)*B$26 -> 321.42852 | Z74: =Y74*1.18 -> 379.28565 | AA74: =AN74*10% -> 64.9 | AB74: 25 | AC74: 73 | AD74: =AA74+AB74+AC74 -> 162.9 | AE74: =AN74*B$72 -> 129.8 | AF74: =AN74*$B$70 -> 12.98 | AG74: =AN74*B$67 -> 32.45 | AH74: =AN74*$B$74 -> 12.98 | AI74: =AN74-(AN74/1.18) -> 99 | AJ74: =Z74*5% -> 18.964283 | AK74: =Z74*3% -> 11.37857 | AL74: =AN74-Y74-AD74-AE74-AG74-AI74-AJ74-AK74-AF74-AH74 -> -152.88137 | AM74: =AL74/AN74 -> -0.23556452 | AN74: 649 | AR74: 1299 | AV74: =SUM(AN74-AI74)-Y74 -> 228.57148 | AW74: =AV74/AN74 -> 0.35219026 | AX74: 8904422504110 | AY74: =Y74/U74 -> 111.996 | AZ74: =AN74/+SUM(Y74/84) -> 169.60536 | BA74: =AN74/U74 -> 226.1324
F75: FBA79273 | G75: B0D2LKB4BJ | H75: HS-02 | I75: Home & Kitchen | J75: Fabric Care | L75: ANIONTE INTERNATIONAL(ZHE JIANG) CO., LTD | M75: Hair Straightner - Purple | N75: 85163200 | U75: 2.96 | V75: 2.96 | W75: =U75*2% -> 0.0592 | X75: =(U75+W75)*(B$31+(B$31*B$45)) -> 0.664224 | Y75: =(U75+W75+X75)*B$26 -> 331.50816 | Z75: =Y75*1.18 -> 391.17963 | AA75: =AN75*10% -> 74.9 | AB75: 25 | AC75: 73 | AD75: =AA75+AB75+AC75 -> 172.9 | AE75: =AN75*B$66 -> 112.35 | AF75: =AN75*$B$70 -> 14.98 | AG75: =AN75*B$67 -> 37.45 | AH75: =AN75*$B$74 -> 14.98 | AI75: =AN75-(AN75/1.18) -> 114.25424 | AJ75: =Z75*5% -> 19.558981 | AK75: =Z75*3% -> 11.735389 | AL75: =AN75-Y75-AD75-AE75-AG75-AI75-AJ75-AK75-AF75-AH75 -> -80.716768 | AM75: =AL75/AN75 -> -0.10776604 | AN75: 749 | AR75: 1499 | AV75: =SUM(AN75-AI75)-Y75 -> 303.2376 | AW75: =AV75/AN75 -> 0.40485661 | AX75: 8904422504127 | AY75: =Y75/U75 -> 111.996 | AZ75: =AN75/+SUM(Y75/84) -> 189.78718 | BA75: =AN75/U75 -> 253.04054
B76: SKU Cancelled | F76: FBA79275 | H76: HD-01 | I76: Hair Care | M76: Hair Dryer | N76: 85163100 | U76: 4.07 | W76: =U76*2% -> 0.0814 | X76: =(U76+W76)*(B$31+(B$31*B$45)) -> 0.913308 | Y76: =(U76+W76+X76)*B$26 -> 455.82372 | Z76: =Y76*1.18 -> 537.87199 | AA76: =AN76*6.5% -> 123.435 | AB76: 47 | AC76: 204 | AD76: =AA76+AB76+AC76 -> 374.435 | AE76: =AN76*B$66 -> 284.85 | AF76: =AN76*$B$70 -> 37.98 | AG76: =AN76*B$67 -> 94.95 | AH76: =AN76*$B$74 -> 37.98 | AI76: =AN76-(AN76/1.18) -> 289.67797 | AJ76: =Z76*5% -> 26.893599 | AK76: =Z76*3% -> 16.13616 | AL76: =AN76-Y76-AD76-AE76-AG76-AI76-AJ76-AK76-AF76-AH76 -> 280.27355 | AM76: =AL76/AN76 -> 0.14759008 | AN76: 1899 | AV76: =SUM(AN76-AI76)-Y76 -> 1153.4983 | AW76: =AV76/AN76 -> 0.60742407 | AY76: =Y76/U76 -> 111.996 | AZ76: =AN76/+SUM(Y76/84) -> 349.95107 | BA76: =AN76/U76 -> 466.58477
B77: SKU Cancelled | H77: HD-02 | I77: Hair Care | M77: Hair Dryer-Ionic | N77: 85163100 | U77: 4.63 | W77: =U77*2% -> 0.0926 | X77: =(U77+W77)*(B$31+(B$31*B$45)) -> 1.038972 | Y77: =(U77+W77+X77)*B$26 -> 518.54148 | Z77: =Y77*1.18 -> 611.87895 | AA77: =AN77*6.5% -> 123.435 | AB77: 47 | AC77: 204 | AD77: =AA77+AB77+AC77 -> 374.435 | AE77: =AN77*B$66 -> 284.85 | AF77: =AN77*$B$70 -> 37.98 | AG77: =AN77*B$67 -> 94.95 | AH77: =AN77*$B$74 -> 37.98 | AI77: =AN77-(AN77/1.18) -> 289.67797 | AJ77: =Z77*5% -> 30.593947 | AK77: =Z77*3% -> 18.356368 | AL77: =AN77-Y77-AD77-AE77-AG77-AI77-AJ77-AK77-AF77-AH77 -> 211.63524 | AM77: =AL77/AN77 -> 0.11144562 | AN77: 1899 | AV77: =SUM(AN77-AI77)-Y77 -> 1090.7806 | AW77: =AV77/AN77 -> 0.57439734 | AY77: =Y77/U77 -> 111.996 | AZ77: =AN77/+SUM(Y77/84) -> 307.62438 | BA77: =AN77/U77 -> 410.15119
F78: FBA79453 | G78: B0D2LFMY48 | H78: HS-01_NE | I78: Home & Kitchen | J78: Fabric Care | L78: ANIONTE INTERNATIONAL(ZHE JIANG) CO., LTD | M78: Nexlev Hair Straightener - Black New | N78: 85163100 | U78: 2.87 | W78: =U78*2% -> 0.0574 | X78: =(U78+W78)*(B$31+(B$31*B$45)) -> 0.644028 | Y78: =(U78+W78+X78)*B$26 -> 321.42852 | Z78: =Y78*1.18 -> 379.28565 | AA78: =AN78*7% -> 55.93 | AB78: 26 | AC78: 59 | AD78: =AA78+AB78+AC78 -> 140.93 | AE78: =AN78*B$66 -> 119.85 | AF78: =AN78*$B$70 -> 15.98 | AG78: =AN78*B$67 -> 39.95 | AI78: =AN78-(AN78/1.18) -> 121.88136 | AJ78: =Z78*5% -> 18.964283 | AK78: =Z78*3% -> 11.37857 | AL78: =AN78-Y78-AD78-AE78-AG78-AI78-AJ78-AK78-AF78-AH78 -> 8.6372718 | AM78: =AL78/AN78 -> 0.010810102 | AN78: 799 | AR78: 1299 | AV78: =SUM(AN78-AI78)-Y78 -> 355.69012 | AW78: =AV78/AN78 -> 0.44516912 | AY78: =Y78/U78 -> 111.996 | AZ78: =AN78/+SUM(Y78/84) -> 208.80537 | BA78: =AN78/U78 -> 278.39721
F79: FBA79454 | G79: B0D2LKB4BJ | H79: HS-02_NE | I79: Home & Kitchen | J79: Fabric Care | L79: ANIONTE INTERNATIONAL(ZHE JIANG) CO., LTD | M79: Nexlev Hair Straightener - Purple New | N79: 85163100 | U79: 2.96 | W79: =U79*2% -> 0.0592 | X79: =(U79+W79)*(B$31+(B$31*B$45)) -> 0.664224 | Y79: =(U79+W79+X79)*B$26 -> 331.50816 | Z79: =Y79*1.18 -> 391.17963 | AA79: =AN79*7% -> 59.43 | AB79: 26 | AC79: 59 | AD79: =AA79+AB79+AC79 -> 144.43 | AE79: =AN79*B$66 -> 127.35 | AF79: =AN79*$B$70 -> 16.98 | AG79: =AN79*B$67 -> 42.45 | AI79: =AN79-(AN79/1.18) -> 129.50847 | AJ79: =Z79*5% -> 19.558981 | AK79: =Z79*3% -> 11.735389 | AL79: =AN79-Y79-AD79-AE79-AG79-AI79-AJ79-AK79-AF79-AH79 -> 25.478995 | AM79: =AL79/AN79 -> 0.030010595 | AN79: 849 | AP79: 799 | AR79: 1499 | AV79: =SUM(AN79-AI79)-Y79 -> 387.98337 | AW79: =AV79/AN79 -> 0.45698865 | AY79: =Y79/U79 -> 111.996 | AZ79: =AN79/+SUM(Y79/84) -> 215.12593 | BA79: =AN79/U79 -> 286.82432
F80: FBA79276 | G80: B0D2LJSQXZ | H80: SM-01 | I80: Home & Kitchen | J80: Cleaning & Vacumming | L80: Zhejiang Huaguang | M80: Steam Mop | N80: 85098000 | U80: 17.5 | W80: =U80*2% -> 0.35 | X80: =(U80+W80)*(B$31+(B$31*B$45)) -> 3.927 | Y80: =(U80+W80+X80)*B$26 -> 1959.93 | Z80: =Y80*1.18 -> 2312.7174 | AA80: =AN80*4.5% -> 170.955 | AB80: 51 | AC80: 214 | AD80: =AA80+AB80+AC80 -> 435.955 | AE80: =AN80*B$66 -> 569.85 | AF80: =AN80*$B$70 -> 75.98 | AG80: =AN80*B$67 -> 189.95 | AH80: =AN80*$B$74 -> 75.98 | AI80: =AN80-(AN80/1.18) -> 579.50847 | AJ80: =Z80*5% -> 115.63587 | AK80: =Z80*3% -> 69.381522 | AL80: =SUM(AN80-AI80)-Y80-AD80-AE80-AG80-AJ80-AK80-AF80-AH80 -> -273.17087 | AM80: =AL80/SUM(AN80-AI80) -> -0.084849071 | AN80: 3799 | AP80: 3799 | AR80: 8999 | AV80: =SUM(AN80-AI80)-Y80 -> 1259.5615 | AW80: =AV80/AN80 -> 0.33155081 | AX80: 8904422504202 | AY80: =Y80/U80 -> 111.996 | AZ80: =AN80/+SUM(Y80/84) -> 162.8201 | BA80: =AN80/U80 -> 217.08571
F81: FBA79277 | G81: B0D672NXC8 | H81: SC-03 | I81: Home & Kitchen | J81: Cleaning & Vacumming | L81: Zhejiang Huaguang | M81: Steam Cleaner-Heavy Duty | N81: 85167990 | U81: 29.5 | V81: 29.5 | W81: =U81*2% -> 0.59 | X81: =(U81+W81)*(B$31+(B$31*B$45)) -> 6.6198 | Y81: =(U81+W81+X81)*B$26 -> 3303.882 | Z81: =Y81*1.18 -> 3898.5808 | AA81: =AN81*8% -> 559.92 | AB81: 65 | AC81: 327 | AD81: =AA81+AB81+AC81 -> 951.92 | AE81: 0 | AF81: 0 | AG81: =AN81*B$67 -> 349.95 | AI81: =AN81-(AN81/1.18) -> 1067.6441 | AJ81: =Z81*5% -> 194.92904 | AK81: =Z81*3% -> 116.95742 | AL81: =SUM(AN81-AI81)-Y81-AD81-AE81-AG81-AJ81-AK81-AF81-AH81 -> 1013.7175 | AM81: =AL81/SUM(AN81-AI81) -> 0.17090822 | AN81: 6999 | AP81: 6999 | AR81: 11999 | AV81: =SUM(AN81-AI81)-Y81 -> 2627.4739 | AW81: =AV81/AN81 -> 0.37540705 | AX81: 8904422504240 | AY81: =Y81/U81 -> 111.996 | AZ81: =AN81/+SUM(Y81/84) -> 177.94703 | BA81: =AN81/U81 -> 237.25424
F82: FBA79279 | G82: B0D8445KJN | H82: LR-01 | I82: Home & Kitchen | J82: Fabric Care | L82: Ningbo Shunway Electrical Appliances CO.,LTD | M82: Nexlev Lint Remover - Mini | N82: 85167990 | U82: 3.4 | W82: =U82*2% -> 0.068 | X82: =(U82+W82)*(B$31+(B$31*B$45)) -> 0.76296 | Y82: =(U82+W82+X82)*B$26 -> 380.7864 | Z82: =Y82*1.18 -> 449.32795 | AA82: =AN82*4.5% -> 31.455 | AB82: 51 | AC82: 59 | AD82: =AA82+AB82+AC82 -> 141.455 | AE82: =AN82*B$66 -> 104.85 | AF82: =AN82*$B$70 -> 13.98 | AG82: =AN82*B$67 -> 34.95 | AH82: =AN82*$B$74 -> 13.98 | AI82: =AN82-(AN82/1.18) -> 106.62712 | AJ82: =Z82*5% -> 22.466398 | AK82: =Z82*3% -> 13.479839 | AL82: =SUM(AN82-AI82)-Y82-AD82-AE82-AG82-AJ82-AK82-AF82-AH82 -> -133.57475 | AM82: =AL82/SUM(AN82-AI82) -> -0.225491 | AN82: 699 | AR82: 1499 | AV82: =SUM(AN82-AI82)-Y82 -> 211.58648 | AW82: =AV82/AN82 -> 0.30269883 | AX82: 8904422504189 | AY82: =Y82/U82 -> 111.996 | AZ82: =AN82/+SUM(Y82/84) -> 154.19668 | BA82: =AN82/U82 -> 205.58824
F83: FBA79280 | G83: B0D845B2DG | H83: LR-02 | I83: Home & Kitchen | J83: Fabric Care | L83: Ningbo Shunway Electrical Appliances CO.,LTD | M83: Nexlev Lint Remover | N83: 85167990 | U83: 6.8 | V83: 6.8 | W83: =U83*2% -> 0.136 | X83: =(U83+W83)*(B$31+(B$31*B$45)) -> 1.52592 | Y83: =(U83+W83+X83)*B$26 -> 761.5728 | Z83: =Y83*1.18 -> 898.6559 | AA83: =AN83*4.5% -> 65.205 | AB83: 51 | AC83: 76 | AD83: =AA83+AB83+AC83 -> 192.205 | AE83: =AN83*B$66 -> 217.35 | AF83: =AN83*$B$70 -> 28.98 | AG83: =AN83*B$67 -> 72.45 | AH83: =AN83*$B$74 -> 28.98 | AI83: =AN83-(AN83/1.18) -> 221.0339 | AJ83: =Z83*5% -> 44.932795 | AK83: =Z83*3% -> 26.959677 | AL83: =SUM(AN83-AI83)-Y83-AD83-AE83-AG83-AJ83-AK83-AF83-AH83 -> -145.46417 | AM83: =AL83/SUM(AN83-AI83) -> -0.11845944 | AN83: 1449 | AP83: 1449 | AR83: 2999 | AV83: =SUM(AN83-AI83)-Y83 -> 466.3933 | AW83: =AV83/AN83 -> 0.32187253 | AX83: 8904422504196 | AY83: =Y83/U83 -> 111.996 | AZ83: =AN83/+SUM(Y83/84) -> 159.82188 | BA83: =AN83/U83 -> 213.08824
F84: FBA79278 | G84: B0D86ZC9YT | H84: HD-01 | I84: HPC | J84: Hair Care | L84: NINGBO MICROSOYA ELECTRIC APPLIANCE CO.,LTD | M84: Nexlev Hair Dryer | N84: 85163100 | U84: =5.45+0.4 -> 5.85 | V84: 5.85 | W84: =U84*2% -> 0.117 | X84: =(U84+W84)*(B$31+(B$31*B$45)) -> 1.31274 | Y84: =(U84+W84+X84)*B$26 -> 655.1766 | Z84: =Y84*1.18 -> 773.10839 | AA84: =AN84*9.5% -> 142.405 | AB84: 51 | AC84: 77 | AD84: =AA84+AB84+AC84 -> 270.405 | AE84: =AN84*B$72 -> 299.8 | AF84: =AN84*$B$70 -> 29.98 | AG84: =AN84*B$67 -> 74.95 | AH84: =AN84*$B$74 -> 29.98 | AI84: =AN84-(AN84/1.18) -> 228.66102 | AJ84: =Z84*5% -> 38.655419 | AK84: =Z84*3% -> 23.193252 | AL84: =AN84-Y84-AD84-AE84-AG84-AI84-AJ84-AK84-AF84-AH84 -> -151.80129 | AM84: =AL84/AN84 -> -0.10126837 | AN84: 1499 | AP84: 1399 | AR84: 2499 | AV84: =SUM(AN84-AI84)-Y84 -> 615.16238 | AW84: =AV84/AN84 -> 0.41038184 | AX84: 8904422504233 | AY84: =Y84/U84 -> 111.996 | AZ84: =AN84/+SUM(Y84/84) -> 192.18635 | BA84: =AN84/U84 -> 256.23932
F85: FBA79332 | G85: B0D63FKYZ5 | H85: HM-01 | I85: HPC | J85: Hair Care | L85: Wenzhou Huifan Electric Appliances Co., Ltd. | M85: Scalp Massager | N85: 90191020 | U85: 4.5 | V85: 4.1 | W85: =U85*2% -> 0.09 | X85: =(U85+W85)*(B$42+(B$42*B$45)) -> 0.5049 | Y85: =(U85+W85+X85)*B$26 -> 458.541 | Z85: =Y85*1.12 -> 513.56592 | AA85: =AN85*7.5% -> 71.925 | AB85: 51 | AC85: 59 | AD85: =AA85+AB85+AC85 -> 181.925 | AE85: =AN85*B$72 -> 191.8 | AF85: =AN85*$B$70 -> 19.18 | AG85: =AN85*B$67 -> 47.95 | AH85: =AN85*$B$74 -> 19.18 | AI85: =AN85-(AN85/1.05) -> 45.666667 | AJ85: =Z85*5% -> 25.678296 | AK85: =Z85*3% -> 15.406978 | AL85: =AN85-Y85-AD85-AE85-AG85-AI85-AJ85-AK85-AF85-AH85 -> -46.32794 | AM85: =AL85/AN85 -> -0.048308593 | AN85: 959 | AP85: 1029 | AR85: 2099 | AV85: =SUM(AN85-AI85)-Y85 -> 454.79233 | AW85: =AV85/AN85 -> 0.47423601 | AX85: 8904422504219 | AY85: =Y85/U85 -> 101.898 | AZ85: =AN85/+SUM(Y85/84) -> 175.67895 | BA85: =AN85/U85 -> 213.11111
F86: FBA79462 | G86: B0D8TKMRM4 | H86: HM-01 | I86: HPC | J86: Hair Care | L86: Wenzhou Huifan Electric Appliances Co., Ltd. | M86: Scalp Massager-Pet Version | N86: 90191020 | U86: 4.95 | W86: =U86*2% -> 0.099 | X86: =(U86+W86)*(B$42+(B$42*B$45)) -> 0.55539 | Y86: =(U86+W86+X86)*B$26 -> 504.3951 | Z86: =Y86*1.12 -> 564.92251 | AA86: =AN86*13.5% -> 148.365 | AB86: 47 | AC86: 78 | AD86: =AA86+AB86+AC86 -> 273.365 | AE86: =AN86*B$66 -> 164.85 | AF86: =AN86*$B$70 -> 21.98 | AG86: =AN86*B$67 -> 54.95 | AH86: =AN86*$B$74 -> 21.98 | AI86: =AN86-(AN86/1.12) -> 117.75 | AJ86: =Z86*5% -> 28.246126 | AK86: =Z86*3% -> 16.947675 | AL86: =AN86-Y86-AD86-AE86-AG86-AI86-AJ86-AK86-AF86-AH86 -> -105.4639 | AM86: =AL86/AN86 -> -0.095963513 | AN86: 1099 | AR86: 2099 | AV86: =SUM(AN86-AI86)-Y86 -> 476.8549 | AW86: =AV86/AN86 -> 0.43389891 | AY86: =Y86/U86 -> 101.898 | AZ86: =AN86/+SUM(Y86/84) -> 183.02319 | BA86: =AN86/U86 -> 222.0202
F87: FBA79333 | G87: B0D63DTKQB | H87: HM-02 | I87: HPC | J87: Hair Care | L87: Shenzhen Phenitech Technology Co.,Ltd | M87: Scalp Massager Pro | N87: 90191020 | U87: 6 | V87: 6 | W87: =U87*2% -> 0.12 | X87: =(U87+W87)*(B$42+(B$42*B$45)) -> 0.6732 | Y87: =(U87+W87+X87)*B$26 -> 611.388 | Z87: =Y87*1.12 -> 684.75456 | AA87: =AN87*14.5% -> 188.355 | AB87: 51 | AC87: 59 | AD87: =AA87+AB87+AC87 -> 298.355 | AE87: =AN87*B$72 -> 259.8 | AF87: =AN87*$B$70 -> 25.98 | AG87: =AN87*B$67 -> 64.95 | AH87: =AN87*$B$74 -> 25.98 | AI87: =AN87-(AN87/1.05) -> 61.857143 | AJ87: =Z87*5% -> 34.237728 | AK87: =Z87*3% -> 20.542637 | AL87: =AN87-Y87-AD87-AE87-AG87-AI87-AJ87-AK87-AF87-AH87 -> -104.09051 | AM87: =AL87/AN87 -> -0.080131261 | AN87: 1299 | AP87: 1328 | AR87: 2699 | AV87: =SUM(AN87-AI87)-Y87 -> 625.75486 | AW87: =AV87/AN87 -> 0.48172044 | AX87: 8904422504226 | AY87: =Y87/U87 -> 101.898 | AZ87: =AN87/+SUM(Y87/84) -> 178.47259 | BA87: =AN87/U87 -> 216.5
F88: FBA79346 | G88: B0D25LNDSY | H88: ETC-04-WH | I88: HPC | J88: Oral Care | L88: Ningbo Oral | M88: Electric Toothbrush - C Type - White-Sparkle Pro | N88: 85098000 | U88: 3.09 | V88: 3.15 | W88: =U88*2% -> 0.0618 | X88: =(U88+W88)*(B$31+(B$31*B$45)) -> 0.693396 | Y88: =(U88+W88+X88)*B$26 -> 346.06764 | Z88: =Y88*1.18 -> 408.35982 | AA88: =AN88*7.5% -> 59.925 | AB88: 26 | AC88: 59 | AD88: =AA88+AB88+AC88 -> 144.925 | AE88: =AN88*B$72 -> 159.8 | AG88: 0 | AI88: =AN88-(AN88/1.18) -> 121.88136 | AJ88: =Z88*5% -> 20.417991 | AK88: =Z88*3% -> 12.250794 | AL88: =AN88-Y88-AD88-AE88-AG88-AI88-AJ88-AK88-AF88-AH88 -> -6.3427811 | AM88: =AL88/AN88 -> -0.0079383994 | AN88: 799 | AR88: 1499 | AV88: =SUM(AN88-AI88)-Y88 -> 331.051 | AW88: =AV88/AN88 -> 0.41433167 | AX88: 8904422504271 | AY88: =Y88/U88 -> 111.996 | AZ88: =AN88/+SUM(Y88/84) -> 193.93897 | BA88: =AN88/U88 -> 258.57605
F89: FBA79347 | G89: B0D842173P | H89: ETC-05-PI | I89: HPC | J89: Oral Care | L89: Ningbo Oral | M89: Electric Toothbrush - C Type - Pink-Sparkle Pro | N89: 85098000 | U89: 3.15 | V89: 3.15 | W89: =U89*2% -> 0.063 | X89: =(U89+W89)*(B$31+(B$31*B$45)) -> 0.70686 | Y89: =(U89+W89+X89)*B$26 -> 352.7874 | Z89: =Y89*1.18 -> 416.28913 | AA89: =AN89*7.5% -> 59.925 | AB89: 26 | AC89: 59 | AD89: =AA89+AB89+AC89 -> 144.925 | AE89: =AN89*B$72 -> 159.8 | AG89: 0 | AI89: =AN89-(AN89/1.18) -> 121.88136 | AJ89: =Z89*5% -> 20.814457 | AK89: =Z89*3% -> 12.488674 | AL89: =AN89-Y89-AD89-AE89-AG89-AI89-AJ89-AK89-AF89-AH89 -> -13.696886 | AM89: =AL89/AN89 -> -0.017142536 | AN89: 799 | AP89: 749 | AR89: 1499 | AV89: =SUM(AN89-AI89)-Y89 -> 324.33124 | AW89: =AV89/AN89 -> 0.40592146 | AX89: 8904422504554 | AY89: =Y89/U89 -> 111.996 | AZ89: =AN89/+SUM(Y89/84) -> 190.24489 | BA89: =AN89/U89 -> 253.65079
F90: FBA79349 | G90: B0D9KDQCCM | H90: SW-01 | I90: Home & Kitchen | J90: Fabric Care | K90: 12% GST | L90: Ningbo Shunway Electrical Appliances CO.,LTD | M90: Portable Sewing Machine | N90: 84521021 | U90: 3.46 | V90: 3.4 | W90: =U90*2% -> 0.0692 | X90: =(U90+W90)*(B$42+(B$42*B$45)) -> 0.388212 | Y90: =(U90+W90+X90)*B$26 -> 352.56708 | Z90: =Y90*1.12 -> 394.87513 | AA90: =AN90*6.5% -> 77.935 | AB90: 50 | AC90: 79 | AD90: =AA90+AB90+AC90 -> 206.935 | AE90: =AN90*B$66 -> 179.85 | AF90: =AN90*$B$70 -> 23.98 | AG90: =AN90*B$67 -> 59.95 | AH90: =AN90*$B$74 -> 23.98 | AI90: =AN90-(AN90/1.18) -> 182.89831 | AJ90: =Z90*5% -> 19.743756 | AK90: =Z90*3% -> 11.846254 | AL90: =AN90-Y90-AD90-AE90-AG90-AI90-AJ90-AK90-AF90-AH90 -> 137.2496 | AM90: =AL90/AN90 -> 0.11447006 | AN90: 1199 | AP90: 1199 | AR90: 1299 | AV90: =SUM(AN90-AI90)-Y90 -> 663.53461 | AW90: =AV90/AN90 -> 0.55340668 | AX90: 8904422504493 | AY90: =Y90/U90 -> 101.898 | AZ90: =AN90/+SUM(Y90/84) -> 285.66479 | BA90: =AN90/U90 -> 346.53179
F91: FBA79348 | G91: B0D81DLSFT | H91: HD-02 | I91: HPC | J91: Hair Care | L91: NINGBO MICROSOYA ELECTRIC APPLIANCE CO.,LTD | M91: Nexlev Hair Dryer 1500W - Women | N91: 85163100 | U91: 3.39 | V91: 3.39 | W91: =U91*2% -> 0.0678 | X91: =(U91+W91)*(B$31+(B$31*B$45)) -> 0.760716 | Y91: =(U91+W91+X91)*B$26 -> 379.66644 | Z91: =Y91*1.18 -> 448.0064 | AA91: =AN91*7% -> 69.93 | AB91: 26 | AC91: 77 | AD91: =AA91+AB91+AC91 -> 172.93 | AE91: =AN91*B$72 -> 199.8 | AF91: =AN91*$B$70 -> 19.98 | AG91: =AN91*B$67 -> 49.95 | AH91: =AN91*$B$74 -> 19.98 | AI91: =AN91-(AN91/1.18) -> 152.38983 | AJ91: =Z91*5% -> 22.40032 | AK91: =Z91*3% -> 13.440192 | AL91: =AN91-Y91-AD91-AE91-AG91-AI91-AJ91-AK91-AF91-AH91 -> -31.536782 | AM91: =AL91/AN91 -> -0.031568351 | AN91: 999 | AR91: 1999 | AV91: =SUM(AN91-AI91)-Y91 -> 466.94373 | AW91: =AV91/AN91 -> 0.46741114 | AX91: 8904422504295 | AY91: =Y91/U91 -> 111.996 | AZ91: =AN91/+SUM(Y91/84) -> 221.02559 | BA91: =AN91/U91 -> 294.69027
F92: FBA79461 | H92: HD-02 | I92: Hair Care | M92: Nexlev Hair Dryer 1500W - Men | N92: 85163100 | U92: 3.39 | W92: =U92*2% -> 0.0678 | X92: =(U92+W92)*(B$31+(B$31*B$45)) -> 0.760716 | Y92: =(U92+W92+X92)*B$26 -> 379.66644 | Z92: =Y92*1.18 -> 448.0064 | AA92: =AN92*9% -> 89.91 | AB92: 47 | AC92: 78 | AD92: =AA92+AB92+AC92 -> 214.91 | AE92: =AN92*B$66 -> 149.85 | AF92: =AN92*$B$70 -> 19.98 | AG92: =AN92*B$67 -> 49.95 | AH92: =AN92*$B$74 -> 19.98 | AI92: =AN92-(AN92/1.18) -> 152.38983 | AJ92: =Z92*5% -> 22.40032 | AK92: =Z92*3% -> 13.440192 | AL92: =AN92-Y92-AD92-AE92-AG92-AI92-AJ92-AK92-AF92-AH92 -> -23.566782 | AM92: =AL92/AN92 -> -0.023590373 | AN92: 999 | AR92: 1999 | AV92: =SUM(AN92-AI92)-Y92 -> 466.94373 | AW92: =AV92/AN92 -> 0.46741114 | AY92: =Y92/U92 -> 111.996 | AZ92: =AN92/+SUM(Y92/84) -> 221.02559 | BA92: =AN92/U92 -> 294.69027
F93: FBA79350 | G93: B0D67727VG | H93: EA-01 | I93: HPC | J93: Hair Care | L93: Shenzhen AIVIQIN Technology Co.,Ltd | M93: Electric Oil Applicator | N93: 90191020 | U93: 6 | V93: 6 | W93: =U93*2% -> 0.12 | X93: =(U93+W93)*(B$42+(B$42*B$45)) -> 0.6732 | Y93: =(U93+W93+X93)*B$26 -> 611.388 | Z93: =Y93*1.18 -> 721.43784 | AA93: =AN93*7.5% -> 89.925 | AB93: 51 | AC93: 59 | AD93: =AA93+AB93+AC93 -> 199.925 | AE93: =AN93*B$72 -> 239.8 | AF93: =AN93*$B$70 -> 23.98 | AG93: =AN93*B$67 -> 59.95 | AH93: =AN93*$B$74 -> 23.98 | AI93: =AN93-(AN93/1.05) -> 57.095238 | AJ93: =Z93*5% -> 36.071892 | AK93: =Z93*3% -> 21.643135 | AL93: =AN93-Y93-AD93-AE93-AG93-AI93-AJ93-AK93-AF93-AH93 -> -74.833265 | AM93: =AL93/AN93 -> -0.062413065 | AN93: 1199 | AP93: 999 | AR93: 2999 | AV93: =SUM(AN93-AI93)-Y93 -> 530.51676 | AW93: =AV93/AN93 -> 0.44246602 | AX93: 8904422504264 | AY93: =Y93/U93 -> 101.898 | AZ93: =AN93/+SUM(Y93/84) -> 164.73336 | BA93: =AN93/U93 -> 199.83333
F94: FBA79588 | G94: B0DHRQPGGM | H94: EA-01 Pro | I94: HPC | J94: Hair Care | L94: Shenzhen AIVIQIN Technology Co.,Ltd | M94: Electric Oil Applicator - pro | N94: 90191020 | U94: 6 | W94: =U94*2% -> 0.12 | X94: =(U94+W94)*(B$42+(B$42*B$45)) -> 0.6732 | Y94: =(U94+W94+X94)*B$26 -> 611.388 | Z94: =Y94*1.18 -> 721.43784 | AA94: =AN94*7.5% -> 115.425 | AB94: 51 | AC94: 59 | AD94: =AA94+AB94+AC94 -> 225.425 | AE94: =AN94*B$72 -> 307.8 | AF94: =AN94*$B$70 -> 30.78 | AG94: 0 | AH94: =AN94*$B$74 -> 30.78 | AI94: =AN94-(AN94/1.18) -> 234.76271 | AJ94: =Z94*5% -> 36.071892 | AK94: =Z94*3% -> 21.643135 | AL94: =AN94-Y94-AD94-AE94-AG94-AI94-AJ94-AK94-AF94-AH94 -> 40.349261 | AM94: =AL94/AN94 -> 0.026217843 | AN94: 1539 | AR94: 2999 | AV94: =SUM(AN94-AI94)-Y94 -> 692.84929 | AW94: =AV94/AN94 -> 0.45019447 | AX94: 8904422504264 | AY94: =Y94/U94 -> 101.898 | AZ94: =AN94/+SUM(Y94/84) -> 211.44674 | BA94: =AN94/U94 -> 256.5
F95: FBA79351 | G95: B0D9KB2RTT | H95: LE-01 | I95: HPC | J95: Skin Care | L95: Shenzhen Meisiyu Electronic Technology Co., Ltd. | M95: LED Face & Skin Care Massager | N95: 85437093 | U95: 3.15 | V95: 3.15 | W95: =U95*2% -> 0.063 | X95: =(U95+W95)*(B$42+(B$42*B$45)) -> 0.35343 | Y95: =(U95+W95+X95)*B$26 -> 320.9787 | Z95: =Y95*1.18 -> 378.75487 | AA95: =AN95*11% -> 65.89 | AB95: 25 | AC95: 59 | AD95: =AA95+AB95+AC95 -> 149.89 | AE95: =AN95*B$66 -> 89.85 | AG95: 0 | AI95: =AN95-(AN95/1.18) -> 91.372881 | AJ95: =Z95*5% -> 18.937743 | AK95: =Z95*3% -> 11.362646 | AL95: =AN95-Y95-AD95-AE95-AG95-AI95-AJ95-AK95-AF95-AH95 -> -83.391971 | AM95: =AL95/AN95 -> -0.13921865 | AN95: 599 | AR95: 1499 | AV95: =SUM(AN95-AI95)-Y95 -> 186.64842 | AW95: =AV95/AN95 -> 0.31160003 | AX95: 8904422504325 | AY95: =Y95/U95 -> 101.898 | AZ95: =AN95/+SUM(Y95/84) -> 156.75807 | BA95: =AN95/U95 -> 190.15873
F96: FBA79352 | G96: B0D637B562 | H96: WF-02-BL | I96: Pet Supplies | J96: Pet Supplies | L96: Shenzhen Aisi Technology Co., Ltd. | M96: Nexlev Pet Water Fountain 2L | N96: 84212190 | O96: 0.06 | P96: 20 | Q96: 18 | R96: 14 | S96: =(P96*Q96*R96)/1000000 -> 0.00504 | T96: =(P96*Q96*R96)/5000 -> 1.008 | U96: 4.5 | V96: 4.7 | W96: =U96*2% -> 0.09 | X96: =(U96+W96)*(B$43+(B$43*B$45)) -> 0.378675 | Y96: =(U96+W96+X96)*B$26 -> 447.18075 | Z96: =Y96*1.18 -> 527.67328 | AA96: =AN96*12.5% -> 156.125 | AB96: 51 | AC96: 115 | AD96: =AA96+AB96+AC96 -> 322.125 | AE96: =AN96*B$66 -> 187.35 | AG96: =AN96*B$67 -> 62.45 | AI96: =AN96-(AN96/1.18) -> 190.52542 | AJ96: =Z96*5% -> 26.383664 | AK96: =Z96*3% -> 15.830199 | AL96: =AN96-Y96-AD96-AE96-AG96-AI96-AJ96-AK96-AF96-AH96 -> -2.8450365 | AM96: =AL96/AN96 -> -0.0022778515 | AN96: 1249 | AR96: 2999 | AV96: =SUM(AN96-AI96)-Y96 -> 611.29383 | AW96: =AV96/AN96 -> 0.4894266 | AX96: 8904422504257 | AY96: =Y96/U96 -> 99.3735 | AZ96: =AN96/+SUM(Y96/84) -> 234.61654 | BA96: =AN96/U96 -> 277.55556
F97: FBA79381 | G97: B0D9KCNVNM | H97: ETR-06 | I97: HPC | J97: Oral Care | L97: Ningbo Oral | M97: Oscillating Electric Toothbrush Sparkle Plus | N97: 85098000 | U97: 5.16 | V97: 5.16 | W97: =U97*2% -> 0.1032 | X97: =(U97+W97)*(B$31+(B$31*B$45)) -> 1.157904 | Y97: =(U97+W97+X97)*B$26 -> 577.89936 | Z97: =Y97*1.18 -> 681.92124 | AA97: =AN97*7.5% -> 89.925 | AB97: 51 | AC97: 59 | AD97: =AA97+AB97+AC97 -> 199.925 | AE97: =AN97*B$72 -> 239.8 | AG97: 0 | AI97: =AN97-(AN97/1.18) -> 182.89831 | AJ97: =Z97*5% -> 34.096062 | AK97: =Z97*3% -> 20.457637 | AL97: =AN97-Y97-AD97-AE97-AG97-AI97-AJ97-AK97-AF97-AH97 -> -56.076365 | AM97: =AL97/AN97 -> -0.046769278 | AN97: 1199 | AP97: 1199 | AR97: 1699 | AV97: =SUM(AN97-AI97)-Y97 -> 438.20233 | AW97: =AV97/AN97 -> 0.36547317 | AX97: 8904422504646 | AY97: =Y97/U97 -> 111.996 | AZ97: =AN97/+SUM(Y97/84) -> 174.27948 | BA97: =AN97/U97 -> 232.36434
F98: FBA79382 | H98: ET-01-BK-4B | I98: HPC | J98: Oral Care | L98: Ningbo Oral | M98: Sonic Electric Toothbrush - 4 Brush Heads | N98: 85098000 | U98: =2.15+0.2 -> 2.35 | W98: =U98*2% -> 0.047 | X98: =(U98+W98)*(B$31+(B$31*B$45)) -> 0.52734 | Y98: =(U98+W98+X98)*B$26 -> 263.1906 | Z98: =Y98*1.18 -> 310.56491 | AA98: =AN98*4.5% -> 22.455 | AB98: 12 | AC98: 60 | AD98: =AA98+AB98+AC98 -> 94.455 | AE98: =AN98*B$72 -> 99.8 | AF98: =AN98*$B$70 -> 9.98 | AG98: 0 | AH98: =AN98*$B$74 -> 9.98 | AI98: =AN98-(AN98/1.18) -> 76.118644 | AJ98: =Z98*5% -> 15.528245 | AK98: =Z98*3% -> 9.3169472 | AL98: =AN98-Y98-AD98-AE98-AG98-AI98-AJ98-AK98-AF98-AH98 -> -79.369437 | AM98: =AL98/AN98 -> -0.15905699 | AN98: 499 | AR98: 1249 | AV98: =SUM(AN98-AI98)-Y98 -> 159.69076 | AW98: =AV98/AN98 -> 0.32002155 | AX98: 8904422504509 | AY98: =Y98/U98 -> 111.996 | AZ98: =AN98/+SUM(Y98/84) -> 159.26101 | BA98: =AN98/U98 -> 212.34043
F99: FBA79383 | G99: B0D3QJ18GX | H99: ET-01-GN-4B | I99: HPC | J99: Oral Care | L99: Ningbo Oral | M99: Sonic Electric Toothbrush - 4 Brush Heads | N99: 85098000 | U99: =2.15+0.2 -> 2.35 | W99: =U99*2% -> 0.047 | X99: =(U99+W99)*(B$31+(B$31*B$45)) -> 0.52734 | Y99: =(U99+W99+X99)*B$26 -> 263.1906 | Z99: =Y99*1.18 -> 310.56491 | AA99: =AN99*4.5% -> 22.455 | AB99: 12 | AC99: 60 | AD99: =AA99+AB99+AC99 -> 94.455 | AE99: =AN99*B$72 -> 99.8 | AF99: =AN99*$B$70 -> 9.98 | AG99: 0 | AH99: =AN99*$B$74 -> 9.98 | AI99: =AN99-(AN99/1.18) -> 76.118644 | AJ99: =Z99*5% -> 15.528245 | AK99: =Z99*3% -> 9.3169472 | AL99: =AN99-Y99-AD99-AE99-AG99-AI99-AJ99-AK99-AF99-AH99 -> -79.369437 | AM99: =AL99/AN99 -> -0.15905699 | AN99: 499 | AR99: 1249 | AV99: =SUM(AN99-AI99)-Y99 -> 159.69076 | AW99: =AV99/AN99 -> 0.32002155 | AX99: 8904422504516 | AY99: =Y99/U99 -> 111.996 | AZ99: =AN99/+SUM(Y99/84) -> 159.26101 | BA99: =AN99/U99 -> 212.34043
F100: FBA79404 | G100: B0D9KFZYG8 | H100: FS-01 | I100: HPC | J100: Skin Care | L100: Ningbo Zhongjia Electrical Appliance Co., Ltd. | M100: Nexlev Face Steamer | N100: 85437093 | U100: 6.65 | V100: 6.7 | W100: =U100*2% -> 0.133 | X100: =(U100+W100)*(B$31+(B$31*B$45)) -> 1.49226 | Y100: =(U100+W100+X100)*B$26 -> 744.7734 | Z100: =Y100*1.18 -> 878.83261 | AA100: =AN100*7% -> 122.43 | AB100: 51 | AC100: 115 | AD100: =AA100+AB100+AC100 -> 288.43 | AE100: =AN100*B$72 -> 349.8 | AF100: =AN100*$B$70 -> 34.98 | AG100: =AN100*B$67 -> 87.45 | AH100: =AN100*$B$74 -> 34.98 | AI100: =AN100-(AN100/1.18) -> 266.79661 | AJ100: =Z100*5% -> 43.941631 | AK100: =Z100*3% -> 26.364978 | AL100: =AN100-Y100-AD100-AE100-AG100-AI100-AJ100-AK100-AF100-AH100 -> -128.51662 | AM100: =AL100/AN100 -> -0.073480057 | AN100: 1749 | AP100: 1549 | AR100: 3399 | AV100: =SUM(AN100-AI100)-Y100 -> 737.42999 | AW100: =AV100/AN100 -> 0.4216295 | AX100: 8904422504653 | AY100: =Y100/U100 -> 111.996 | AZ100: =AN100/+SUM(Y100/84) -> 197.26268 | BA100: =AN100/U100 -> 263.00752
...

Sheet Amazon Live Products
D1: Status | E1: SKU | F1: ASIN | G1: Model | H1: Category L1 | I1: Category L2 | J1: Description | K1: HSN Code | L1: FOB (USD) | M1: Previous Price | N1: Freight+Clearance | O1: Duty and Surcharge | P1: DP | Q1: NLC | R1: Referral Fee | S1: Fixed Closing Fee | T1: Fulfillment Fees | U1: Total FBA Fee | V1: AMS | W1: Coupon | X1: Returns Loss | Y1: SMM | Z1: 18% GST in SP | AA1: Business OH | AB1: Finance | AC1: Total Cost | AD1: Margin | AE1: Margin% | AF1: BAU Deal SP | AG1: Other Charges | AH1: Juiter SP | AI1: MRP | AJ1: Gross Margin | AK1: Gross Margin % | AL1: EAN | AN1: Image ASIN | AO1: July 2025 BAU Deal Price
A2: Dollar Conversion Rate | B2: 88 | D2: Live | E2: FBA78980 | F2: B0CDPMX152 | G2: GS-02 | H2: Home & Kitchen | I2: Fabric Care | J2: Nexlev Garment Steamer - Swift | K2: 85167990 | L2: =VLOOKUP(E2,'Margin Calculation'!F:U,16,0) -> 9.45 | M2: =VLOOKUP(E2,'Margin Calculation'!F:V,17,0) -> 9.45 | N2: 0.3 | O2: =VLOOKUP(E2,'Margin Calculation'!F:X,19,0) -> 2.136559 | P2: =(L2+N2+O2)*$B$2 -> 1046.0172 | Q2: =P2*1.18 -> 1234.3003 | R2: =VLOOKUP(E2,'Margin Calculation'!F:AA,22,0) -> 92.25 | S2: 50 | T2: 136 | U2: 322.4 | V2: =AF2*10% -> 204.9 | W2: =AF2*$B$18 -> 20.49 | X2: =AF2*$B$15 -> 102.45 | Y2: =AF2*$B$21 -> 40.98 | Z2: =AF2-(AF2/1.18) -> 312.55932 | AA2: =AF2*$B$16 -> 102.45 | AB2: =AF2*$B$17 -> 61.47 | AC2: =P2+R2+S2+T2+V2+W2+X2+Y2+Z2+AA2+AB2 -> 2169.5665 | AD2: =AF2-AC2 -> -120.56652 | AE2: =AD2/AF2 -> -0.058841639 | AF2: 2049 | AI2: 4999 | AJ2: =(AF2-P2)-Z2 -> 690.42348 | AK2: =AJ2/AF2 -> 0.33695631 | AL2: 8904422503373 | AN2: B0F9P5NFBK | AO2: 2449
A3: 40HQ Freight+Clearance | B3: 2000 | D3: Live | E3: FBA78981 | F3: B0CDPP45BM | G3: SC-01 | H3: Home & Kitchen | I3: Cleaning & Vacumming | J3: Nexlev Steam Cleaner | K3: 85098000 | L3: =VLOOKUP(E3,'Margin Calculation'!F:U,16,0) -> 13.5 | M3: =VLOOKUP(E3,'Margin Calculation'!F:V,17,0) -> 13.4 | N3: 0.4 | O3: =VLOOKUP(E3,'Margin Calculation'!F:X,19,0) -> 3.0494912 | P3: =(L3+N3+O3)*$B$2 -> 1491.5552 | Q3: =P3*1.18 -> 1760.0352 | R3: =VLOOKUP(E3,'Margin Calculation'!F:AA,22,0) -> 161.955 | S3: 50 | T3: 136 | U3: 406.9 | V3: =AF3*10% -> 339.9 | W3: =AF3*$B$18 -> 33.99 | X3: =AF3*$B$15 -> 169.95 | Y3: =AF3*$B$21 -> 67.98 | Z3: =AF3-(AF3/1.18) -> 518.49153 | AA3: =AF3*$B$16 -> 169.95 | AB3: =AF3*$B$17 -> 101.97 | AC3: =P3+R3+S3+T3+V3+W3+X3+Y3+Z3+AA3+AB3 -> 3241.7417 | AD3: =AF3-AC3 -> 157.25825 | AE3: =AD3/AF3 -> 0.046266034 | AF3: 3399 | AI3: 9999 | AJ3: =(AF3-P3)-Z3 -> 1388.9533 | AK3: =AJ3/AF3 -> 0.40863585 | AL3: 8904422503380 | AN3: B0CDPMX152 | AO3: 2099
A4: 40HQ Usable CBM | B4: 68 | D4: Live | E4: FBA78994 | F4: B0CDQ98FDM | G4: NP-01 | H4: Sports, Fitness & Outdoors | I4: Travel Accessories | J4: Neck Pillow with Memory Foam and Striped Texture | K4: 94043090 | L4: =VLOOKUP(E4,'Margin Calculation'!F:U,16,0) -> 2.95 | M4: =VLOOKUP(E4,'Margin Calculation'!F:V,17,0) -> 0 | N4: 0.1 | O4: =VLOOKUP(E4,'Margin Calculation'!F:X,19,0) -> 0.85156164 | P4: =(L4+N4+O4)*$B$2 -> 343.33742 | Q4: =P4*1.18 -> 405.13816 | R4: =VLOOKUP(E4,'Margin Calculation'!F:AA,22,0) -> 69.9 | S4: 25 | T4: 78 | U4: 172.9 | V4: =AF4*10% -> 69.9 | W4: =AF4*$B$18 -> 6.99 | X4: =AF4*$B$15 -> 34.95 | Y4: =AF4*$B$21 -> 13.98 | Z4: =AF4-(AF4/1.18) -> 106.62712 | AA4: =AF4*$B$16 -> 34.95 | AB4: =AF4*$B$17 -> 20.97 | AC4: =P4+R4+S4+T4+V4+W4+X4+Y4+Z4+AA4+AB4 -> 804.60454 | AD4: =AF4-AC4 -> -105.60454 | AE4: =AD4/AF4 -> -0.15107946 | AF4: =VLOOKUP(F4,AN:AO,2,0) -> 699 | AI4: 1499 | AJ4: =(AF4-P4)-Z4 -> 249.03546 | AK4: =AJ4/AF4 -> 0.3562739 | AL4: 8904422503496 | AN4: B0CYSLCRQS | AO4: 2899
A5: Fulfillment Rate/kg | B5: 40 | D5: Live | E5: FBA78995 | F5: B0CDQ55W2M | G5: NP-02 | H5: Sports, Fitness & Outdoors | I5: Travel Accessories | J5: Neck Pillow with Memory Foam (Dark Grey) | K5: 94043090 | L5: =VLOOKUP(E5,'Margin Calculation'!F:U,16,0) -> 2.95 | M5: =VLOOKUP(E5,'Margin Calculation'!F:V,17,0) -> 0 | N5: 0.1 | O5: =VLOOKUP(E5,'Margin Calculation'!F:X,19,0) -> 0.85156164 | P5: =(L5+N5+O5)*$B$2 -> 343.33742 | Q5: =P5*1.18 -> 405.13816 | R5: =VLOOKUP(E5,'Margin Calculation'!F:AA,22,0) -> 69.9 | S5: 25 | T5: 78 | U5: 172.9 | V5: =AF5*10% -> 69.9 | W5: =AF5*$B$18 -> 6.99 | X5: =AF5*$B$15 -> 34.95 | Y5: =AF5*$B$21 -> 13.98 | Z5: =AF5-(AF5/1.18) -> 106.62712 | AA5: =AF5*$B$16 -> 34.95 | AB5: =AF5*$B$17 -> 20.97 | AC5: =P5+R5+S5+T5+V5+W5+X5+Y5+Z5+AA5+AB5 -> 804.60454 | AD5: =AF5-AC5 -> -105.60454 | AE5: =AD5/AF5 -> -0.15107946 | AF5: =VLOOKUP(F5,AN:AO,2,0) -> 699 | AI5: 1999 | AJ5: =(AF5-P5)-Z5 -> 249.03546 | AK5: =AJ5/AF5 -> 0.3562739 | AL5: 8904422503502 | AN5: B0DCK7ZH5P | AO5: 3199
A6: Duty - Furniture | B6: 0.25 | D6: Live | E6: FBA78996 | F6: B0CDQ6G4TC | G6: NP-03 | H6: Sports, Fitness & Outdoors | I6: Travel Accessories | J6: Neck Pillow with Memory Foam ( Grey) | K6: 94043090 | L6: =VLOOKUP(E6,'Margin Calculation'!F:U,16,0) -> 2.95 | M6: =VLOOKUP(E6,'Margin Calculation'!F:V,17,0) -> 0 | N6: 0.1 | O6: =VLOOKUP(E6,'Margin Calculation'!F:X,19,0) -> 0.85156164 | P6: =(L6+N6+O6)*$B$2 -> 343.33742 | Q6: =P6*1.18 -> 405.13816 | R6: =VLOOKUP(E6,'Margin Calculation'!F:AA,22,0) -> 69.9 | S6: 25 | T6: 78 | U6: 172.9 | V6: =AF6*10% -> 69.9 | W6: =AF6*$B$18 -> 6.99 | X6: =AF6*$B$15 -> 34.95 | Y6: =AF6*$B$21 -> 13.98 | Z6: =AF6-(AF6/1.18) -> 106.62712 | AA6: =AF6*$B$16 -> 34.95 | AB6: =AF6*$B$17 -> 20.97 | AC6: =P6+R6+S6+T6+V6+W6+X6+Y6+Z6+AA6+AB6 -> 804.60454 | AD6: =AF6-AC6 -> -105.60454 | AE6: =AD6/AF6 -> -0.15107946 | AF6: =VLOOKUP(F6,AN:AO,2,0) -> 699 | AI6: 1999 | AJ6: =(AF6-P6)-Z6 -> 249.03546 | AK6: =AJ6/AF6 -> 0.3562739 | AL6: 8904422503519 | AN6: B0DCGHVN81 | AO6: 1999
A7: Duty - Small Appliances | B7: 0.2 | D7: Live | E7: FBA79174 | F7: B0CW1JJP9S | G7: DF-01-BK | H7: HPC | I7: Oral Care | J7: Nexlev Dental Flosser (Black) | K7: 84244900 | L7: =VLOOKUP(E7,'Margin Calculation'!F:U,16,0) -> 9.17 | M7: =VLOOKUP(E7,'Margin Calculation'!F:V,17,0) -> 0 | N7: =L7*2% -> 0.1834 | O7: =VLOOKUP(E7,'Margin Calculation'!F:X,19,0) -> 0.7716555 | P7: =(L7+N7+O7)*$B$2 -> 891.00488 | Q7: =P7*1.18 -> 1051.3858 | R7: =VLOOKUP(E7,'Margin Calculation'!F:AA,22,0) -> 98.925 | S7: 60 | T7: 50 | U7: 222.8 | V7: =AF7*20% -> 305.8 | W7: =AF7*$B$18 -> 15.29 | X7: =AF7*$B$15 -> 76.45 | Y7: =AF7*$B$21 -> 30.58 | Z7: =AF7-(AF7/1.18) -> 233.23729 | AA7: =AF7*$B$16 -> 76.45 | AB7: =AF7*$B$17 -> 45.87 | AC7: =P7+R7+S7+T7+V7+W7+X7+Y7+Z7+AA7+AB7 -> 1883.6072 | AD7: =AF7-AC7 -> -354.60717 | AE7: =AD7/AF7 -> -0.23192098 | AF7: 1529 | AI7: 3599 | AJ7: =(AF7-P7)-Z7 -> 404.75783 | AK7: =AJ7/AF7 -> 0.26472062 | AL7: 8904422503854 | AN7: B0D845B2DG | AO7: 1499
A8: Duty - Other Appliances | B8: 0.1 | D8: Live | E8: FBA79229 | F8: B0CQX9ZZMH | G8: GS-04 | H8: Home & Kitchen | I8: Fabric Care | J8: Nexlev Garment Steamer with Touch Screen Breeze | K8: 85167990 | L8: =VLOOKUP(E8,'Margin Calculation'!F:U,16,0) -> 11.38 | M8: =VLOOKUP(E8,'Margin Calculation'!F:V,17,0) -> 0 | N8: =L8*2% -> 0.2276 | O8: =VLOOKUP(E8,'Margin Calculation'!F:X,19,0) -> 2.561159 | P8: =(L8+N8+O8)*$B$2 -> 1246.8508 | Q8: =P8*1.18 -> 1471.2839 | R8: =VLOOKUP(E8,'Margin Calculation'!F:AA,22,0) -> 98.955 | S8: 50 | T8: 136 | U8: 329.3 | V8: =AF8*10% -> 219.9 | W8: =AF8*$B$18 -> 21.99 | X8: =AF8*$B$15 -> 109.95 | Y8: =AF8*$B$21 -> 43.98 | Z8: =AF8-(AF8/1.18) -> 335.44068 | AA8: =AF8*$B$16 -> 109.95 | AB8: =AF8*$B$17 -> 65.97 | AC8: =P8+R8+S8+T8+V8+W8+X8+Y8+Z8+AA8+AB8 -> 2438.9865 | AD8: =AF8-AC8 -> -239.98647 | AE8: =AD8/AF8 -> -0.10913437 | AF8: =VLOOKUP(F8,AN:AO,2,0) -> 2199 | AI8: 5999 | AJ8: =(AF8-P8)-Z8 -> 616.70853 | AK8: =AJ8/AF8 -> 0.28044953 | AL8: 8904422503991 | AN8: B0CDPP45BM | AO8: 3399
A9: Duty - Flosser | B9: 0.075 | D9: Live | E9: FBA79233 | F9: B0CS69T7HF | G9: ET-01-BK | H9: HPC | I9: Oral Care | J9: Electric Toothbrush - Black - Humm | K9: 85098000 | L9: =VLOOKUP(E9,'Margin Calculation'!F:U,16,0) -> 2.15 | M9: =VLOOKUP(E9,'Margin Calculation'!F:V,17,0) -> 2.15 | N9: =L9*2% -> 0.043 | O9: =VLOOKUP(E9,'Margin Calculation'!F:X,19,0) -> 0.48246 | P9: =(L9+N9+O9)*$B$2 -> 235.44048 | Q9: =P9*1.18 -> 277.81977 | R9: =VLOOKUP(E9,'Margin Calculation'!F:AA,22,0) -> 17.955 | S9: 12 | T9: 60 | U9: 89.9 | V9: =AF9*20% -> 59.8 | W9: =AF9*$B$18 -> 2.99 | X9: =AF9*$B$15 -> 14.95 | Y9: =AF9*$B$21 -> 5.98 | Z9: =AF9-(AF9/1.18) -> 45.610169 | AA9: =AF9*$B$16 -> 14.95 | AB9: =AF9*$B$17 -> 8.97 | AC9: =P9+R9+S9+T9+V9+W9+X9+Y9+Z9+AA9+AB9 -> 478.64565 | AD9: =AF9-AC9 -> -179.64565 | AE9: =AD9/AF9 -> -0.60082157 | AF9: 299 | AI9: 1199 | AJ9: =(AF9-P9)-Z9 -> 17.949351 | AK9: =AJ9/AF9 -> 0.060031273 | AL9: 8904422504004 | AN9: B0DFD123P5 | AO9: 1499
A10: Duty - Pet water fountain | B10: 0.08 | D10: Live | E10: FBA79234 | F10: B0CSG2JZ19 | G10: ET-02-GN | H10: HPC | I10: Oral Care | J10: Electric Toothbrush - Green - Humm | K10: 85098000 | L10: =VLOOKUP(E10,'Margin Calculation'!F:U,16,0) -> 2.15 | M10: =VLOOKUP(E10,'Margin Calculation'!F:V,17,0) -> 2.15 | N10: =L10*2% -> 0.043 | O10: =VLOOKUP(E10,'Margin Calculation'!F:X,19,0) -> 0.48246 | P10: =(L10+N10+O10)*$B$2 -> 235.44048 | Q10: =P10*1.18 -> 277.81977 | R10: =VLOOKUP(E10,'Margin Calculation'!F:AA,22,0) -> 15.705 | S10: 12 | T10: 60 | U10: 89.9 | V10: =AF10*20% -> 59.8 | W10: =AF10*$B$18 -> 2.99 | X10: =AF10*$B$15 -> 14.95 | Y10: =AF10*$B$21 -> 5.98 | Z10: =AF10-(AF10/1.18) -> 45.610169 | AA10: =AF10*$B$16 -> 14.95 | AB10: =AF10*$B$17 -> 8.97 | AC10: =P10+R10+S10+T10+V10+W10+X10+Y10+Z10+AA10+AB10 -> 476.39565 | AD10: =AF10-AC10 -> -177.39565 | AE10: =AD10/AF10 -> -0.59329649 | AF10: 299 | AI10: 1199 | AJ10: =(AF10-P10)-Z10 -> 17.949351 | AK10: =AJ10/AF10 -> 0.060031273 | AL10: 8904422504011 | AN10: B0CQX9ZZMH | AO10: 2199
A11: Surcharge | B11: 0.1 | D11: Live | E11: FBA79262 | F11: B0CYSMBCB8 | G11: SC-02 | H11: Home & Kitchen | I11: Cleaning & Vacumming | J11: Steam Cleaner-Shine | K11: 85098000 | L11: =VLOOKUP(E11,'Margin Calculation'!F:U,16,0) -> 10.35 | M11: =VLOOKUP(E11,'Margin Calculation'!F:V,17,0) -> 10.3 | N11: =L11*2% -> 0.207 | O11: =VLOOKUP(E11,'Margin Calculation'!F:X,19,0) -> 2.32254 | P11: =(L11+N11+O11)*$B$2 -> 1133.3995 | Q11: =P11*1.18 -> 1337.4114 | R11: =VLOOKUP(E11,'Margin Calculation'!F:AA,22,0) -> 110.205 | S11: 50 | T11: 135 | U11: 344.2 | V11: =AF11*10% -> 244.9 | W11: =AF11*$B$18 -> 24.49 | X11: =AF11*$B$15 -> 122.45 | Y11: =AF11*$B$21 -> 48.98 | Z11: =AF11-(AF11/1.18) -> 373.57627 | AA11: =AF11*$B$16 -> 122.45 | AB11: =AF11*$B$17 -> 73.47 | AC11: =P11+R11+S11+T11+V11+W11+X11+Y11+Z11+AA11+AB11 -> 2438.9208 | AD11: =AF11-AC11 -> 10.079209 | AE11: =AD11/AF11 -> 0.0041156426 | AF11: 2449 | AI11: 6999 | AJ11: =(AF11-P11)-Z11 -> 942.02421 | AK11: =AJ11/AF11 -> 0.38465668 | AL11: 8904422504042 | AN11: B0DTK4FY1G | AO11: 2599
A12: Referral Fee (<15001) | B12: 0.15 | D12: Live | E12: FBA79263 | F12: B0CYSLCRQS | G12: MR-01 | H12: Home & Kitchen | I12: Cleaning & Vacumming | J12: Smart Care Mite Remover (Nexlev Dust Mite UV) | K12: 85086000 | L12: =VLOOKUP(E12,'Margin Calculation'!F:U,16,0) -> 9.4 | M12: =VLOOKUP(E12,'Margin Calculation'!F:V,17,0) -> 0 | N12: =L12*2% -> 0.188 | O12: =VLOOKUP(E12,'Margin Calculation'!F:X,19,0) -> 1.05468 | P12: =(L12+N12+O12)*$B$2 -> 936.55584 | Q12: =P12*1.18 -> 1105.1359 | R12: =VLOOKUP(E12,'Margin Calculation'!F:AA,22,0) -> 132.705 | S12: 50 | T12: 164 | U12: 402.4 | V12: =AF12*10% -> 289.9 | W12: =AF12*$B$18 -> 28.99 | X12: =AF12*$B$15 -> 144.95 | Y12: =AF12*$B$21 -> 57.98 | Z12: =AF12-(AF12/1.18) -> 442.22034 | AA12: =AF12*$B$16 -> 144.95 | AB12: =AF12*$B$17 -> 86.97 | AC12: =P12+R12+S12+T12+V12+W12+X12+Y12+Z12+AA12+AB12 -> 2479.2212 | AD12: =AF12-AC12 -> 419.77882 | AE12: =AD12/AF12 -> 0.14480125 | AF12: =VLOOKUP(F12,AN:AO,2,0) -> 2899 | AI12: 5499 | AJ12: =(AF12-P12)-Z12 -> 1520.2238 | AK12: =AJ12/AF12 -> 0.52439594 | AL12: 8904422504080 | AN12: B0D9KDQCCM | AO12: 999
A13: Referral Fee (>15000) | B13: 0.1 | D13: Live | E13: FBA79265 | F13: B0D2LHNS9B | G13: CR-01 | H13: HPC | I13: Skin Care | J13: Smooth Sole Callus Remover | K13: 82142090 | L13: =VLOOKUP(E13,'Margin Calculation'!F:U,16,0) -> 4.48 | M13: =VLOOKUP(E13,'Margin Calculation'!F:V,17,0) -> 4.48 | N13: =L13*2% -> 0.0896 | O13: =VLOOKUP(E13,'Margin Calculation'!F:X,19,0) -> 0.502656 | P13: =(L13+N13+O13)*$B$2 -> 446.35853 | Q13: =P13*1.18 -> 526.70306 | R13: =VLOOKUP(E13,'Margin Calculation'!F:AA,22,0) -> 98.89 | S13: 47 | T13: 58 | U13: 203.8 | V13: =AF13*20% -> 155.8 | W13: =AF13*$B$18 -> 7.79 | X13: =AF13*$B$15 -> 38.95 | Y13: =AF13*$B$21 -> 15.58 | Z13: =AF13-(AF13/1.18) -> 118.83051 | AA13: =AF13*$B$16 -> 38.95 | AB13: =AF13*$B$17 -> 23.37 | AC13: =P13+R13+S13+T13+V13+W13+X13+Y13+Z13+AA13+AB13 -> 1049.519 | AD13: =AF13-AC13 -> -270.51904 | AE13: =AD13/AF13 -> -0.34726449 | AF13: 779 | AI13: 1999 | AJ13: =(AF13-P13)-Z13 -> 213.81096 | AK13: =AJ13/AF13 -> 0.2744685 | AL13: 8904422504172 | AN13: B0D637B562 | AO13: 1249
A14: AMS | B14: 0.1 | D14: Live | E14: FBA79266 | F14: B0D2LGR3GG | G14: T-01 | H14: HPC | I14: Trimmers & Body Groomers | J14: Velvet Vibe Multi-Trimmer | K14: 85101000 | L14: =VLOOKUP(E14,'Margin Calculation'!F:U,16,0) -> 3.96 | M14: =VLOOKUP(E14,'Margin Calculation'!F:V,17,0) -> 3.96 | N14: =L14*2% -> 0.0792 | O14: =VLOOKUP(E14,'Margin Calculation'!F:X,19,0) -> 0.888624 | P14: =(L14+N14+O14)*$B$2 -> 433.64851 | Q14: =P14*1.18 -> 511.70524 | R14: =VLOOKUP(E14,'Margin Calculation'!F:AA,22,0) -> 69.93 | S14: 25 | T14: 58 | U14: 172.8 | V14: =AF14*20% -> 199.8 | W14: =AF14*$B$18 -> 9.99 | X14: =AF14*$B$15 -> 49.95 | Y14: =AF14*$B$21 -> 19.98 | Z14: =AF14-(AF14/1.18) -> 152.38983 | AA14: =AF14*$B$16 -> 49.95 | AB14: =AF14*$B$17 -> 29.97 | AC14: =P14+R14+S14+T14+V14+W14+X14+Y14+Z14+AA14+AB14 -> 1098.6083 | AD14: =AF14-AC14 -> -99.608343 | AE14: =AD14/AF14 -> -0.099708051 | AF14: 999 | AI14: 1499 | AJ14: =(AF14-P14)-Z14 -> 412.96166 | AK14: =AJ14/AF14 -> 0.41337503 | AL14: 8904422504059 | AN14: B0DFCG2VGS | AO14: 1699
A15: Returns and Repairs | B15: 0.05 | D15: Live | E15: FBA79267 | F15: B0D2LD6BYJ | G15: T-02 | H15: HPC | I15: Trimmers & Body Groomers | J15: Velvet Vibe Plus Multi-Trimmer | K15: 85101000 | L15: =VLOOKUP(E15,'Margin Calculation'!F:U,16,0) -> 4.65 | M15: =VLOOKUP(E15,'Margin Calculation'!F:V,17,0) -> 4.65 | N15: =L15*2% -> 0.093 | O15: =VLOOKUP(E15,'Margin Calculation'!F:X,19,0) -> 1.04346 | P15: =(L15+N15+O15)*$B$2 -> 509.20848 | Q15: =P15*1.18 -> 600.86601 | R15: =VLOOKUP(E15,'Margin Calculation'!F:AA,22,0) -> 113.905 | S15: 25 | T15: 58 | U15: 206.1 | V15: =AF15*20% -> 219.8 | W15: =AF15*$B$18 -> 10.99 | X15: =AF15*$B$15 -> 54.95 | Y15: =AF15*$B$21 -> 21.98 | Z15: =AF15-(AF15/1.18) -> 167.64407 | AA15: =AF15*$B$16 -> 54.95 | AB15: =AF15*$B$17 -> 32.97 | AC15: =P15+R15+S15+T15+V15+W15+X15+Y15+Z15+AA15+AB15 -> 1269.3975 | AD15: =AF15-AC15 -> -170.39755 | AE15: =AD15/AF15 -> -0.15504781 | AF15: 1099 | AI15: 1899 | AJ15: =(AF15-P15)-Z15 -> 422.14745 | AK15: =AJ15/AF15 -> 0.38411961 | AL15: 8904422504066 | AN15: B0D8445KJN | AO15: 699
A16: Overheads | B16: 0.05 | D16: Live | E16: FBA79268 | F16: B0D383WQPB | G16: GS-05 | H16: Home & Kitchen | I16: Fabric Care | J16: Nexlev Smart Care Travel Steamer - Nomad | K16: 85167990 | L16: =VLOOKUP(E16,'Margin Calculation'!F:U,16,0) -> 7.5 | M16: =VLOOKUP(E16,'Margin Calculation'!F:V,17,0) -> 7.5 | N16: =L16*2% -> 0.15 | O16: =VLOOKUP(E16,'Margin Calculation'!F:X,19,0) -> 1.683 | P16: =(L16+N16+O16)*$B$2 -> 821.304 | Q16: =P16*1.18 -> 969.13872 | R16: =VLOOKUP(E16,'Margin Calculation'!F:AA,22,0) -> 80.955 | S16: 50 | T16: 136 | U16: 316.3 | V16: =AF16*10% -> 199.9 | W16: =AF16*$B$18 -> 19.99 | X16: =AF16*$B$15 -> 99.95 | Y16: =AF16*$B$21 -> 39.98 | Z16: =AF16-(AF16/1.18) -> 304.9322 | AA16: =AF16*$B$16 -> 99.95 | AB16: =AF16*$B$17 -> 59.97 | AC16: =P16+R16+S16+T16+V16+W16+X16+Y16+Z16+AA16+AB16 -> 1912.9312 | AD16: =AF16-AC16 -> 86.068797 | AE16: =AD16/AF16 -> 0.043055926 | AF16: =VLOOKUP(F16,AN:AO,2,0) -> 1999 | AI16: 3999 | AJ16: =(AF16-P16)-Z16 -> 872.7638 | AK16: =AJ16/AF16 -> 0.4366002 | AL16: 8904422504097 | AN16: B0D383WQPB | AO16: 1999
A17: Finance | B17: 0.03 | D17: Live | E17: FBA79271 | F17: B0D83Q7L8W | G17: V-01 | H17: HPC | I17: Hair Care | J17: Nexlev Volumizer | K17: 85163100 | L17: =VLOOKUP(E17,'Margin Calculation'!F:U,16,0) -> 5.5 | M17: =VLOOKUP(E17,'Margin Calculation'!F:V,17,0) -> 0 | N17: =L17*2% -> 0.11 | O17: =VLOOKUP(E17,'Margin Calculation'!F:X,19,0) -> 1.2342 | P17: =(L17+N17+O17)*$B$2 -> 602.2896 | Q17: =P17*1.18 -> 710.70173 | R17: =VLOOKUP(E17,'Margin Calculation'!F:AA,22,0) -> 142.405 | S17: 47 | T17: 78 | U17: 250.9 | V17: =AF17*20% -> 249.8 | W17: =AF17*$B$18 -> 12.49 | X17: =AF17*$B$15 -> 62.45 | Y17: =AF17*$B$21 -> 24.98 | Z17: =AF17-(AF17/1.18) -> 190.52542 | AA17: =AF17*$B$16 -> 62.45 | AB17: =AF17*$B$17 -> 37.47 | AC17: =P17+R17+S17+T17+V17+W17+X17+Y17+Z17+AA17+AB17 -> 1509.86 | AD17: =AF17-AC17 -> -260.86002 | AE17: =AD17/AF17 -> -0.2088551 | AF17: 1249 | AI17: 3499 | AJ17: =(AF17-P17)-Z17 -> 456.18498 | AK17: =AJ17/AF17 -> 0.36524017 | AL17: 8904422504103 | AN17: B0D2LJSQXZ | AO17: 3699
A18: Coupon | B18: 0.01 | D18: Live | E18: FBK79271 | F18: B0DQ8W1RBV | G18: V-01 Rose Gold | H18: HPC | I18: Hair Care | J18: Nexlev Volumizer | K18: 85163100 | L18: =VLOOKUP(E18,'Margin Calculation'!F:U,16,0) -> 5 | M18: =VLOOKUP(E18,'Margin Calculation'!F:V,17,0) -> 0 | N18: =L18*2% -> 0.1 | O18: =VLOOKUP(E18,'Margin Calculation'!F:X,19,0) -> 1.122 | P18: =(L18+N18+O18)*$B$2 -> 547.536 | Q18: =P18*1.18 -> 646.09248 | R18: =VLOOKUP(E18,'Margin Calculation'!F:AA,22,0) -> 142.405 | S18: 47 | T18: 78 | U18: 246.4 | V18: =AF18*20% -> 299.8 | W18: =AF18*$B$18 -> 14.99 | X18: =AF18*$B$15 -> 74.95 | Y18: =AF18*$B$21 -> 29.98 | Z18: =AF18-(AF18/1.18) -> 228.66102 | AA18: =AF18*$B$16 -> 74.95 | AB18: =AF18*$B$17 -> 44.97 | AC18: =P18+R18+S18+T18+V18+W18+X18+Y18+Z18+AA18+AB18 -> 1583.242 | AD18: =AF18-AC18 -> -84.242017 | AE18: =AD18/AF18 -> -0.056198811 | AF18: 1499 | AI18: 3499 | AJ18: =(AF18-P18)-Z18 -> 722.80298 | AK18: =AJ18/AF18 -> 0.48219012 | AL18: 8904422504103 | AN18: B0DCK56Q85 | AO18: 2499
A19: AMS -HPC | B19: 0.2 | D19: Live | E19: FBA79453 | F19: B0D2LFMY48 | G19: HS-01 | H19: HPC | I19: Hair Care | J19: Hair Straightner - Black | K19: 85163200 | L19: =VLOOKUP(E19,'Margin Calculation'!F:U,16,0) -> 2.87 | M19: =VLOOKUP(E19,'Margin Calculation'!F:V,17,0) -> 0 | N19: =L19*2% -> 0.0574 | O19: =VLOOKUP(E19,'Margin Calculation'!F:X,19,0) -> 0.644028 | P19: =(L19+N19+O19)*$B$2 -> 314.28566 | Q19: =P19*1.18 -> 370.85708 | R19: =VLOOKUP(E19,'Margin Calculation'!F:AA,22,0) -> 55.93 | S19: 25 | T19: 73 | U19: 167.9 | V19: =AF19*20% -> 159.8 | W19: =AF19*$B$18 -> 7.99 | X19: =AF19*$B$15 -> 39.95 | Y19: =AF19*$B$21 -> 15.98 | Z19: =AF19-(AF19/1.18) -> 121.88136 | AA19: =AF19*$B$16 -> 39.95 | AB19: =AF19*$B$17 -> 23.97 | AC19: =P19+R19+S19+T19+V19+W19+X19+Y19+Z19+AA19+AB19 -> 877.73702 | AD19: =AF19-AC19 -> -78.73702 | AE19: =AD19/AF19 -> -0.098544455 | AF19: 799 | AI19: 1299 | AJ19: =(AF19-P19)-Z19 -> 362.83298 | AK19: =AJ19/AF19 -> 0.45410886 | AL19: 8904422504110 | AN19: B0CW1JJP9S | AO19: 1499
A20: AMS- Hair care | B20: 0.15 | D20: Live | E20: FBA79454 | F20: B0D2LKB4BJ | G20: HS-02 | H20: Home & Kitchen | I20: Fabric Care | J20: Hair Straightner - Purple | K20: 85163200 | L20: =VLOOKUP(E20,'Margin Calculation'!F:U,16,0) -> 2.96 | M20: =VLOOKUP(E20,'Margin Calculation'!F:V,17,0) -> 0 | N20: =L20*2% -> 0.0592 | O20: =VLOOKUP(E20,'Margin Calculation'!F:X,19,0) -> 0.664224 | P20: =(L20+N20+O20)*$B$2 -> 324.14131 | Q20: =P20*1.18 -> 382.48675 | R20: =VLOOKUP(E20,'Margin Calculation'!F:AA,22,0) -> 59.43 | S20: 25 | T20: 73 | U20: 178.4 | V20: =AF20*10% -> 84.9 | W20: =AF20*$B$18 -> 8.49 | X20: =AF20*$B$15 -> 42.45 | Y20: =AF20*$B$21 -> 16.98 | Z20: =AF20-(AF20/1.18) -> 129.50847 | AA20: =AF20*$B$16 -> 42.45 | AB20: =AF20*$B$17 -> 25.47 | AC20: =P20+R20+S20+T20+V20+W20+X20+Y20+Z20+AA20+AB20 -> 831.81979 | AD20: =AF20-AC20 -> 17.180213 | AE20: =AD20/AF20 -> 0.020235823 | AF20: 849 | AI20: 1499 | AJ20: =(AF20-P20)-Z20 -> 395.35021 | AK20: =AJ20/AF20 -> 0.46566574 | AL20: 8904422504127 | AN20: B0D2P6KF4N | AO20: 299
A21: SMM | B21: 0.02 | D21: Live | E21: FBA79278 | F21: B0D86ZC9YT | G21: HD-01 | H21: Hair Care | J21: Hair Dryer | K21: 85163100 | L21: =VLOOKUP(E21,'Margin Calculation'!F:U,16,0) -> 5.85 | M21: =VLOOKUP(E21,'Margin Calculation'!F:V,17,0) -> 5.85 | N21: =L21*2% -> 0.117 | O21: =VLOOKUP(E21,'Margin Calculation'!F:X,19,0) -> 1.31274 | P21: =(L21+N21+O21)*$B$2 -> 640.61712 | Q21: =P21*1.18 -> 755.9282 | R21: =VLOOKUP(E21,'Margin Calculation'!F:AA,22,0) -> 142.405 | S21: 47 | T21: 204 | U21: 348.4 | V21: =AF21*20% -> 248.6 | W21: =AF21*$B$18 -> 12.43 | X21: =AF21*$B$15 -> 62.15 | Y21: =AF21*$B$21 -> 24.86 | Z21: =AF21-(AF21/1.18) -> 189.61017 | AA21: =AF21*$B$16 -> 62.15 | AB21: =AF21*$B$17 -> 37.29 | AC21: =P21+R21+S21+T21+V21+W21+X21+Y21+Z21+AA21+AB21 -> 1671.1123 | AD21: =AF21-AC21 -> -428.11229 | AE21: =AD21/AF21 -> -0.34441858 | AF21: 1243 | AJ21: =(AF21-P21)-Z21 -> 412.77271 | AK21: =AJ21/AF21 -> 0.3320778 | AN21: B0DTYDTKN8 | AO21: 3499
D22: Live | E22: FBA79348 | F22: B0D81DLSFT | G22: HD-02 | H22: Hair Care | J22: Hair Dryer-Ionic | K22: 85163100 | L22: =VLOOKUP(E22,'Margin Calculation'!F:U,16,0) -> 3.39 | M22: =VLOOKUP(E22,'Margin Calculation'!F:V,17,0) -> 3.39 | N22: =L22*2% -> 0.0678 | O22: =VLOOKUP(E22,'Margin Calculation'!F:X,19,0) -> 0.760716 | P22: =(L22+N22+O22)*$B$2 -> 371.22941 | Q22: =P22*1.18 -> 438.0507 | R22: =VLOOKUP(E22,'Margin Calculation'!F:AA,22,0) -> 69.93 | S22: 47 | T22: 204 | U22: 315.9 | V22: =AF22*20% -> 164.8 | W22: =AF22*$B$18 -> 8.24 | X22: =AF22*$B$15 -> 41.2 | Y22: =AF22*$B$21 -> 16.48 | Z22: =AF22-(AF22/1.18) -> 125.69492 | AA22: =AF22*$B$16 -> 41.2 | AB22: =AF22*$B$17 -> 24.72 | AC22: =P22+R22+S22+T22+V22+W22+X22+Y22+Z22+AA22+AB22 -> 1114.4943 | AD22: =AF22-AC22 -> -290.49432 | AE22: =AD22/AF22 -> -0.35254165 | AF22: 824 | AJ22: =(AF22-P22)-Z22 -> 327.07568 | AK22: =AJ22/AF22 -> 0.3969365 | AN22: B0DCK7J87D | AO22: 3499
D23: Live | E23: FBA79276 | F23: B0D2LJSQXZ | G23: SM-01 | H23: Home & Kitchen | I23: Cleaning & Vacumming | J23: Steam Mop | K23: 85098000 | L23: =VLOOKUP(E23,'Margin Calculation'!F:U,16,0) -> 17.5 | M23: =VLOOKUP(E23,'Margin Calculation'!F:V,17,0) -> 0 | N23: =L23*2% -> 0.35 | O23: =VLOOKUP(E23,'Margin Calculation'!F:X,19,0) -> 3.927 | P23: =(L23+N23+O23)*$B$2 -> 1916.376 | Q23: =P23*1.18 -> 2261.3237 | R23: =VLOOKUP(E23,'Margin Calculation'!F:AA,22,0) -> 170.955 | S23: 50 | T23: 162 | U23: 452.2 | V23: =AF23*10% -> 379.9 | W23: =AF23*$B$18 -> 37.99 | X23: =AF23*$B$15 -> 189.95 | Y23: =AF23*$B$21 -> 75.98 | Z23: =AF23-(AF23/1.18) -> 579.50847 | AA23: =AF23*$B$16 -> 189.95 | AB23: =AF23*$B$17 -> 113.97 | AC23: =P23+R23+S23+T23+V23+W23+X23+Y23+Z23+AA23+AB23 -> 3866.5795 | AD23: =AF23-AC23 -> -67.579475 | AE23: =AD23/AF23 -> -0.017788754 | AF23: 3799 | AI23: 8999 | AJ23: =(AF23-P23)-Z23 -> 1303.1155 | AK23: =AJ23/AF23 -> 0.34301541 | AL23: 8904422504202 | AN23: B0DDC3GVZW | AO23: 1999
D24: Live | E24: FBA79277 | F24: B0D672NXC8 | G24: SC-03 | H24: Home & Kitchen | I24: Cleaning & Vacumming | J24: Steam Cleaner-Heavy Duty | K24: 85167990 | L24: =VLOOKUP(E24,'Margin Calculation'!F:U,16,0) -> 29.5 | M24: =VLOOKUP(E24,'Margin Calculation'!F:V,17,0) -> 29.5 | N24: =L24*2% -> 0.59 | O24: =VLOOKUP(E24,'Margin Calculation'!F:X,19,0) -> 6.6198 | P24: =(L24+N24+O24)*$B$2 -> 3230.4624 | Q24: =P24*1.18 -> 3811.9456 | R24: =VLOOKUP(E24,'Margin Calculation'!F:AA,22,0) -> 559.92 | S24: 47 | T24: 246 | U24: 832.2 | V24: =AF24*10% -> 699.9 | W24: =AF24*$B$18 -> 69.99 | X24: =AF24*$B$15 -> 349.95 | Y24: =AF24*$B$21 -> 139.98 | Z24: =AF24-(AF24/1.18) -> 1067.6441 | AA24: =AF24*$B$16 -> 349.95 | AB24: =AF24*$B$17 -> 209.97 | AC24: =P24+R24+S24+T24+V24+W24+X24+Y24+Z24+AA24+AB24 -> 6970.7665 | AD24: =AF24-AC24 -> 28.233532 | AE24: =AD24/AF24 -> 0.004033938 | AF24: =VLOOKUP(F24,AN:AO,2,0) -> 6999 | AI24: 11999 | AJ24: =(AF24-P24)-Z24 -> 2700.8935 | AK24: =AJ24/AF24 -> 0.38589706 | AL24: 8904422504240 | AN24: B0DFM4JZV9 | AO24: 2299
D25: Live | E25: FBA79279 | F25: B0D8445KJN | G25: LR-01 | H25: Home & Kitchen | I25: Fabric Care | J25: Nexlev Lint Remover - Mini | K25: 85167990 | L25: =VLOOKUP(E25,'Margin Calculation'!F:U,16,0) -> 3.4 | M25: =VLOOKUP(E25,'Margin Calculation'!F:V,17,0) -> 0 | N25: =L25*2% -> 0.068 | O25: =VLOOKUP(E25,'Margin Calculation'!F:X,19,0) -> 0.76296 | P25: =(L25+N25+O25)*$B$2 -> 372.32448 | Q25: =P25*1.18 -> 439.34289 | R25: =VLOOKUP(E25,'Margin Calculation'!F:AA,22,0) -> 31.455 | S25: 25 | T25: 58 | U25: 128.8 | V25: =AF25*10% -> 99.9 | W25: =AF25*$B$18 -> 9.99 | X25: =AF25*$B$15 -> 49.95 | Y25: =AF25*$B$21 -> 19.98 | Z25: =AF25-(AF25/1.18) -> 152.38983 | AA25: =AF25*$B$16 -> 49.95 | AB25: =AF25*$B$17 -> 29.97 | AC25: =P25+R25+S25+T25+V25+W25+X25+Y25+Z25+AA25+AB25 -> 898.90931 | AD25: =AF25-AC25 -> 100.09069 | AE25: =AD25/AF25 -> 0.10019088 | AF25: 999 | AI25: 1499 | AJ25: =(AF25-P25)-Z25 -> 474.28569 | AK25: =AJ25/AF25 -> 0.47476045 | AL25: 8904422504189 | AN25: B0CDPQXPC1 | AO25: 2299
D26: Live | E26: FBA79280 | F26: B0D845B2DG | G26: LR-02 | H26: Home & Kitchen | I26: Fabric Care | J26: Nexlev Lint Remover | K26: 85167990 | L26: =VLOOKUP(E26,'Margin Calculation'!F:U,16,0) -> 6.8 | M26: =VLOOKUP(E26,'Margin Calculation'!F:V,17,0) -> 6.8 | N26: =L26*2% -> 0.136 | O26: =VLOOKUP(E26,'Margin Calculation'!F:X,19,0) -> 1.52592 | P26: =(L26+N26+O26)*$B$2 -> 744.64896 | Q26: =P26*1.18 -> 878.68577 | R26: =VLOOKUP(E26,'Margin Calculation'!F:AA,22,0) -> 65.205 | S26: 50 | T26: 79 | U26: 226.4 | V26: =AF26*10% -> 149.9 | W26: =AF26*$B$18 -> 14.99 | X26: =AF26*$B$15 -> 74.95 | Y26: =AF26*$B$21 -> 29.98 | Z26: =AF26-(AF26/1.18) -> 228.66102 | AA26: =AF26*$B$16 -> 74.95 | AB26: =AF26*$B$17 -> 44.97 | AC26: =P26+R26+S26+T26+V26+W26+X26+Y26+Z26+AA26+AB26 -> 1557.255 | AD26: =AF26-AC26 -> -58.254977 | AE26: =AD26/AF26 -> -0.03886256 | AF26: =VLOOKUP(F26,AN:AO,2,0) -> 1499 | AI26: 2999 | AJ26: =(AF26-P26)-Z26 -> 525.69002 | AK26: =AJ26/AF26 -> 0.35069381 | AL26: 8904422504196 | AN26: B0DJFH6RTL | AO26: 1499
D27: Live | E27: FBA79332 | F27: B0D63FKYZ5 | G27: HM-01 | H27: HPC | I27: Hair Care | J27: Scalp Massager | K27: 90191020 | L27: =VLOOKUP(E27,'Margin Calculation'!F:U,16,0) -> 4.5 | M27: =VLOOKUP(E27,'Margin Calculation'!F:V,17,0) -> 4.1 | N27: =L27*2% -> 0.09 | O27: =VLOOKUP(E27,'Margin Calculation'!F:X,19,0) -> 0.5049 | P27: =(L27+N27+O27)*$B$2 -> 448.3512 | Q27: =P27*1.18 -> 529.05442 | R27: =VLOOKUP(E27,'Margin Calculation'!F:AA,22,0) -> 71.925 | S27: 47 | T27: 78 | U27: 200.3 | V27: =AF27*20% -> 187.8 | W27: =AF27*$B$18 -> 9.39 | X27: =AF27*$B$15 -> 46.95 | Y27: =AF27*$B$21 -> 18.78 | Z27: =AF27-(AF27/1.18) -> 143.23729 | AA27: =AF27*$B$16 -> 46.95 | AB27: =AF27*$B$17 -> 28.17 | AC27: =P27+R27+S27+T27+V27+W27+X27+Y27+Z27+AA27+AB27 -> 1126.5535 | AD27: =AF27-AC27 -> -187.55349 | AE27: =AD27/AF27 -> -0.19973747 | AF27: 939 | AI27: 2099 | AJ27: =(AF27-P27)-Z27 -> 347.41151 | AK27: =AJ27/AF27 -> 0.36998031 | AL27: 8904422504219 | AN27: B0DJFH4K8B | AO27: 1949
D28: Live | E28: FBA79333 | F28: B0D63DTKQB | G28: HM-02 | H28: HPC | I28: Hair Care | J28: Scalp Massager Pro | K28: 90191020 | L28: =VLOOKUP(E28,'Margin Calculation'!F:U,16,0) -> 6 | M28: =VLOOKUP(E28,'Margin Calculation'!F:V,17,0) -> 6 | N28: =L28*2% -> 0.12 | O28: =VLOOKUP(E28,'Margin Calculation'!F:X,19,0) -> 0.6732 | P28: =(L28+N28+O28)*$B$2 -> 597.8016 | Q28: =P28*1.18 -> 705.40589 | R28: =VLOOKUP(E28,'Margin Calculation'!F:AA,22,0) -> 188.355 | S28: 50 | T28: 59 | U28: 213.9 | V28: =AF28*20% -> 279.8 | W28: =AF28*$B$18 -> 13.99 | X28: =AF28*$B$15 -> 69.95 | Y28: =AF28*$B$21 -> 27.98 | Z28: =AF28-(AF28/1.18) -> 213.40678 | AA28: =AF28*$B$16 -> 69.95 | AB28: =AF28*$B$17 -> 41.97 | AC28: =P28+R28+S28+T28+V28+W28+X28+Y28+Z28+AA28+AB28 -> 1612.2034 | AD28: =AF28-AC28 -> -213.20338 | AE28: =AD28/AF28 -> -0.15239698 | AF28: =VLOOKUP(F28,AN:AO,2,0) -> 1399 | AI28: 2699 | AJ28: =(AF28-P28)-Z28 -> 587.79162 | AK28: =AJ28/AF28 -> 0.42015127 | AL28: 8904422504226 | AN28: B0DJFJZMC6 | AO28: 2299
D29: Live | E29: FBA79346 | F29: B0D25LNDSY | G29: ETC-04-WH | H29: HPC | I29: Oral Care | J29: Electric Toothbrush - C Type - White-Sparkle Pro | K29: 85098000 | L29: =VLOOKUP(E29,'Margin Calculation'!F:U,16,0) -> 3.09 | M29: =VLOOKUP(E29,'Margin Calculation'!F:V,17,0) -> 3.15 | N29: =L29*2% -> 0.0618 | O29: =VLOOKUP(E29,'Margin Calculation'!F:X,19,0) -> 0.693396 | P29: =(L29+N29+O29)*$B$2 -> 338.37725 | Q29: =P29*1.18 -> 399.28515 | R29: =VLOOKUP(E29,'Margin Calculation'!F:AA,22,0) -> 59.925 | S29: 20 | T29: 58 | U29: 137.9 | V29: =AF29*20% -> 159.8 | W29: =AF29*$B$18 -> 7.99 | X29: =AF29*$B$15 -> 39.95 | Y29: =AF29*$B$21 -> 15.98 | Z29: =AF29-(AF29/1.18) -> 121.88136 | AA29: =AF29*$B$16 -> 39.95 | AB29: =AF29*$B$17 -> 23.97 | AC29: =P29+R29+S29+T29+V29+W29+X29+Y29+Z29+AA29+AB29 -> 885.8236 | AD29: =AF29-AC29 -> -86.823604 | AE29: =AD29/AF29 -> -0.10866534 | AF29: =VLOOKUP(F29,AN:AO,2,0) -> 799 | AI29: 1499 | AJ29: =(AF29-P29)-Z29 -> 338.7414 | AK29: =AJ29/AF29 -> 0.42395669 | AL29: 8904422504271 | AN29: B0DNJS23HS | AO29: 5999
D30: Live | E30: FBA79347 | F30: B0D842173P | G30: ETC-05-PI | H30: HPC | I30: Oral Care | J30: Electric Toothbrush - C Type - Pink-Sparkle Pro | K30: 85098000 | L30: =VLOOKUP(E30,'Margin Calculation'!F:U,16,0) -> 3.15 | M30: =VLOOKUP(E30,'Margin Calculation'!F:V,17,0) -> 3.15 | N30: =L30*2% -> 0.063 | O30: =VLOOKUP(E30,'Margin Calculation'!F:X,19,0) -> 0.70686 | P30: =(L30+N30+O30)*$B$2 -> 344.94768 | Q30: =P30*1.18 -> 407.03826 | R30: =VLOOKUP(E30,'Margin Calculation'!F:AA,22,0) -> 59.925 | S30: 20 | T30: 58 | U30: 130.4 | V30: =AF30*20% -> 140.8 | W30: =AF30*$B$18 -> 7.04 | X30: =AF30*$B$15 -> 35.2 | Y30: =AF30*$B$21 -> 14.08 | Z30: =AF30-(AF30/1.18) -> 107.38983 | AA30: =AF30*$B$16 -> 35.2 | AB30: =AF30*$B$17 -> 21.12 | AC30: =P30+R30+S30+T30+V30+W30+X30+Y30+Z30+AA30+AB30 -> 843.70251 | AD30: =AF30-AC30 -> -139.70251 | AE30: =AD30/AF30 -> -0.19844107 | AF30: 704 | AI30: 1499 | AJ30: =(AF30-P30)-Z30 -> 251.66249 | AK30: =AJ30/AF30 -> 0.35747513 | AL30: 8904422504554 | AN30: B0DKJZDY72 | AO30: 1999
D31: Live | E31: FBA79349 | F31: B0D9KDQCCM | G31: SW-01 | H31: Home & Kitchen | I31: Fabric Care | J31: Portable Sewing Machine | K31: 84521021 | L31: =VLOOKUP(E31,'Margin Calculation'!F:U,16,0) -> 3.46 | M31: =VLOOKUP(E31,'Margin Calculation'!F:V,17,0) -> 3.4 | N31: =L31*2% -> 0.0692 | O31: =VLOOKUP(E31,'Margin Calculation'!F:X,19,0) -> 0.388212 | P31: =(L31+N31+O31)*$B$2 -> 344.73226 | Q31: =P31*1.18 -> 406.78406 | R31: =VLOOKUP(E31,'Margin Calculation'!F:AA,22,0) -> 77.935 | S31: 50 | T31: 79 | U31: 193.9 | V31: =AF31*10% -> 109.9 | W31: =AF31*$B$18 -> 10.99 | X31: =AF31*$B$15 -> 54.95 | Y31: =AF31*$B$21 -> 21.98 | Z31: =AF31-(AF31/1.18) -> 167.64407 | AA31: =AF31*$B$16 -> 54.95 | AB31: =AF31*$B$17 -> 32.97 | AC31: =P31+R31+S31+T31+V31+W31+X31+Y31+Z31+AA31+AB31 -> 1005.0513 | AD31: =AF31-AC31 -> 93.948676 | AE31: =AD31/AF31 -> 0.085485602 | AF31: 1099 | AI31: 1299 | AJ31: =(AF31-P31)-Z31 -> 586.62368 | AK31: =AJ31/AF31 -> 0.53377951 | AL31: 8904422504493 | AN31: B0DKJSCLBD | AO31: 2299
D32: Live | E32: FBA79350 | F32: B0D67727VG | G32: EA-01 | H32: HPC | I32: Hair Care | J32: Electric Oil Applicator | K32: 90191020 | L32: =VLOOKUP(E32,'Margin Calculation'!F:U,16,0) -> 6 | M32: =VLOOKUP(E32,'Margin Calculation'!F:V,17,0) -> 6 | N32: =L32*2% -> 0.12 | O32: =VLOOKUP(E32,'Margin Calculation'!F:X,19,0) -> 0.6732 | P32: =(L32+N32+O32)*$B$2 -> 597.8016 | Q32: =P32*1.18 -> 705.40589 | R32: =VLOOKUP(E32,'Margin Calculation'!F:AA,22,0) -> 89.925 | S32: 20 | T32: 58 | U32: 154.4 | V32: =AF32*20% -> 219.8 | W32: =AF32*$B$18 -> 10.99 | X32: =AF32*$B$15 -> 54.95 | Y32: =AF32*$B$21 -> 21.98 | Z32: =AF32-(AF32/1.18) -> 167.64407 | AA32: =AF32*$B$16 -> 54.95 | AB32: =AF32*$B$17 -> 32.97 | AC32: =P32+R32+S32+T32+V32+W32+X32+Y32+Z32+AA32+AB32 -> 1329.0107 | AD32: =AF32-AC32 -> -230.01067 | AE32: =AD32/AF32 -> -0.20929087 | AF32: 1099 | AI32: 2999 | AJ32: =(AF32-P32)-Z32 -> 333.55433 | AK32: =AJ32/AF32 -> 0.30350713 | AL32: 8904422504264 | AN32: B0DKJVWM8Q | AO32: 1599
D33: Live | E33: FBA79352 | F33: B0D637B562 | G33: WF-02-BL | H33: Pet Supplies | I33: Pet Supplies | J33: Nexlev Pet Water Fountain 2L | K33: 84212190 | L33: =VLOOKUP(E33,'Margin Calculation'!F:U,16,0) -> 4.5 | M33: =VLOOKUP(E33,'Margin Calculation'!F:V,17,0) -> 4.7 | N33: =L33*2% -> 0.09 | O33: =VLOOKUP(E33,'Margin Calculation'!F:X,19,0) -> 0.378675 | P33: =(L33+N33+O33)*$B$2 -> 437.2434 | Q33: =P33*1.18 -> 515.94721 | R33: =VLOOKUP(E33,'Margin Calculation'!F:AA,22,0) -> 156.125 | S33: 50 | T33: 76 | U33: 275.9 | V33: =AF33*10% -> 124.9 | W33: =AF33*$B$18 -> 12.49 | X33: =AF33*$B$15 -> 62.45 | Y33: =AF33*$B$21 -> 24.98 | Z33: =AF33-(AF33/1.18) -> 190.52542 | AA33: =AF33*$B$16 -> 62.45 | AB33: =AF33*$B$17 -> 37.47 | AC33: =P33+R33+S33+T33+V33+W33+X33+Y33+Z33+AA33+AB33 -> 1234.6338 | AD33: =AF33-AC33 -> 14.366176 | AE33: =AD33/AF33 -> 0.011502143 | AF33: =VLOOKUP(F33,AN:AO,2,0) -> 1249 | AI33: 2999 | AJ33: =(AF33-P33)-Z33 -> 621.23118 | AK33: =AJ33/AF33 -> 0.49738285 | AL33: 8904422504257 | AN33: B0DMSMKRD9 | AO33: 3599
D34: Live | E34: FBA79381 | F34: B0D9KCNVNM | G34: ETR-06 | H34: HPC | I34: Oral Care | J34: Oscillating Electric Toothbrush Sparkle Plus | K34: 85098000 | L34: =VLOOKUP(E34,'Margin Calculation'!F:U,16,0) -> 5.16 | M34: =VLOOKUP(E34,'Margin Calculation'!F:V,17,0) -> 5.16 | N34: =L34*2% -> 0.1032 | O34: =VLOOKUP(E34,'Margin Calculation'!F:X,19,0) -> 1.157904 | P34: =(L34+N34+O34)*$B$2 -> 565.05715 | Q34: =P34*1.18 -> 666.76744 | R34: =VLOOKUP(E34,'Margin Calculation'!F:AA,22,0) -> 89.925 | S34: 12 | T34: 60 | U34: 126 | V34: =AF34*20% -> 239.8 | W34: =AF34*$B$18 -> 11.99 | X34: =AF34*$B$15 -> 59.95 | Y34: =AF34*$B$21 -> 23.98 | Z34: =AF34-(AF34/1.18) -> 182.89831 | AA34: =AF34*$B$16 -> 59.95 | AB34: =AF34*$B$17 -> 35.97 | AC34: =P34+R34+S34+T34+V34+W34+X34+Y34+Z34+AA34+AB34 -> 1341.5205 | AD34: =AF34-AC34 -> -142.52046 | AE34: =AD34/AF34 -> -0.1188661 | AF34: =VLOOKUP(F34,AN:AO,2,0) -> 1199 | AI34: 1699 | AJ34: =(AF34-P34)-Z34 -> 451.04454 | AK34: =AJ34/AF34 -> 0.37618394 | AL34: 8904422504646 | AN34: B0DM6MG4ZH | AO34: 2599
D35: Live | E35: FBA79404 | F35: B0D9KFZYG8 | G35: FS-01 | H35: HPC | I35: Skin Care | J35: Nexlev Face Steamer | K35: 85437093 | L35: =VLOOKUP(E35,'Margin Calculation'!F:U,16,0) -> 6.65 | M35: =VLOOKUP(E35,'Margin Calculation'!F:V,17,0) -> 6.7 | N35: =L35*2% -> 0.133 | O35: =VLOOKUP(E35,'Margin Calculation'!F:X,19,0) -> 1.49226 | P35: =(L35+N35+O35)*$B$2 -> 728.22288 | Q35: =P35*1.18 -> 859.303 | R35: =VLOOKUP(E35,'Margin Calculation'!F:AA,22,0) -> 122.43 | S35: 50 | T35: 108 | U35: 269.9 | V35: =AF35*20% -> 339.8 | W35: =AF35*$B$18 -> 16.99 | X35: =AF35*$B$15 -> 84.95 | Y35: =AF35*$B$21 -> 33.98 | Z35: =AF35-(AF35/1.18) -> 259.16949 | AA35: =AF35*$B$16 -> 84.95 | AB35: =AF35*$B$17 -> 50.97 | AC35: =P35+R35+S35+T35+V35+W35+X35+Y35+Z35+AA35+AB35 -> 1879.4624 | AD35: =AF35-AC35 -> -180.46237 | AE35: =AD35/AF35 -> -0.10621682 | AF35: 1699 | AI35: 2499 | AJ35: =(AF35-P35)-Z35 -> 711.60763 | AK35: =AJ35/AF35 -> 0.4188391 | AL35: 8904422504653 | AN35: B0DMSHZXG2 | AO35: 1799
D36: Live | E36: FBA79405 | F36: B0D9KFP4MG | G36: HSB-03 | H36: HPC | I36: Hair Care | J36: Nexlev Hair Straightener Brush | K36: 85163200 | L36: =VLOOKUP(E36,'Margin Calculation'!F:U,16,0) -> 6.34 | M36: =VLOOKUP(E36,'Margin Calculation'!F:V,17,0) -> 6.64 | N36: =L36*2% -> 0.1268 | O36: =VLOOKUP(E36,'Margin Calculation'!F:X,19,0) -> 1.422696 | P36: =(L36+N36+O36)*$B$2 -> 694.27565 | Q36: =P36*1.18 -> 819.24526 | R36: =VLOOKUP(E36,'Margin Calculation'!F:AA,22,0) -> 180.405 | S36: 25 | T36: 73 | U36: 277.7 | V36: =AF36*20% -> 379.8 | W36: =AF36*$B$18 -> 18.99 | X36: =AF36*$B$15 -> 94.95 | Y36: =AF36*$B$21 -> 37.98 | Z36: =AF36-(AF36/1.18) -> 289.67797 | AA36: =AF36*$B$16 -> 94.95 | AB36: =AF36*$B$17 -> 56.97 | AC36: =P36+R36+S36+T36+V36+W36+X36+Y36+Z36+AA36+AB36 -> 1945.9986 | AD36: =AF36-AC36 -> -46.998614 | AE36: =AD36/AF36 -> -0.024749139 | AF36: 1899 | AI36: 3599 | AJ36: =(AF36-P36)-Z36 -> 915.04639 | AK36: =AJ36/AF36 -> 0.48185697 | AL36: 8904422504790 | AN36: B0DNJHKZ2G | AO36: 1599
D37: Live | E37: FBA79406 | F37: B0DCK3N2JJ | G37: HSB-04 | H37: HPC | I37: Hair Care | J37: Nexlev Hair Straightener Brush - Portable | K37: 85163200 | L37: =VLOOKUP(E37,'Margin Calculation'!F:U,16,0) -> 7.39 | M37: =VLOOKUP(E37,'Margin Calculation'!F:V,17,0) -> 0 | N37: =L37*2% -> 0.1478 | O37: =VLOOKUP(E37,'Margin Calculation'!F:X,19,0) -> 1.658316 | P37: =(L37+N37+O37)*$B$2 -> 809.25821 | Q37: =P37*1.18 -> 954.92469 | R37: =VLOOKUP(E37,'Margin Calculation'!F:AA,22,0) -> 225.53 | S37: 25 | T37: 73 | U37: 322.8 | V37: =AF37*20% -> 499.8 | W37: =AF37*$B$18 -> 24.99 | X37: =AF37*$B$15 -> 124.95 | Y37: =AF37*$B$21 -> 49.98 | Z37: =AF37-(AF37/1.18) -> 381.20339 | AA37: =AF37*$B$16 -> 124.95 | AB37: =AF37*$B$17 -> 74.97 | AC37: =P37+R37+S37+T37+V37+W37+X37+Y37+Z37+AA37+AB37 -> 2413.6316 | AD37: =AF37-AC37 -> 85.368402 | AE37: =AD37/AF37 -> 0.034161025 | AF37: 2499 | AI37: 3599 | AJ37: =(AF37-P37)-Z37 -> 1308.5384 | AK37: =AJ37/AF37 -> 0.52362481 | AL37: 8904422504813 | AN37: B0DNJF1BLS | AO37: 1499
D38: Live | E38: FBA79439 | F38: B0DCK7ZH5P | G38: MR-02 | H38: Home & Kitchen | I38: Cleaning & Vacumming | J38: Nexlev Cordless Mite Remover | K38: 85086000 | L38: =VLOOKUP(E38,'Margin Calculation'!F:U,16,0) -> 11.3 | M38: =VLOOKUP(E38,'Margin Calculation'!F:V,17,0) -> 11.3 | N38: =L38*2% -> 0.226 | O38: =VLOOKUP(E38,'Margin Calculation'!F:X,19,0) -> 1.26786 | P38: =(L38+N38+O38)*$B$2 -> 1125.8597 | Q38: =P38*1.18 -> 1328.5144 | R38: =VLOOKUP(E38,'Margin Calculation'!F:AA,22,0) -> 148.455 | S38: 50 | T38: 135 | U38: 399.2 | V38: =AF38*10% -> 329.9 | W38: =AF38*$B$18 -> 32.99 | X38: =AF38*$B$15 -> 164.95 | Y38: =AF38*$B$21 -> 65.98 | Z38: =AF38-(AF38/1.18) -> 503.23729 | AA38: =AF38*$B$16 -> 164.95 | AB38: =AF38*$B$17 -> 98.97 | AC38: =P38+R38+S38+T38+V38+W38+X38+Y38+Z38+AA38+AB38 -> 2820.292 | AD38: =AF38-AC38 -> 478.70803 | AE38: =AD38/AF38 -> 0.14510701 | AF38: 3299 | AI38: 6599 | AJ38: =(AF38-P38)-Z38 -> 1669.903 | AK38: =AJ38/AF38 -> 0.50618461 | AL38: 8904422504820 | AN38: B0DNJP9T35 | AO38: 1999
D39: Live | E39: FBA79440 | F39: B0DCGHKRXX | G39: LE-02 | H39: HPC | I39: Skin Care | J39: NEXLEV LED Light Therapy Comb | K39: 85437093 | L39: =VLOOKUP(E39,'Margin Calculation'!F:U,16,0) -> 5.3 | M39: =VLOOKUP(E39,'Margin Calculation'!F:V,17,0) -> 6.8 | N39: =L39*2% -> 0.106 | O39: =VLOOKUP(E39,'Margin Calculation'!F:X,19,0) -> 0.59466 | P39: =(L39+N39+O39)*$B$2 -> 528.05808 | Q39: =P39*1.18 -> 623.10853 | R39: =VLOOKUP(E39,'Margin Calculation'!F:AA,22,0) -> 189.905 | S39: 50 | T39: 60 | U39: 294.9 | V39: =AF39*20% -> 399.8 | W39: =AF39*$B$18 -> 19.99 | X39: =AF39*$B$15 -> 99.95 | Y39: =AF39*$B$21 -> 39.98 | Z39: =AF39-(AF39/1.18) -> 304.9322 | AA39: =AF39*$B$16 -> 99.95 | AB39: =AF39*$B$17 -> 59.97 | AC39: =P39+R39+S39+T39+V39+W39+X39+Y39+Z39+AA39+AB39 -> 1852.5353 | AD39: =AF39-AC39 -> 146.46472 | AE39: =AD39/AF39 -> 0.073268993 | AF39: 1999 | AI39: 2999 | AJ39: =(AF39-P39)-Z39 -> 1166.0097 | AK39: =AJ39/AF39 -> 0.58329651 | AL39: 8904422504837 | AN39: B0DRD8J8R5 | AO39: 1399
D40: Live | E40: FBA79443 | F40: B0D9KFQG8Q | G40: LE-03 | H40: HPC | I40: Skin Care | J40: NEXLEV Light Therapy Skin Scrubber | K40: 85437099 | L40: =VLOOKUP(E40,'Margin Calculation'!F:U,16,0) -> 8.7 | M40: =VLOOKUP(E40,'Margin Calculation'!F:V,17,0) -> 9.4 | N40: =L40*2% -> 0.174 | O40: =VLOOKUP(E40,'Margin Calculation'!F:X,19,0) -> 0.732105 | P40: =(L40+N40+O40)*$B$2 -> 845.33724 | Q40: =P40*1.18 -> 997.49794 | R40: =VLOOKUP(E40,'Margin Calculation'!F:AA,22,0) -> 118.93 | S40: 50 | T40: 60 | U40: 235.9 | V40: =AF40*20% -> 339.8 | W40: =AF40*$B$18 -> 16.99 | X40: =AF40*$B$15 -> 84.95 | Y40: =AF40*$B$21 -> 33.98 | Z40: =AF40-(AF40/1.18) -> 259.16949 | AA40: =AF40*$B$16 -> 84.95 | AB40: =AF40*$B$17 -> 50.97 | AC40: =P40+R40+S40+T40+V40+W40+X40+Y40+Z40+AA40+AB40 -> 1945.0767 | AD40: =AF40-AC40 -> -246.07673 | AE40: =AD40/AF40 -> -0.14483622 | AF40: 1699 | AI40: 3399 | AJ40: =(AF40-P40)-Z40 -> 594.49327 | AK40: =AJ40/AF40 -> 0.34990775 | AL40: 8904422504844 | AN40: B0DVC8NYY2 | AO40: 1599
D41: Live | E41: FBA79452 | F41: B0DCGHVN81 | G41: FS-01 | H41: Home & Kitchen | I41: Cleaning & Vacumming | J41: Nexlev Stick Vacuum Cleaner | K41: 85086000 | L41: =VLOOKUP(E41,'Margin Calculation'!F:U,16,0) -> 8.3 | M41: =VLOOKUP(E41,'Margin Calculation'!F:V,17,0) -> 8.7 | N41: =L41*2% -> 0.166 | O41: =VLOOKUP(E41,'Margin Calculation'!F:X,19,0) -> 0.93126 | P41: =(L41+N41+O41)*$B$2 -> 826.95888 | Q41: =P41*1.18 -> 975.81148 | R41: =VLOOKUP(E41,'Margin Calculation'!F:AA,22,0) -> 94.455 | S41: 50 | T41: 135 | U41: 315.3 | V41: =AF41*10% -> 199.9 | W41: =AF41*$B$18 -> 19.99 | X41: =AF41*$B$15 -> 99.95 | Y41: =AF41*$B$21 -> 39.98 | Z41: =AF41-(AF41/1.18) -> 304.9322 | AA41: =AF41*$B$16 -> 99.95 | AB41: =AF41*$B$17 -> 59.97 | AC41: =P41+R41+S41+T41+V41+W41+X41+Y41+Z41+AA41+AB41 -> 1931.0861 | AD41: =AF41-AC41 -> 67.913917 | AE41: =AD41/AF41 -> 0.033973945 | AF41: =VLOOKUP(F41,AN:AO,2,0) -> 1999 | AI41: 3699 | AJ41: =(AF41-P41)-Z41 -> 867.10892 | AK41: =AJ41/AF41 -> 0.43377134 | AL41: 8904422504882 | AN41: B0DVC968P1 | AO41: 1999
D42: Live | E42: FBA79451 | F42: B0DTK4FY1G | G42: SS-01 | H42: Home & Kitchen | I42: Cleaning & Vacumming | J42: Nexlev Spin Scrubber | K42: 85098000 | L42: =VLOOKUP(E42,'Margin Calculation'!F:U,16,0) -> 9.29 | M42: =VLOOKUP(E42,'Margin Calculation'!F:V,17,0) -> 11.6 | N42: =L42*2% -> 0.1858 | O42: =VLOOKUP(E42,'Margin Calculation'!F:X,19,0) -> 2.084676 | P42: =(L42+N42+O42)*$B$2 -> 1017.3219 | Q42: =P42*1.18 -> 1200.4398 | R42: =VLOOKUP(E42,'Margin Calculation'!F:AA,22,0) -> 249.9 | S42: 50 | T42: 108 | U42: 427.9 | V42: =AF42*10% -> 269.9 | W42: =AF42*$B$18 -> 26.99 | X42: =AF42*$B$15 -> 134.95 | Y42: =AF42*$B$21 -> 53.98 | Z42: =AF42-(AF42/1.18) -> 411.71186 | AA42: =AF42*$B$16 -> 134.95 | AB42: =AF42*$B$17 -> 80.97 | AC42: =P42+R42+S42+T42+V42+W42+X42+Y42+Z42+AA42+AB42 -> 2538.6738 | AD42: =AF42-AC42 -> 160.32625 | AE42: =AD42/AF42 -> 0.059402092 | AF42: 2699 | AI42: 4999 | AJ42: =(AF42-P42)-Z42 -> 1269.9662 | AK42: =AJ42/AF42 -> 0.47053214 | AL42: 8904422504875 | AN42: B0CDQ98FDM | AO42: 699
D43: Live | E43: FBA79463 | F43: B0DCK56Q85 | G43: VC-02 | H43: Home & Kitchen | I43: Cleaning & Vacumming | J43: Nexlev Portable vacuum cleaner - Duster Pro | K43: 85086000 | L43: =VLOOKUP(E43,'Margin Calculation'!F:U,16,0) -> 10.76 | M43: =VLOOKUP(E43,'Margin Calculation'!F:V,17,0) -> 10.76 | N43: =L43*2% -> 0.2152 | O43: =VLOOKUP(E43,'Margin Calculation'!F:X,19,0) -> 2.414544 | P43: =(L43+N43+O43)*$B$2 -> 1178.2975 | Q43: =P43*1.18 -> 1390.391 | R43: =VLOOKUP(E43,'Margin Calculation'!F:AA,22,0) -> 112.455 | S43: 50 | T43: 107 | U43: 319.8 | V43: =AF43*10% -> 249.9 | W43: =AF43*$B$18 -> 24.99 | X43: =AF43*$B$15 -> 124.95 | Y43: =AF43*$B$21 -> 49.98 | Z43: =AF43-(AF43/1.18) -> 381.20339 | AA43: =AF43*$B$16 -> 124.95 | AB43: =AF43*$B$17 -> 74.97 | AC43: =P43+R43+S43+T43+V43+W43+X43+Y43+Z43+AA43+AB43 -> 2478.6959 | AD43: =AF43-AC43 -> 20.304138 | AE43: =AD43/AF43 -> 0.0081249052 | AF43: =VLOOKUP(F43,AN:AO,2,0) -> 2499 | AI43: 4299 | AJ43: =(AF43-P43)-Z43 -> 939.49914 | AK43: =AJ43/AF43 -> 0.37595004 | AL43: 8904422504899 | AN43: B0DVCDD5VC | AO43: 1099
D44: Live | E44: FBA79464 | F44: B0DFCDKMWR | G44: CM-01-BL | H44: HPC | I44: Electric Massagers | J44: Nexlev Cramp Massager Blue | K44: 90191020 | L44: =VLOOKUP(E44,'Margin Calculation'!F:U,16,0) -> 4.7 | M44: =VLOOKUP(E44,'Margin Calculation'!F:V,17,0) -> 0 | N44: =L44*2% -> 0.094 | O44: =VLOOKUP(E44,'Margin Calculation'!F:X,19,0) -> 0.52734 | P44: =(L44+N44+O44)*$B$2 -> 468.27792 | Q44: =P44*1.12 -> 524.47127 | R44: =VLOOKUP(E44,'Margin Calculation'!F:AA,22,0) -> 86.925 | S44: 50 | T44: 79 | U44: 233.9 | V44: =AF44*20% -> 255 | W44: =AF44*$B$18 -> 12.75 | X44: =AF44*$B$15 -> 63.75 | Y44: =AF44*$B$21 -> 25.5 | Z44: =AF44-(AF44/1.18) -> 194.49153 | AA44: =AF44*$B$16 -> 63.75 | AB44: =AF44*$B$17 -> 38.25 | AC44: =P44+R44+S44+T44+V44+W44+X44+Y44+Z44+AA44+AB44 -> 1337.6944 | AD44: =AF44-AC44 -> -62.694445 | AE44: =AD44/AF44 -> -0.049172114 | AF44: 1275 | AI44: 2499 | AJ44: =(AF44-P44)-Z44 -> 612.23055 | AK44: =AJ44/AF44 -> 0.48018083 | AL44: 8904422504929 | AN44: B0DVCBR11D | AO44: 1099
D45: Live | E45: FBA79472 | F45: B0DFCDZWND | G45: CM-02-PR | H45: HPC | I45: Electric Massagers | J45: Nexlev Cramp Massager Purple | K45: 90191020 | L45: =VLOOKUP(E45,'Margin Calculation'!F:U,16,0) -> 4.7 | M45: =VLOOKUP(E45,'Margin Calculation'!F:V,17,0) -> 0 | N45: =L45*2% -> 0.094 | O45: =VLOOKUP(E45,'Margin Calculation'!F:X,19,0) -> 0.52734 | P45: =(L45+N45+O45)*$B$2 -> 468.27792 | Q45: =P45*1.12 -> 524.47127 | R45: =VLOOKUP(E45,'Margin Calculation'!F:AA,22,0) -> 97.425 | S45: 50 | T45: 79 | U45: 220.4 | V45: =AF45*20% -> 259.8 | W45: =AF45*$B$18 -> 12.99 | X45: =AF45*$B$15 -> 64.95 | Y45: =AF45*$B$21 -> 25.98 | Z45: =AF45-(AF45/1.18) -> 198.15254 | AA45: =AF45*$B$16 -> 64.95 | AB45: =AF45*$B$17 -> 38.97 | AC45: =P45+R45+S45+T45+V45+W45+X45+Y45+Z45+AA45+AB45 -> 1360.4955 | AD45: =AF45-AC45 -> -61.495462 | AE45: =AD45/AF45 -> -0.047340618 | AF45: 1299 | AI45: 2499 | AJ45: =(AF45-P45)-Z45 -> 632.56954 | AK45: =AJ45/AF45 -> 0.48696654 | AL45: 8904422504936 | AN45: B0DVC9PRSD | AO45: 15990
D46: Live | E46: FBA79466 | F46: B0DFM4JZV9 | G46: TI-01 | H46: Car & Motorbike | I46: Car Accessories | J46: Corded Tyre Inflator With Touch Control and Carry Pouch | K46: 84148090 | L46: =VLOOKUP(E46,'Margin Calculation'!F:U,16,0) -> 10.7 | M46: =VLOOKUP(E46,'Margin Calculation'!F:V,17,0) -> 10.7 | N46: =L46*2% -> 0.214 | O46: =VLOOKUP(E46,'Margin Calculation'!F:X,19,0) -> 0.900405 | P46: =(L46+N46+O46)*$B$2 -> 1039.6676 | Q46: =P46*1.18 -> 1226.8078 | R46: =VLOOKUP(E46,'Margin Calculation'!F:AA,22,0) -> 298.87 | S46: 50 | T46: 80 | U46: 429.5 | V46: =AF46*10% -> 229.9 | W46: =AF46*$B$18 -> 22.99 | X46: =AF46*$B$15 -> 114.95 | Y46: =AF46*$B$21 -> 45.98 | Z46: =AF46-(AF46/1.18) -> 350.69492 | AA46: =AF46*$B$16 -> 114.95 | AB46: =AF46*$B$17 -> 68.97 | AC46: =P46+R46+S46+T46+V46+W46+X46+Y46+Z46+AA46+AB46 -> 2416.9726 | AD46: =AF46-AC46 -> -117.97256 | AE46: =AD46/AF46 -> -0.051314726 | AF46: =VLOOKUP(F46,AN:AO,2,0) -> 2299 | AI46: 4199 | AJ46: =(AF46-P46)-Z46 -> 908.63744 | AK46: =AJ46/AF46 -> 0.3952316 | AL46: 8904422504905 | AN46: B0DVC9Q219 | AO46: 9999
D47: Live | E47: FBA79467 | F47: B0DK9LYT4P | G47: TM-01 | H47: HPC | I47: Trimmers & Body Groomers | J47: Beard Boss Men Beard Trimmer | K47: 85101000 | L47: =VLOOKUP(E47,'Margin Calculation'!F:U,16,0) -> 3.7 | M47: =VLOOKUP(E47,'Margin Calculation'!F:V,17,0) -> 3.7 | N47: =L47*2% -> 0.074 | O47: =VLOOKUP(E47,'Margin Calculation'!F:X,19,0) -> 0.83028 | P47: =(L47+N47+O47)*$B$2 -> 405.17664 | Q47: =P47*1.18 -> 478.10844 | R47: =VLOOKUP(E47,'Margin Calculation'!F:AA,22,0) -> 62.93 | S47: 50 | T47: 60 | U47: 219.9 | V47: =AF47*20% -> 158 | W47: =AF47*$B$18 -> 7.9 | X47: =AF47*$B$15 -> 39.5 | Y47: =AF47*$B$21 -> 15.8 | Z47: =AF47-(AF47/1.18) -> 120.50847 | AA47: =AF47*$B$16 -> 39.5 | AB47: =AF47*$B$17 -> 23.7 | AC47: =P47+R47+S47+T47+V47+W47+X47+Y47+Z47+AA47+AB47 -> 983.01511 | AD47: =AF47-AC47 -> -193.01511 | AE47: =AD47/AF47 -> -0.24432293 | AF47: 790 | AI47: 1499 | AJ47: =(AF47-P47)-Z47 -> 264.31489 | AK47: =AJ47/AF47 -> 0.3345758 | AL47: 8904422504912 | AN47: B0DVC7VJP1 | AO47: 5699
D48: Live | E48: FBA79468 | F48: B0DTYDTKN8 | G48: SPM-01 | H48: Cleaning & Vacumming | J48: Nexlev Spin Mop | K48: 85098000 | L48: =VLOOKUP(E48,'Margin Calculation'!F:U,16,0) -> #N/A | M48: =VLOOKUP(E48,'Margin Calculation'!F:V,17,0) -> #N/A | N48: =L48*2% -> #N/A | O48: =VLOOKUP(E48,'Margin Calculation'!F:X,19,0) -> #N/A | P48: =(L48+N48+O48)*$B$2 -> #N/A | Q48: =P48*1.18 -> #N/A | R48: =VLOOKUP(E48,'Margin Calculation'!F:AA,22,0) -> #N/A | S48: 60 | T48: 163 | U48: 450.8 | V48: =AF48*10% -> 399.9 | W48: =AF48*$B$18 -> 39.99 | X48: =AF48*$B$15 -> 199.95 | Y48: =AF48*$B$21 -> 79.98 | Z48: =AF48-(AF48/1.18) -> 610.01695 | AA48: =AF48*$B$16 -> 199.95 | AB48: =AF48*$B$17 -> 119.97 | AC48: =P48+R48+S48+T48+V48+W48+X48+Y48+Z48+AA48+AB48 -> #N/A | AD48: =AF48-AC48 -> #N/A | AE48: =AD48/AF48 -> #N/A | AF48: 3999 | AI48: 7499 | AJ48: =(AF48-P48)-Z48 -> #N/A | AK48: =AJ48/AF48 -> #N/A | AL48: 8904422504943 | AN48: B0DV8XH455 | AO48: 1899
D49: Live | E49: FBA79469 | F49: B0DCK4DR1B | G49: LE-04 | H49: HPC | I49: Skin Care | J49: Nexlev Skin Lift Device | K49: 85437093 | L49: =VLOOKUP(E49,'Margin Calculation'!F:U,16,0) -> 5 | M49: =VLOOKUP(E49,'Margin Calculation'!F:V,17,0) -> 5 | N49: =L49*2% -> 0.1 | O49: =VLOOKUP(E49,'Margin Calculation'!F:X,19,0) -> 0.561 | P49: =(L49+N49+O49)*$B$2 -> 498.168 | Q49: =P49*1.18 -> 587.83824 | R49: =VLOOKUP(E49,'Margin Calculation'!F:AA,22,0) -> 217.355 | S49: 50 | T49: 59 | U49: 225.2 | V49: =AF49*20% -> 299.8 | W49: =AF49*$B$18 -> 14.99 | X49: =AF49*$B$15 -> 74.95 | Y49: =AF49*$B$21 -> 29.98 | Z49: =AF49-(AF49/1.18) -> 228.66102 | AA49: =AF49*$B$16 -> 74.95 | AB49: =AF49*$B$17 -> 44.97 | AC49: =P49+R49+S49+T49+V49+W49+X49+Y49+Z49+AA49+AB49 -> 1592.824 | AD49: =AF49-AC49 -> -93.824017 | AE49: =AD49/AF49 -> -0.062591072 | AF49: 1499 | AI49: 2499 | AJ49: =(AF49-P49)-Z49 -> 772.17098 | AK49: =AJ49/AF49 -> 0.51512407 | AL49: 8904422505131 | AN49: B0DV9MYK6S | AO49: 1999
D50: Live | E50: FBA79473 | F50: B0DJFH6RTL | G50: TI-02 | H50: Car & Motorbike | I50: Car Accessories | J50: Nexlev Corded Tyre Inflator | K50: 84148090 | L50: =VLOOKUP(E50,'Margin Calculation'!F:U,16,0) -> 7 | M50: =VLOOKUP(E50,'Margin Calculation'!F:V,17,0) -> 7.4 | N50: =L50*2% -> 0.14 | O50: =VLOOKUP(E50,'Margin Calculation'!F:X,19,0) -> 0.58905 | P50: =(L50+N50+O50)*$B$2 -> 680.1564 | Q50: =P50*1.18 -> 802.58455 | R50: =VLOOKUP(E50,'Margin Calculation'!F:AA,22,0) -> 209.85 | S50: 50 | T50: 80 | U50: 354.9 | V50: =AF50*10% -> 149.9 | W50: =AF50*$B$18 -> 14.99 | X50: =AF50*$B$15 -> 74.95 | Y50: =AF50*$B$21 -> 29.98 | Z50: =AF50-(AF50/1.18) -> 228.66102 | AA50: =AF50*$B$16 -> 74.95 | AB50: =AF50*$B$17 -> 44.97 | AC50: =P50+R50+S50+T50+V50+W50+X50+Y50+Z50+AA50+AB50 -> 1638.4074 | AD50: =AF50-AC50 -> -139.40742 | AE50: =AD50/AF50 -> -0.093000278 | AF50: =VLOOKUP(F50,AN:AO,2,0) -> 1499 | AI50: 2799 | AJ50: =(AF50-P50)-Z50 -> 590.18258 | AK50: =AJ50/AF50 -> 0.39371753 | AL50: 8904422505100 | AN50: B0DV8V3Y88 | AO50: 1499
D51: Live | E51: FBA79474 | F51: B0DJFH4K8B | G51: TIC-03 | H51: Car & Motorbike | I51: Car Accessories | J51: Nexlev Cordeless Tyre Inflator 4000mAh | K51: 84148090 | L51: =VLOOKUP(E51,'Margin Calculation'!F:U,16,0) -> 7 | M51: =VLOOKUP(E51,'Margin Calculation'!F:V,17,0) -> 7 | N51: =L51*2% -> 0.14 | O51: =VLOOKUP(E51,'Margin Calculation'!F:X,19,0) -> 0.58905 | P51: =(L51+N51+O51)*$B$2 -> 680.1564 | Q51: =P51*1.18 -> 802.58455 | R51: =VLOOKUP(E51,'Margin Calculation'!F:AA,22,0) -> 253.37 | S51: 50 | T51: 76 | U51: 372.9 | V51: =AF51*10% -> 194.9 | W51: =AF51*$B$18 -> 19.49 | X51: =AF51*$B$15 -> 97.45 | Y51: =AF51*$B$21 -> 38.98 | Z51: =AF51-(AF51/1.18) -> 297.30508 | AA51: =AF51*$B$16 -> 97.45 | AB51: =AF51*$B$17 -> 58.47 | AC51: =P51+R51+S51+T51+V51+W51+X51+Y51+Z51+AA51+AB51 -> 1863.5715 | AD51: =AF51-AC51 -> 85.428515 | AE51: =AD51/AF51 -> 0.043831973 | AF51: =VLOOKUP(F51,AN:AO,2,0) -> 1949 | AI51: 3699 | AJ51: =(AF51-P51)-Z51 -> 971.53852 | AK51: =AJ51/AF51 -> 0.49848051 | AL51: 8904422505117 | AN51: B0DV94R4QD | AO51: 1099
D52: Live | E52: FBA79475 | F52: B0DJFJZMC6 | G52: TIC-04 | H52: Car & Motorbike | I52: Car Accessories | J52: Nexlev Cordeless Tyre Inflator 6000mAh | K52: 84148090 | L52: =VLOOKUP(E52,'Margin Calculation'!F:U,16,0) -> 9.42 | M52: =VLOOKUP(E52,'Margin Calculation'!F:V,17,0) -> 12 | N52: =L52*2% -> 0.1884 | O52: =VLOOKUP(E52,'Margin Calculation'!F:X,19,0) -> 0.792693 | P52: =(L52+N52+O52)*$B$2 -> 915.29618 | Q52: =P52*1.18 -> 1080.0495 | R52: =VLOOKUP(E52,'Margin Calculation'!F:AA,22,0) -> 344.85 | S52: 50 | T52: 80 | U52: 474.9 | V52: =AF52*10% -> 229.9 | W52: =AF52*$B$18 -> 22.99 | X52: =AF52*$B$15 -> 114.95 | Y52: =AF52*$B$21 -> 45.98 | Z52: =AF52-(AF52/1.18) -> 350.69492 | AA52: =AF52*$B$16 -> 114.95 | AB52: =AF52*$B$17 -> 68.97 | AC52: =P52+R52+S52+T52+V52+W52+X52+Y52+Z52+AA52+AB52 -> 2338.5811 | AD52: =AF52-AC52 -> -39.581099 | AE52: =AD52/AF52 -> -0.017216659 | AF52: =VLOOKUP(F52,AN:AO,2,0) -> 2299 | AI52: 4699 | AJ52: =(AF52-P52)-Z52 -> 1033.0089 | AK52: =AJ52/AF52 -> 0.44932967 | AL52: 8904422505124 | AN52: B0DV9CY3XR | AO52: 2299
D53: Live | E53: FBA79480 | F53: B0DDC3GVZW | G53: VC-03 | H53: Home & Kitchen | I53: Cleaning & Vacumming | J53: Nexlev Car Vacuum Cleaner with safety feature | K53: 85086000 | L53: =VLOOKUP(E53,'Margin Calculation'!F:U,16,0) -> 6.73 | M53: =VLOOKUP(E53,'Margin Calculation'!F:V,17,0) -> 6.73 | N53: =L53*2% -> 0.1346 | O53: =VLOOKUP(E53,'Margin Calculation'!F:X,19,0) -> 1.510212 | P53: =(L53+N53+O53)*$B$2 -> 736.98346 | Q53: =P53*1.18 -> 869.64048 | R53: =VLOOKUP(E53,'Margin Calculation'!F:AA,22,0) -> 89.955 | S53: 50 | T53: 107 | U53: 286.9 | V53: =AF53*10% -> 199.9 | W53: =AF53*$B$18 -> 19.99 | X53: =AF53*$B$15 -> 99.95 | Y53: =AF53*$B$21 -> 39.98 | Z53: =AF53-(AF53/1.18) -> 304.9322 | AA53: =AF53*$B$16 -> 99.95 | AB53: =AF53*$B$17 -> 59.97 | AC53: =P53+R53+S53+T53+V53+W53+X53+Y53+Z53+AA53+AB53 -> 1808.6107 | AD53: =AF53-AC53 -> 190.38934 | AE53: =AD53/AF53 -> 0.095242291 | AF53: =VLOOKUP(F53,AN:AO,2,0) -> 1999 | AI53: 3999 | AJ53: =(AF53-P53)-Z53 -> 957.08434 | AK53: =AJ53/AF53 -> 0.47878156 | AL53: 8904422505001 | AN53: B0DV8TR64D | AO53: 9999
D54: Live | E54: FBA79481 | F54: B0DFMRG2K4 | G54: TM-02 | H54: HPC | I54: Trimmers & Body Groomers | J54: NexLev Multi-Trimmer for Men | K54: 85101000 | L54: =VLOOKUP(E54,'Margin Calculation'!F:U,16,0) -> 10 | M54: =VLOOKUP(E54,'Margin Calculation'!F:V,17,0) -> 10 | N54: =L54*2% -> 0.2 | O54: =VLOOKUP(E54,'Margin Calculation'!F:X,19,0) -> 2.244 | P54: =(L54+N54+O54)*$B$2 -> 1095.072 | Q54: =P54*1.18 -> 1292.185 | R54: =VLOOKUP(E54,'Margin Calculation'!F:AA,22,0) -> 268.755 | S54: 50 | T54: 60 | U54: 379.9 | V54: =AF54*20% -> 439.8 | W54: =AF54*$B$18 -> 21.99 | X54: =AF54*$B$15 -> 109.95 | Y54: =AF54*$B$21 -> 43.98 | Z54: =AF54-(AF54/1.18) -> 335.44068 | AA54: =AF54*$B$16 -> 109.95 | AB54: =AF54*$B$17 -> 65.97 | AC54: =P54+R54+S54+T54+V54+W54+X54+Y54+Z54+AA54+AB54 -> 2600.9077 | AD54: =AF54-AC54 -> -401.90768 | AE54: =AD54/AF54 -> -0.18276838 | AF54: 2199 | AI54: 3999 | AJ54: =(AF54-P54)-Z54 -> 768.48732 | AK54: =AJ54/AF54 -> 0.34947127 | AL54: 8904422505018 | AN54: B0DVSZ2VVJ | AO54: 5499
D55: Live | E55: FBA79484 | F55: B0DNJF1BLS | G55: CF-01 | H55: Kitchen Appliances | I55: Home & Kitchen Appliances | J55: Nexlev Drip Coffee Maker | K55: 85167100 | L55: =VLOOKUP(E55,'Margin Calculation'!F:U,16,0) -> 5.2 | M55: =VLOOKUP(E55,'Margin Calculation'!F:V,17,0) -> 5.2 | N55: =L55*2% -> 0.104 | O55: =VLOOKUP(E55,'Margin Calculation'!F:X,19,0) -> 1.16688 | P55: =(L55+N55+O55)*$B$2 -> 569.43744 | Q55: =P55*1.18 -> 671.93618 | R55: =VLOOKUP(E55,'Margin Calculation'!F:AA,22,0) -> 67.455 | S55: 50 | T55: 153 | U55: 300.4 | V55: =AF55*10% -> 149.9 | W55: =AF55*$B$18 -> 14.99 | X55: =AF55*$B$15 -> 74.95 | Y55: =AF55*$B$21 -> 29.98 | Z55: =AF55-(AF55/1.18) -> 228.66102 | AA55: =AF55*$B$16 -> 74.95 | AB55: =AF55*$B$17 -> 44.97 | AC55: =P55+R55+S55+T55+V55+W55+X55+Y55+Z55+AA55+AB55 -> 1458.2935 | AD55: =AF55-AC55 -> 40.706543 | AE55: =AD55/AF55 -> 0.027155799 | AF55: =VLOOKUP(F55,AN:AO,2,0) -> 1499 | AI55: 2699 | AJ55: =(AF55-P55)-Z55 -> 700.90154 | AK55: =AJ55/AF55 -> 0.46757941 | AL55: 8904422505179 | AN55: B0DV931G48 | AO55: 1799
D56: Live | E56: FBA79483 | F56: B0DK9NRBWJ | G56: TM-03 | H56: HPC | J56: Nexlev Intimate Body Trimmer With Charging Base, Display and Light | K56: 85101000 | L56: =VLOOKUP(E56,'Margin Calculation'!F:U,16,0) -> 4.55 | M56: =VLOOKUP(E56,'Margin Calculation'!F:V,17,0) -> 4.55 | N56: =L56*2% -> 0.091 | O56: =VLOOKUP(E56,'Margin Calculation'!F:X,19,0) -> 1.02102 | P56: =(L56+N56+O56)*$B$2 -> 498.25776 | Q56: =P56*1.18 -> 587.94416 | R56: =VLOOKUP(E56,'Margin Calculation'!F:AA,22,0) -> 103.455 | S56: 50 | T56: 60 | U56: 286.4 | V56: =AF56*20% -> 226.6 | W56: =AF56*$B$18 -> 11.33 | X56: =AF56*$B$15 -> 56.65 | Y56: =AF56*$B$21 -> 22.66 | Z56: =AF56-(AF56/1.18) -> 172.83051 | AA56: =AF56*$B$16 -> 56.65 | AB56: =AF56*$B$17 -> 33.99 | AC56: =P56+R56+S56+T56+V56+W56+X56+Y56+Z56+AA56+AB56 -> 1292.4233 | AD56: =AF56-AC56 -> -159.42327 | AE56: =AD56/AF56 -> -0.14070897 | AF56: 1133 | AI56: 1999 | AJ56: =(AF56-P56)-Z56 -> 461.91173 | AK56: =AJ56/AF56 -> 0.40768908 | AL56: 8904422505094 | AN56: B0DVC58QPZ | AO56: 3598
D57: Live | E57: FBA79485 | F57: B0DK9QNKK8 | G57: TM-04 | H57: HPC | J57: Nexlev Intimate Body Trimmer and Nose Trimmer | K57: 85101000 | L57: =VLOOKUP(E57,'Margin Calculation'!F:U,16,0) -> 3.52 | M57: =VLOOKUP(E57,'Margin Calculation'!F:V,17,0) -> 3.52 | N57: =L57*2% -> 0.0704 | O57: =VLOOKUP(E57,'Margin Calculation'!F:X,19,0) -> 0.789888 | P57: =(L57+N57+O57)*$B$2 -> 385.46534 | Q57: =P57*1.18 -> 454.84911 | R57: =VLOOKUP(E57,'Margin Calculation'!F:AA,22,0) -> 113.905 | S57: 50 | T57: 60 | U57: 237.5 | V57: =AF57*20% -> 199.8 | W57: =AF57*$B$18 -> 9.99 | X57: =AF57*$B$15 -> 49.95 | Y57: =AF57*$B$21 -> 19.98 | Z57: =AF57-(AF57/1.18) -> 152.38983 | AA57: =AF57*$B$16 -> 49.95 | AB57: =AF57*$B$17 -> 29.97 | AC57: =P57+R57+S57+T57+V57+W57+X57+Y57+Z57+AA57+AB57 -> 1121.4002 | AD57: =AF57-AC57 -> -122.40017 | AE57: =AD57/AF57 -> -0.1225227 | AF57: 999 | AI57: 1599 | AJ57: =(AF57-P57)-Z57 -> 461.14483 | AK57: =AJ57/AF57 -> 0.46160643 | AL57: 8904422505087 | AN57: B0CDQ55W2M | AO57: 699
D58: Live | E58: FBA79488 | F58: B0DFCG2VGS | G58: KE-01 | H58: Home & Kitchen | I58: Kitchen Appliances | J58: Nexlev Multi-Purpose Food Kettle 1.8L | K58: 85167990 | L58: =VLOOKUP(E58,'Margin Calculation'!F:U,16,0) -> 7.25 | M58: =VLOOKUP(E58,'Margin Calculation'!F:V,17,0) -> 7.25 | N58: =L58*2% -> 0.145 | O58: =VLOOKUP(E58,'Margin Calculation'!F:X,19,0) -> 1.6269 | P58: =(L58+N58+O58)*$B$2 -> 793.9272 | Q58: =P58*1.18 -> 936.8341 | R58: =VLOOKUP(E58,'Margin Calculation'!F:AA,22,0) -> 76.455 | S58: 50 | T58: 107 | U58: 267.4 | V58: =AF58*10% -> 169.9 | W58: =AF58*$B$18 -> 16.99 | X58: =AF58*$B$15 -> 84.95 | Y58: =AF58*$B$21 -> 33.98 | Z58: =AF58-(AF58/1.18) -> 259.16949 | AA58: =AF58*$B$16 -> 84.95 | AB58: =AF58*$B$17 -> 50.97 | AC58: =P58+R58+S58+T58+V58+W58+X58+Y58+Z58+AA58+AB58 -> 1728.2917 | AD58: =AF58-AC58 -> -29.291692 | AE58: =AD58/AF58 -> -0.017240548 | AF58: =VLOOKUP(F58,AN:AO,2,0) -> 1699 | AI58: 2799 | AJ58: =(AF58-P58)-Z58 -> 645.90331 | AK58: =AJ58/AF58 -> 0.38016675 | AL58: 8904422505148 | AN58: B0CDQ6G4TC | AO58: 699
D59: Live | E59: FBA79489 | F59: B0DFD123P5 | G59: KE-02 | H59: Home & Kitchen | I59: Kitchen Appliances | J59: Nexlev Multi-Purpose Food Kettle 1.5L | K59: 85167990 | L59: =VLOOKUP(E59,'Margin Calculation'!F:U,16,0) -> 7.25 | M59: =VLOOKUP(E59,'Margin Calculation'!F:V,17,0) -> 7.25 | N59: =L59*2% -> 0.145 | O59: =VLOOKUP(E59,'Margin Calculation'!F:X,19,0) -> 1.6269 | P59: =(L59+N59+O59)*$B$2 -> 793.9272 | Q59: =P59*1.18 -> 936.8341 | R59: =VLOOKUP(E59,'Margin Calculation'!F:AA,22,0) -> 71.955 | S59: 50 | T59: 107 | U59: 254.4 | V59: =AF59*10% -> 149.9 | W59: =AF59*$B$18 -> 14.99 | X59: =AF59*$B$15 -> 74.95 | Y59: =AF59*$B$21 -> 29.98 | Z59: =AF59-(AF59/1.18) -> 228.66102 | AA59: =AF59*$B$16 -> 74.95 | AB59: =AF59*$B$17 -> 44.97 | AC59: =P59+R59+S59+T59+V59+W59+X59+Y59+Z59+AA59+AB59 -> 1641.2832 | AD59: =AF59-AC59 -> -142.28322 | AE59: =AD59/AF59 -> -0.094918757 | AF59: =VLOOKUP(F59,AN:AO,2,0) -> 1499 | AI59: 2799 | AJ59: =(AF59-P59)-Z59 -> 476.41178 | AK59: =AJ59/AF59 -> 0.31781974 | AL59: 8904422505155 | AN59: B0DQ8W1RBV | AO59: 1599
D60: Live | E60: FBA79492 | F60: B0DT6Y7KJM | G60: V-02 | H60: HPC | I60: Hair Care | J60: Nexlev Volumizer Straightener | K60: 85163100 | L60: =VLOOKUP(E60,'Margin Calculation'!F:U,16,0) -> 8.32 | M60: =VLOOKUP(E60,'Margin Calculation'!F:V,17,0) -> 8.32 | N60: =L60*2% -> 0.1664 | O60: =VLOOKUP(E60,'Margin Calculation'!F:X,19,0) -> 1.867008 | P60: =(L60+N60+O60)*$B$2 -> 911.0999 | Q60: =P60*1.18 -> 1075.0979 | R60: =VLOOKUP(E60,'Margin Calculation'!F:AA,22,0) -> 208.905 | S60: 47 | T60: 78 | U60: 394.9 | V60: =AF60*20% -> 399.8 | W60: =AF60*$B$18 -> 19.99 | X60: =AF60*$B$15 -> 99.95 | Y60: =AF60*$B$21 -> 39.98 | Z60: =AF60-(AF60/1.18) -> 304.9322 | AA60: =AF60*$B$16 -> 99.95 | AB60: =AF60*$B$17 -> 59.97 | AC60: =P60+R60+S60+T60+V60+W60+X60+Y60+Z60+AA60+AB60 -> 2269.5771 | AD60: =AF60-AC60 -> -270.57711 | AE60: =AD60/AF60 -> -0.13535623 | AF60: 1999 | AI60: 3699 | AJ60: =(AF60-P60)-Z60 -> 782.96789 | AK60: =AJ60/AF60 -> 0.39167979 | AL60: 8904422505186 | AN60: B0DCGHKRXX | AO60: 2049
D61: Live | E61: FBA79493 | F61: B0DQCWRG3H | G61: V-03 | H61: HPC | I61: Hair Care | J61: Nexlev Volumizer Dryer | K61: 85163100 | L61: =VLOOKUP(E61,'Margin Calculation'!F:U,16,0) -> 6.47 | M61: =VLOOKUP(E61,'Margin Calculation'!F:V,17,0) -> 6.47 | N61: =L61*2% -> 0.1294 | O61: =VLOOKUP(E61,'Margin Calculation'!F:X,19,0) -> 1.451868 | P61: =(L61+N61+O61)*$B$2 -> 708.51158 | Q61: =P61*1.18 -> 836.04367 | R61: =VLOOKUP(E61,'Margin Calculation'!F:AA,22,0) -> 192.755 | S61: 50 | T61: 79 | U61: 308.9 | V61: =AF61*20% -> 399.6 | W61: =AF61*$B$18 -> 19.98 | X61: =AF61*$B$15 -> 99.9 | Y61: =AF61*$B$21 -> 39.96 | Z61: =AF61-(AF61/1.18) -> 304.77966 | AA61: =AF61*$B$16 -> 99.9 | AB61: =AF61*$B$17 -> 59.94 | AC61: =P61+R61+S61+T61+V61+W61+X61+Y61+Z61+AA61+AB61 -> 2054.3262 | AD61: =AF61-AC61 -> -56.326245 | AE61: =AD61/AF61 -> -0.028191314 | AF61: 1998 | AI61: 3399 | AJ61: =(AF61-P61)-Z61 -> 984.70875 | AK61: =AJ61/AF61 -> 0.49284722 | AL61: 8904422505193 | AN61: B0F29SZCVF | AO61: 1549
D62: Live | E62: FBA79567 | F62: B0DNJS23HS | G62: SC-04 | H62: Home & Kitchen | I62: Cleaning & Vacumming | J62: Nexlev 10 in 1 Steam Cleaner | K62: 85098000 | L62: =VLOOKUP(E62,'Margin Calculation'!F:U,16,0) -> 20 | M62: =VLOOKUP(E62,'Margin Calculation'!F:V,17,0) -> 20 | N62: =L62*2% -> 0.4 | O62: =VLOOKUP(E62,'Margin Calculation'!F:X,19,0) -> 4.488 | P62: =(L62+N62+O62)*$B$2 -> 2190.144 | Q62: =P62*1.18 -> 2584.3699 | R62: =VLOOKUP(E62,'Margin Calculation'!F:AA,22,0) -> 479.92 | S62: 47 | T62: 162 | U62: 688.9 | V62: =AF62*10% -> 579.9 | W62: =AF62*$B$18 -> 57.99 | X62: =AF62*$B$15 -> 289.95 | Y62: =AF62*$B$21 -> 115.98 | Z62: =AF62-(AF62/1.18) -> 884.59322 | AA62: =AF62*$B$16 -> 289.95 | AB62: =AF62*$B$17 -> 173.97 | AC62: =P62+R62+S62+T62+V62+W62+X62+Y62+Z62+AA62+AB62 -> 5271.3972 | AD62: =AF62-AC62 -> 527.60278 | AE62: =AD62/AF62 -> 0.090981683 | AF62: 5799 | AI62: 8299 | AJ62: =(AF62-P62)-Z62 -> 2724.2628 | AK62: =AJ62/AF62 -> 0.46978148 | AL62: 8904422505223 | AN62: B0DM66B2DW | AO62: 1549
D63: Live | E63: FBA79566 | F63: B0DKJSCLBD | G63: VC-05 | H63: Home & Kitchen | I63: Cleaning & Vacumming | J63: Nexlev Portable Vacuum Cleaner and Blower | K63: 85086000 | L63: =VLOOKUP(E63,'Margin Calculation'!F:U,16,0) -> 8.83 | M63: =VLOOKUP(E63,'Margin Calculation'!F:V,17,0) -> 0 | N63: =L63*2% -> 0.1766 | O63: =VLOOKUP(E63,'Margin Calculation'!F:X,19,0) -> 1.981452 | P63: =(L63+N63+O63)*$B$2 -> 966.94858 | Q63: =P63*1.18 -> 1140.9993 | R63: =VLOOKUP(E63,'Margin Calculation'!F:AA,22,0) -> 172.425 | S63: 50 | T63: 107 | U63: 329.8 | V63: =AF63*10% -> 229.9 | W63: =AF63*$B$18 -> 22.99 | X63: =AF63*$B$15 -> 114.95 | Y63: =AF63*$B$21 -> 45.98 | Z63: =AF63-(AF63/1.18) -> 350.69492 | AA63: =AF63*$B$16 -> 114.95 | AB63: =AF63*$B$17 -> 68.97 | AC63: =P63+R63+S63+T63+V63+W63+X63+Y63+Z63+AA63+AB63 -> 2244.8085 | AD63: =AF63-AC63 -> 54.191509 | AE63: =AD63/AF63 -> 0.023571774 | AF63: =VLOOKUP(F63,AN:AO,2,0) -> 2299 | AI63: 4499 | AJ63: =(AF63-P63)-Z63 -> 981.35651 | AK63: =AJ63/AF63 -> 0.42686234 | AL63: 8904422505209 | AN63: B0F43P6D23 | AO63: 2999
D64: Live | E64: FBA79565 | F64: B0DKJZDY72 | G64: VC-04 | H64: Home & Kitchen | I64: Cleaning & Vacumming | J64: Nexlev Portable Vacuum Cleaner and Blower | K64: 85086000 | L64: =VLOOKUP(E64,'Margin Calculation'!F:U,16,0) -> 9.35 | M64: =VLOOKUP(E64,'Margin Calculation'!F:V,17,0) -> 9.35 | N64: =L64*2% -> 0.187 | O64: =VLOOKUP(E64,'Margin Calculation'!F:X,19,0) -> 2.09814 | P64: =(L64+N64+O64)*$B$2 -> 1023.8923 | Q64: =P64*1.18 -> 1208.1929 | R64: =VLOOKUP(E64,'Margin Calculation'!F:AA,22,0) -> 187.425 | S64: 50 | T64: 107 | U64: 386.9 | V64: =AF64*10% -> 249.9 | W64: =AF64*$B$18 -> 24.99 | X64: =AF64*$B$15 -> 124.95 | Y64: =AF64*$B$21 -> 49.98 | Z64: =AF64-(AF64/1.18) -> 381.20339 | AA64: =AF64*$B$16 -> 124.95 | AB64: =AF64*$B$17 -> 74.97 | AC64: =P64+R64+S64+T64+V64+W64+X64+Y64+Z64+AA64+AB64 -> 2399.2607 | AD64: =AF64-AC64 -> 99.73929 | AE64: =AD64/AF64 -> 0.039911681 | AF64: 2499 | AI64: 4499 | AJ64: =(AF64-P64)-Z64 -> 1093.9043 | AK64: =AJ64/AF64 -> 0.43773681 | AL64: 8904422505209 | AN64: B0DVC91Q7J | AO64: 2499
D65: Live | E65: FBA79570 | F65: B0DKJXRXKM | G65: BR-01 | H65: HPC | J65: Nexlev Black Head Remover | K65: 85437093 | L65: =VLOOKUP(E65,'Margin Calculation'!F:U,16,0) -> 4.5 | M65: =VLOOKUP(E65,'Margin Calculation'!F:V,17,0) -> 4.5 | N65: =L65*2% -> 0.09 | O65: =VLOOKUP(E65,'Margin Calculation'!F:X,19,0) -> 0.5049 | P65: =(L65+N65+O65)*$B$2 -> 448.3512 | Q65: =P65*1.18 -> 529.05442 | R65: =VLOOKUP(E65,'Margin Calculation'!F:AA,22,0) -> 108.43 | S65: 20 | T65: 59 | U65: 186.6 | V65: =AF65*20% -> 309.8 | W65: =AF65*$B$18 -> 15.49 | X65: =AF65*$B$15 -> 77.45 | Y65: =AF65*$B$21 -> 30.98 | Z65: =AF65-(AF65/1.18) -> 236.28814 | AA65: =AF65*$B$16 -> 77.45 | AB65: =AF65*$B$17 -> 46.47 | AC65: =P65+R65+S65+T65+V65+W65+X65+Y65+Z65+AA65+AB65 -> 1429.7093 | AD65: =AF65-AC65 -> 119.29066 | AE65: =AD65/AF65 -> 0.077011404 | AF65: 1549 | AI65: 1699 | AJ65: =(AF65-P65)-Z65 -> 864.36066 | AK65: =AJ65/AF65 -> 0.55801205 | AL65: 8904422505254 | AN65: B0D672NXC8 | AO65: 6999
D66: Live | E66: FBA79571 | F66: B0DKK12XWR | G66: IPL-01 | H66: HPC | I66: Hair Care | J66: Nexlev IPL Hair Removal Device | K66: 85437093 | L66: =VLOOKUP(E66,'Margin Calculation'!F:U,16,0) -> 11 | M66: =VLOOKUP(E66,'Margin Calculation'!F:V,17,0) -> 0 | N66: =L66*2% -> 0.22 | O66: =VLOOKUP(E66,'Margin Calculation'!F:X,19,0) -> 1.2342 | P66: =(L66+N66+O66)*$B$2 -> 1095.9696 | Q66: =P66*1.18 -> 1293.2441 | R66: =VLOOKUP(E66,'Margin Calculation'!F:AA,22,0) -> 284.905 | S66: 50 | T66: 79 | U66: 389.9 | V66: =AF66*20% -> 659.8 | W66: =AF66*$B$18 -> 32.99 | X66: =AF66*$B$15 -> 164.95 | Y66: =AF66*$B$21 -> 65.98 | Z66: =AF66-(AF66/1.18) -> 503.23729 | AA66: =AF66*$B$16 -> 164.95 | AB66: =AF66*$B$17 -> 98.97 | AC66: =P66+R66+S66+T66+V66+W66+X66+Y66+Z66+AA66+AB66 -> 3200.7519 | AD66: =AF66-AC66 -> 98.248112 | AE66: =AD66/AF66 -> 0.02978118 | AF66: 3299 | AI66: 5399 | AJ66: =(AF66-P66)-Z66 -> 1699.7931 | AK66: =AJ66/AF66 -> 0.51524496 | AL66: 8904422505261 | AN66: B0DKJXRXKM | AO66: 1429
D67: Live | E67: FBA79573 | F67: B0DKK15YNJ | G67: EA-02 | H67: HPC | I67: Hair Care | J67: Nexlev Oil Applicator Comb | K67: 90191020 | L67: =VLOOKUP(E67,'Margin Calculation'!F:U,16,0) -> 10.15 | M67: =VLOOKUP(E67,'Margin Calculation'!F:V,17,0) -> 11.35 | N67: =L67*2% -> 0.203 | O67: =VLOOKUP(E67,'Margin Calculation'!F:X,19,0) -> 1.13883 | P67: =(L67+N67+O67)*$B$2 -> 1011.281 | Q67: =P67*1.18 -> 1193.3116 | R67: =VLOOKUP(E67,'Margin Calculation'!F:AA,22,0) -> 194.925 | S67: 20 | T67: 58 | U67: 295.4 | V67: =AF67*20% -> 519.8 | W67: =AF67*$B$18 -> 25.99 | X67: =AF67*$B$15 -> 129.95 | Y67: =AF67*$B$21 -> 51.98 | Z67: =AF67-(AF67/1.18) -> 396.45763 | AA67: =AF67*$B$16 -> 129.95 | AB67: =AF67*$B$17 -> 77.97 | AC67: =P67+R67+S67+T67+V67+W67+X67+Y67+Z67+AA67+AB67 -> 2616.3037 | AD67: =AF67-AC67 -> -17.303667 | AE67: =AD67/AF67 -> -0.0066578173 | AF67: 2599 | AI67: 3999 | AJ67: =(AF67-P67)-Z67 -> 1191.2613 | AK67: =AJ67/AF67 -> 0.45835373 | AL67: 8904422505285 | AN67: B0DFCDKMWR | AO67: 1398
D68: Live | E68: FBA79589 | F68: B0DNJP9T35 | G68: SS-02 | H68: Cleaning & Vacumming | J68: Nexlev Spin Scrubber - mini | K68: 85098000 | L68: =VLOOKUP(E68,'Margin Calculation'!F:U,16,0) -> 9 | M68: =VLOOKUP(E68,'Margin Calculation'!F:V,17,0) -> 9.9 | N68: =L68*2% -> 0.18 | O68: =VLOOKUP(E68,'Margin Calculation'!F:X,19,0) -> 1.0098 | P68: =(L68+N68+O68)*$B$2 -> 896.7024 | Q68: =P68*1.18 -> 1058.1088 | R68: =VLOOKUP(E68,'Margin Calculation'!F:AA,22,0) -> 204.9 | S68: 50 | T68: 108 | U68: 357.9 | V68: =AF68*10% -> 209.9 | W68: =AF68*$B$18 -> 20.99 | X68: =AF68*$B$15 -> 104.95 | Y68: =AF68*$B$21 -> 41.98 | Z68: =AF68-(AF68/1.18) -> 320.18644 | AA68: =AF68*$B$16 -> 104.95 | AB68: =AF68*$B$17 -> 62.97 | AC68: =P68+R68+S68+T68+V68+W68+X68+Y68+Z68+AA68+AB68 -> 2125.5288 | AD68: =AF68-AC68 -> -26.528841 | AE68: =AD68/AF68 -> -0.0126388 | AF68: 2099 | AI68: 4999 | AJ68: =(AF68-P68)-Z68 -> 882.11116 | AK68: =AJ68/AF68 -> 0.42025305 | AL68: 8904422505292 | AN68: B0D2LHNS9B | AO68: 898
D69: Live | E69: FBA79590 | F69: B0DM6BB3VT | G69: CFM-01 | H69: HPC | I69: Electric Massagers | J69: NexLev Calf Massager | K69: 90191020 | L69: =VLOOKUP(E69,'Margin Calculation'!F:U,16,0) -> 8.4 | M69: =VLOOKUP(E69,'Margin Calculation'!F:V,17,0) -> 0 | N69: =L69*2% -> 0.168 | O69: =VLOOKUP(E69,'Margin Calculation'!F:X,19,0) -> 0.94248 | P69: =(L69+N69+O69)*$B$2 -> 836.92224 | Q69: =P69*1.12 -> 937.35291 | R69: =VLOOKUP(E69,'Margin Calculation'!F:AA,22,0) -> 202.425 | S69: 50 | T69: 107 | U69: 577.4 | V69: =AF69*20% -> 537.8 | W69: =AF69*$B$18 -> 26.89 | X69: =AF69*$B$15 -> 134.45 | Y69: =AF69*$B$21 -> 53.78 | Z69: =AF69-(AF69/1.18) -> 410.18644 | AA69: =AF69*$B$16 -> 134.45 | AB69: =AF69*$B$17 -> 80.67 | AC69: =P69+R69+S69+T69+V69+W69+X69+Y69+Z69+AA69+AB69 -> 2574.5737 | AD69: =AF69-AC69 -> 114.42632 | AE69: =AD69/AF69 -> 0.042553484 | AF69: 2689 | AI69: 3999 | AJ69: =(AF69-P69)-Z69 -> 1441.8913 | AK69: =AJ69/AF69 -> 0.53621842 | AL69: 8904422505308 | AN69: B0DQCWRG3H | AO69: 1999
D70: Live | E70: FBA79591 | F70: B0DM66B2DW | G70: KM-01 | H70: HPC | I70: Electric Massagers | J70: NexLev Knee Massager | K70: 90191020 | L70: =VLOOKUP(E70,'Margin Calculation'!F:U,16,0) -> 8.65 | M70: =VLOOKUP(E70,'Margin Calculation'!F:V,17,0) -> 0 | N70: =L70*2% -> 0.173 | O70: =VLOOKUP(E70,'Margin Calculation'!F:X,19,0) -> 0.97053 | P70: =(L70+N70+O70)*$B$2 -> 861.83064 | Q70: =P70*1.12 -> 965.25032 | R70: =VLOOKUP(E70,'Margin Calculation'!F:AA,22,0) -> 108.675 | S70: 50 | T70: 59 | U70: 287.1 | V70: =AF70*20% -> 289.8 | W70: =AF70*$B$18 -> 14.49 | X70: =AF70*$B$15 -> 72.45 | Y70: =AF70*$B$21 -> 28.98 | Z70: =AF70-(AF70/1.18) -> 221.0339 | AA70: =AF70*$B$16 -> 72.45 | AB70: =AF70*$B$17 -> 43.47 | AC70: =P70+R70+S70+T70+V70+W70+X70+Y70+Z70+AA70+AB70 -> 1822.1795 | AD70: =AF70-AC70 -> -373.17954 | AE70: =AD70/AF70 -> -0.25754281 | AF70: 1449 | AI70: 3399 | AJ70: =(AF70-P70)-Z70 -> 366.13546 | AK70: =AJ70/AF70 -> 0.25268148 | AL70: 8904422505315 | AN70: B0DFCDZWND | AO70: 1219
D71: Live | E71: FBA79595 | F71: B0DMSHZXG2 | G71: EM-02 | H71: HPC | I71: Electric Massagers | J71: NexLev Eye Massager - Pro | K71: 90191020 | L71: =VLOOKUP(E71,'Margin Calculation'!F:U,16,0) -> 12 | M71: =VLOOKUP(E71,'Margin Calculation'!F:V,17,0) -> 0 | N71: =L71*2% -> 0.24 | O71: =VLOOKUP(E71,'Margin Calculation'!F:X,19,0) -> 1.3464 | P71: =(L71+N71+O71)*$B$2 -> 1195.6032 | Q71: =P71*1.12 -> 1339.0756 | R71: =VLOOKUP(E71,'Margin Calculation'!F:AA,22,0) -> 132.225 | S71: 50 | T71: 79 | U71: 389.9 | V71: =AF71*20% -> 352.6 | W71: =AF71*$B$18 -> 17.63 | X71: =AF71*$B$15 -> 88.15 | Y71: =AF71*$B$21 -> 35.26 | Z71: =AF71-(AF71/1.18) -> 268.9322 | AA71: =AF71*$B$16 -> 88.15 | AB71: =AF71*$B$17 -> 52.89 | AC71: =P71+R71+S71+T71+V71+W71+X71+Y71+Z71+AA71+AB71 -> 2360.4404 | AD71: =AF71-AC71 -> -597.4404 | AE71: =AD71/AF71 -> -0.33887714 | AF71: 1763 | AI71: 6299 | AJ71: =(AF71-P71)-Z71 -> 298.4646 | AK71: =AJ71/AF71 -> 0.16929359 | AL71: 8904422505353 | AN71: B0D2LGR3GG | AO71: 898
D72: OOS | E72: FBA79596 | F72: B0DMT19RWC | G72: MG-01 | H72: HPC | I72: Electric Massagers | J72: NexLev Massage Gun | K72: 90191020 | L72: =VLOOKUP(E72,'Margin Calculation'!F:U,16,0) -> #N/A | M72: =VLOOKUP(E72,'Margin Calculation'!F:V,17,0) -> #N/A | N72: =L72*2% -> #N/A | O72: =VLOOKUP(E72,'Margin Calculation'!F:X,19,0) -> #N/A | P72: =(L72+N72+O72)*$B$2 -> #N/A | Q72: =P72*1.12 -> #N/A | R72: =VLOOKUP(E72,'Margin Calculation'!F:AA,22,0) -> #N/A | S72: 50 | T72: 107 | U72: 418.6 | V72: =AF72*20% -> 351.8 | W72: =AF72*$B$18 -> 17.59 | X72: =AF72*$B$15 -> 87.95 | Y72: =AF72*$B$21 -> 35.18 | Z72: =AF72-(AF72/1.18) -> 268.32203 | AA72: =AF72*$B$16 -> 87.95 | AB72: =AF72*$B$17 -> 52.77 | AC72: =P72+R72+S72+T72+V72+W72+X72+Y72+Z72+AA72+AB72 -> #N/A | AD72: =AF72-AC72 -> #N/A | AE72: =AD72/AF72 -> #N/A | AF72: 1759 | AI72: 3199 | AJ72: =(AF72-P72)-Z72 -> #N/A | AK72: =AJ72/AF72 -> #N/A | AL72: 8904422505360 | AN72: B0D67727VG | AO72: 1019
D73: Live | E73: FBA79598 | F73: B0DNJJKBKG | G73: BM-02 | H73: HPC | I73: Electric Massagers | J73: NexLev Back and Shoulder Massager | K73: 90191020 | L73: =VLOOKUP(E73,'Margin Calculation'!F:U,16,0) -> 7.82 | M73: =VLOOKUP(E73,'Margin Calculation'!F:V,17,0) -> 0 | N73: =L73*2% -> 0.1564 | O73: =VLOOKUP(E73,'Margin Calculation'!F:X,19,0) -> 0.877404 | P73: =(L73+N73+O73)*$B$2 -> 779.13475 | Q73: =P73*1.12 -> 872.63092 | R73: =VLOOKUP(E73,'Margin Calculation'!F:AA,22,0) -> 139.425 | S73: 50 | T73: 135 | U73: 475.6 | V73: =AF73*20% -> 371.8 | W73: =AF73*$B$18 -> 18.59 | X73: =AF73*$B$15 -> 92.95 | Y73: =AF73*$B$21 -> 37.18 | Z73: =AF73-(AF73/1.18) -> 283.57627 | AA73: =AF73*$B$16 -> 92.95 | AB73: =AF73*$B$17 -> 55.77 | AC73: =P73+R73+S73+T73+V73+W73+X73+Y73+Z73+AA73+AB73 -> 2056.376 | AD73: =AF73-AC73 -> -197.37602 | AE73: =AD73/AF73 -> -0.10617322 | AF73: 1859 | AG73: 300 | AI73: 3399 | AJ73: =(AF73-P73)-Z73 -> 796.28898 | AK73: =AJ73/AF73 -> 0.42834264 | AL73: 8904422505384 | AN73: B0DKK15YNJ | AO73: 2999
D74: Live | E74: FBA79599 | F74: B0DRD8J8R5 | G74: VC-06 | H74: Home & Kitchen | I74: Cleaning & Vacumming | J74: NexLev Handheld Vacuum Cleaner | K74: 85086000 | L74: =VLOOKUP(E74,'Margin Calculation'!F:U,16,0) -> 7.4 | M74: =VLOOKUP(E74,'Margin Calculation'!F:V,17,0) -> 0 | N74: =L74*2% -> 0.148 | O74: =VLOOKUP(E74,'Margin Calculation'!F:X,19,0) -> 0.83028 | P74: =(L74+N74+O74)*$B$2 -> 737.28864 | Q74: =P74*1.18 -> 870.0006 | R74: =VLOOKUP(E74,'Margin Calculation'!F:AA,22,0) -> 97.435 | S74: 50 | T74: 135 | U74: 276.3 | V74: =AF74*10% -> 139.9 | W74: =AF74*$B$18 -> 13.99 | X74: =AF74*$B$15 -> 69.95 | Y74: =AF74*$B$21 -> 27.98 | Z74: =AF74-(AF74/1.18) -> 213.40678 | AA74: =AF74*$B$16 -> 69.95 | AB74: =AF74*$B$17 -> 41.97 | AC74: =P74+R74+S74+T74+V74+W74+X74+Y74+Z74+AA74+AB74 -> 1596.8704 | AD74: =AF74-AC74 -> -197.87042 | AE74: =AD74/AF74 -> -0.14143704 | AF74: =VLOOKUP(F74,AN:AO,2,0) -> 1399 | AI74: 3699 | AJ74: =(AF74-P74)-Z74 -> 448.30458 | AK74: =AJ74/AF74 -> 0.32044645 | AL74: 8904422505391 | AN74: B0D63DTKQB | AO74: 1399
D75: Live | E75: FBA79652 | F75: B0F43P6D23 | G75: SC-05 | H75: Cleaning & Vacuuming | J75: Steam Cleaner-Shine Pro | K75: 85098000 | L75: =VLOOKUP(E75,'Margin Calculation'!F:U,16,0) -> 10.8 | M75: =VLOOKUP(E75,'Margin Calculation'!F:V,17,0) -> 0 | N75: =L75*2% -> 0.216 | O75: =VLOOKUP(E75,'Margin Calculation'!F:X,19,0) -> 2.42352 | P75: =(L75+N75+O75)*$B$2 -> 1182.6778 | Q75: =P75*1.18 -> 1395.5598 | R75: =VLOOKUP(E75,'Margin Calculation'!F:AA,22,0) -> 180 | S75: 50 | T75: 135 | U75: 380.3 | V75: =AF75*10% -> 279.9 | W75: =AF75*$B$18 -> 27.99 | X75: =AF75*$B$15 -> 139.95 | Y75: =AF75*$B$21 -> 55.98 | Z75: =AF75-(AF75/1.18) -> 426.9661 | AA75: =AF75*$B$16 -> 139.95 | AB75: =AF75*$B$17 -> 83.97 | AC75: =P75+R75+S75+T75+V75+W75+X75+Y75+Z75+AA75+AB75 -> 2702.3839 | AD75: =AF75-AC75 -> 96.616138 | AE75: =AD75/AF75 -> 0.034518092 | AF75: 2799 | AI75: 5499 | AJ75: =(AF75-P75)-Z75 -> 1189.3561 | AK75: =AJ75/AF75 -> 0.42492181 | AL75: 8904422505520 | AN75: B0DCK3N2JJ | AO75: 2498
D76: Live | E76: FBA79679 | F76: B0DVC7VJP1 | G76: ST-01 | H76: Kitchen Appliances | J76: Stand Mixer | K76: 85094090 | L76: =VLOOKUP(E76,'Margin Calculation'!F:U,16,0) -> 25.5 | M76: =VLOOKUP(E76,'Margin Calculation'!F:V,17,0) -> 0 | N76: =L76*2% -> 0.51 | O76: =VLOOKUP(E76,'Margin Calculation'!F:X,19,0) -> 5.7222 | P76: =(L76+N76+O76)*$B$2 -> 2792.4336 | Q76: =P76*1.18 -> 3295.0716 | R76: =VLOOKUP(E76,'Margin Calculation'!F:AA,22,0) -> 479.92 | S76: 54 | T76: 219 | U76: 736.9 | V76: =AF76*10% -> 599.9 | W76: =AF76*$B$18 -> 59.99 | X76: =AF76*$B$15 -> 299.95 | Y76: =AF76*$B$21 -> 119.98 | Z76: =AF76-(AF76/1.18) -> 915.10169 | AA76: =AF76*$B$16 -> 299.95 | AB76: =AF76*$B$17 -> 179.97 | AC76: =P76+R76+S76+T76+V76+W76+X76+Y76+Z76+AA76+AB76 -> 6020.1953 | AD76: =AF76-AC76 -> -21.195295 | AE76: =AD76/AF76 -> -0.003533138 | AF76: 5999 | AI76: 10999 | AJ76: =(AF76-P76)-Z76 -> 2291.4647 | AK76: =AJ76/AF76 -> 0.38197445 | AL76: 8904422505759 | AN76: B0D2LD6BYJ | AO76: 1119
D77: Live | E77: FBA79673 | F77: B0FJG5PFGQ | G77: ETC-07-WH | H77: Oral care | J77: Electric Toothbrush - Type C- White | K77: 85098000 | L77: =VLOOKUP(E77,'Margin Calculation'!F:U,16,0) -> 2.84 | M77: =VLOOKUP(E77,'Margin Calculation'!F:V,17,0) -> 0 | N77: =L77*2% -> 0.0568 | O77: =VLOOKUP(E77,'Margin Calculation'!F:X,19,0) -> 0.637296 | P77: =(L77+N77+O77)*$B$2 -> 311.00045 | Q77: =P77*1.18 -> 366.98053 | R77: =VLOOKUP(E77,'Margin Calculation'!F:AA,22,0) -> 56.175 | S77: 12 | T77: 60 | U77: 103.5 | V77: =AF77*10% -> 69.9 | W77: =AF77*$B$18 -> 6.99 | X77: =AF77*$B$15 -> 34.95 | Y77: =AF77*$B$21 -> 13.98 | Z77: =AF77-(AF77/1.18) -> 106.62712 | AA77: =AF77*$B$16 -> 34.95 | AB77: =AF77*$B$17 -> 20.97 | AC77: =P77+R77+S77+T77+V77+W77+X77+Y77+Z77+AA77+AB77 -> 727.54257 | AD77: =AF77-AC77 -> -28.542567 | AE77: =AD77/AF77 -> -0.040833429 | AF77: 699 | AI77: 1199 | AJ77: =(AF77-P77)-Z77 -> 281.37243 | AK77: =AJ77/AF77 -> 0.40253567 | AL77: 8904422505780 | AN77: B0D9KB2RTT | AO77: 599
D78: Live | E78: FBA79674 | F78: B0DV8XH455 | G78: BM-03 | H78: Massager | J78: Back and Shoulder Massager Pro | K78: 90191020 | L78: =VLOOKUP(E78,'Margin Calculation'!F:U,16,0) -> 8 | M78: =VLOOKUP(E78,'Margin Calculation'!F:V,17,0) -> 0 | N78: =L78*2% -> 0.16 | O78: =VLOOKUP(E78,'Margin Calculation'!F:X,19,0) -> 0.8976 | P78: =(L78+N78+O78)*$B$2 -> 797.0688 | Q78: =P78*1.18 -> 940.54118 | R78: =VLOOKUP(E78,'Margin Calculation'!F:AA,22,0) -> 139.425 | S78: 50 | T78: 59 | U78: 384.4 | V78: =AF78*10% -> 204.5 | W78: =AF78*$B$18 -> 20.45 | X78: =AF78*$B$15 -> 102.25 | Y78: =AF78*$B$21 -> 40.9 | Z78: =AF78-(AF78/1.18) -> 311.94915 | AA78: =AF78*$B$16 -> 102.25 | AB78: =AF78*$B$17 -> 61.35 | AC78: =P78+R78+S78+T78+V78+W78+X78+Y78+Z78+AA78+AB78 -> 1889.143 | AD78: =AF78-AC78 -> 155.85705 | AE78: =AD78/AF78 -> 0.076213715 | AF78: 2045 | AG78: 300 | AI78: 3499 | AJ78: =(AF78-P78)-Z78 -> 935.98205 | AK78: =AJ78/AF78 -> 0.45769293 | AL78: 8904422505728 | AN78: B0DMSSLXST | AO78: 1699
D79: Live | E79: FBA79675 | F79: B0DV9MYK6S | G79: PM-01 | H79: Massager | J79: Handheld Percussion Massager | K79: 90191020 | L79: =VLOOKUP(E79,'Margin Calculation'!F:U,16,0) -> 7.9 | M79: =VLOOKUP(E79,'Margin Calculation'!F:V,17,0) -> 0 | N79: =L79*2% -> 0.158 | O79: =VLOOKUP(E79,'Margin Calculation'!F:X,19,0) -> 0.88638 | P79: =(L79+N79+O79)*$B$2 -> 787.10544 | Q79: =P79*1.18 -> 928.78442 | R79: =VLOOKUP(E79,'Margin Calculation'!F:AA,22,0) -> 154.425 | S79: 50 | T79: 79 | U79: 433.4 | V79: =AF79*10% -> 218.3 | W79: =AF79*$B$18 -> 21.83 | X79: =AF79*$B$15 -> 109.15 | Y79: =AF79*$B$21 -> 43.66 | Z79: =AF79-(AF79/1.18) -> 333 | AA79: =AF79*$B$16 -> 109.15 | AB79: =AF79*$B$17 -> 65.49 | AC79: =P79+R79+S79+T79+V79+W79+X79+Y79+Z79+AA79+AB79 -> 1971.1104 | AD79: =AF79-AC79 -> 211.88956 | AE79: =AD79/AF79 -> 0.097063472 | AF79: 2183 | AI79: 3899 | AJ79: =(AF79-P79)-Z79 -> 1062.8946 | AK79: =AJ79/AF79 -> 0.48689627 | AL79: 8904422505735 | AN79: B0CSG2JZ19 | AO79: 398
D80: Live | E80: FBA79677 | F80: B0DVCBR11D | G80: NP-06 | H80: Travel & outdoor | J80: NexLev Donut Pillow - Blue | K80: 94043090 | L80: =VLOOKUP(E80,'Margin Calculation'!F:U,16,0) -> 3.6 | M80: =VLOOKUP(E80,'Margin Calculation'!F:V,17,0) -> 0 | N80: =L80*2% -> 0.072 | O80: =VLOOKUP(E80,'Margin Calculation'!F:X,19,0) -> 1.0303116 | P80: =(L80+N80+O80)*$B$2 -> 413.80342 | Q80: =P80*1.18 -> 488.28804 | R80: =VLOOKUP(E80,'Margin Calculation'!F:AA,22,0) -> 131.88 | S80: 50 | T80: 79 | U80: 261.5 | V80: =AF80*10% -> 109.9 | W80: =AF80*$B$18 -> 10.99 | X80: =AF80*$B$15 -> 54.95 | Y80: =AF80*$B$21 -> 21.98 | Z80: =AF80-(AF80/1.18) -> 167.64407 | AA80: =AF80*$B$16 -> 54.95 | AB80: =AF80*$B$17 -> 32.97 | AC80: =P80+R80+S80+T80+V80+W80+X80+Y80+Z80+AA80+AB80 -> 1128.0675 | AD80: =AF80-AC80 -> -29.067492 | AE80: =AD80/AF80 -> -0.026449037 | AF80: =VLOOKUP(F80,AN:AO,2,0) -> 1099 | AI80: 1899 | AJ80: =(AF80-P80)-Z80 -> 517.55251 | AK80: =AJ80/AF80 -> 0.4709304 | AL80: 8904422505766 | AN80: B0CS69T7HF | AO80: 398
D81: Live | E81: FBA79678 | F81: B0DVCDD5VC | G81: NP-07 | H81: Travel & outdoor | J81: NexLev Donut Pillow - Grey | K81: 94043090 | L81: =VLOOKUP(E81,'Margin Calculation'!F:U,16,0) -> 3.6 | M81: =VLOOKUP(E81,'Margin Calculation'!F:V,17,0) -> 0 | N81: =L81*2% -> 0.072 | O81: =VLOOKUP(E81,'Margin Calculation'!F:X,19,0) -> 1.0303116 | P81: =(L81+N81+O81)*$B$2 -> 413.80342 | Q81: =P81*1.18 -> 488.28804 | R81: =VLOOKUP(E81,'Margin Calculation'!F:AA,22,0) -> 131.88 | S81: 50 | T81: 79 | U81: 260.9 | V81: =AF81*10% -> 109.9 | W81: =AF81*$B$18 -> 10.99 | X81: =AF81*$B$15 -> 54.95 | Y81: =AF81*$B$21 -> 21.98 | Z81: =AF81-(AF81/1.18) -> 167.64407 | AA81: =AF81*$B$16 -> 54.95 | AB81: =AF81*$B$17 -> 32.97 | AC81: =P81+R81+S81+T81+V81+W81+X81+Y81+Z81+AA81+AB81 -> 1128.0675 | AD81: =AF81-AC81 -> -29.067492 | AE81: =AD81/AF81 -> -0.026449037 | AF81: =VLOOKUP(F81,AN:AO,2,0) -> 1099 | AI81: 1899 | AJ81: =(AF81-P81)-Z81 -> 517.55251 | AK81: =AJ81/AF81 -> 0.4709304 | AL81: 8904422505773 | AN81: B0D9KFZYG8 | AO81: 1599
D82: Live | E82: FBA79683 | F82: B0DVC9PRSD | G82: AP-01 | H82: Home & Kitchen | J82: Air Purifier - 5 Speed | K82: 84213920 | L82: =VLOOKUP(E82,'Margin Calculation'!F:U,16,0) -> 85 | M82: =VLOOKUP(E82,'Margin Calculation'!F:V,17,0) -> 0 | N82: =L82*2% -> 1.7 | O82: =VLOOKUP(E82,'Margin Calculation'!F:X,19,0) -> 7.0245935 | P82: =(L82+N82+O82)*$B$2 -> 8247.7642 | Q82: =P82*1.18 -> 9732.3618 | R82: =VLOOKUP(E82,'Margin Calculation'!F:AA,22,0) -> 1214.65 | S82: 50 | T82: 191 | U82: 1600.2 | V82: =AF82*10% -> 1599 | W82: =AF82*$B$18 -> 159.9 | X82: =AF82*$B$15 -> 799.5 | Y82: =AF82*$B$21 -> 319.8 | Z82: =AF82-(AF82/1.18) -> 2439.1525 | AA82: =AF82*$B$16 -> 799.5 | AB82: =AF82*$B$17 -> 479.7 | AC82: =P82+R82+S82+T82+V82+W82+X82+Y82+Z82+AA82+AB82 -> 16299.967 | AD82: =AF82-AC82 -> -309.96677 | AE82: =AD82/AF82 -> -0.019385039 | AF82: =VLOOKUP(F82,AN:AO,2,0) -> 15990 | AI82: 29999 | AJ82: =(AF82-P82)-Z82 -> 5303.0832 | AK82: =AJ82/AF82 -> 0.33164998 | AL82: 8904422505810 | AN82: B0D63FKYZ5 | AO82: 999
D83: Live | E83: FBA79681 | F83: B0DVC968P1 | G83: HU-01 | H83: Home & Kitchen | J83: Humidifier - Black | K83: 85098000 | L83: =VLOOKUP(E83,'Margin Calculation'!F:U,16,0) -> 6 | M83: =VLOOKUP(E83,'Margin Calculation'!F:V,17,0) -> 0 | N83: =L83*2% -> 0.12 | O83: =VLOOKUP(E83,'Margin Calculation'!F:X,19,0) -> 1.3522493 | P83: =(L83+N83+O83)*$B$2 -> 657.55794 | Q83: =P83*1.18 -> 775.91837 | R83: =VLOOKUP(E83,'Margin Calculation'!F:AA,22,0) -> 138.675 | S83: 50 | T83: 191 | U83: 387 | V83: =AF83*10% -> 184.9 | W83: =AF83*$B$18 -> 18.49 | X83: =AF83*$B$15 -> 92.45 | Y83: =AF83*$B$21 -> 36.98 | Z83: =AF83-(AF83/1.18) -> 282.05085 | AA83: =AF83*$B$16 -> 92.45 | AB83: =AF83*$B$17 -> 55.47 | AC83: =P83+R83+S83+T83+V83+W83+X83+Y83+Z83+AA83+AB83 -> 1800.0238 | AD83: =AF83-AC83 -> 48.976213 | AE83: =AD83/AF83 -> 0.026487947 | AF83: 1849 | AI83: 3599 | AJ83: =(AF83-P83)-Z83 -> 909.39121 | AK83: =AJ83/AF83 -> 0.49182867 | AL83: 8904422505797 | AN83: B0DM6BB3VT | AO83: 2599
D84: Live | E84: FBA79682 | F84: B0DVC8NYY2 | G84: HU-02 | H84: Home & Kitchen | J84: Humidifier - White | K84: 85098000 | L84: =VLOOKUP(E84,'Margin Calculation'!F:U,16,0) -> 6 | M84: =VLOOKUP(E84,'Margin Calculation'!F:V,17,0) -> 0 | N84: =L84*2% -> 0.12 | O84: =VLOOKUP(E84,'Margin Calculation'!F:X,19,0) -> 1.3522493 | P84: =(L84+N84+O84)*$B$2 -> 657.55794 | Q84: =P84*1.18 -> 775.91837 | R84: =VLOOKUP(E84,'Margin Calculation'!F:AA,22,0) -> 146.175 | S84: 50 | T84: 191 | U84: 360.9 | V84: =AF84*10% -> 179.9 | W84: =AF84*$B$18 -> 17.99 | X84: =AF84*$B$15 -> 89.95 | Y84: =AF84*$B$21 -> 35.98 | Z84: =AF84-(AF84/1.18) -> 274.42373 | AA84: =AF84*$B$16 -> 89.95 | AB84: =AF84*$B$17 -> 53.97 | AC84: =P84+R84+S84+T84+V84+W84+X84+Y84+Z84+AA84+AB84 -> 1786.8967 | AD84: =AF84-AC84 -> 12.103332 | AE84: =AD84/AF84 -> 0.006727811 | AF84: 1799 | AI84: 2899 | AJ84: =(AF84-P84)-Z84 -> 867.01833 | AK84: =AJ84/AF84 -> 0.4819446 | AL84: 8904422505803 | AN84: B0DK9LYT4P | AO84: 999
D85: Live | E85: FBA79690 | F85: B0DV931G48 | G85: PM-02 | H85: Massager | J85: Percussion Massager - Mini | K85: 90191020 | L85: =VLOOKUP(E85,'Margin Calculation'!F:U,16,0) -> 8 | M85: =VLOOKUP(E85,'Margin Calculation'!F:V,17,0) -> 0 | N85: =L85*2% -> 0.16 | O85: =VLOOKUP(E85,'Margin Calculation'!F:X,19,0) -> 0.8976 | P85: =(L85+N85+O85)*$B$2 -> 797.0688 | Q85: =P85*1.18 -> 940.54118 | R85: =VLOOKUP(E85,'Margin Calculation'!F:AA,22,0) -> 250.56 | S85: 50 | T85: 79 | U85: 389.9 | V85: =AF85*10% -> 186.9 | W85: =AF85*$B$18 -> 18.69 | X85: =AF85*$B$15 -> 93.45 | Y85: =AF85*$B$21 -> 37.38 | Z85: =AF85-(AF85/1.18) -> 285.10169 | AA85: =AF85*$B$16 -> 93.45 | AB85: =AF85*$B$17 -> 56.07 | AC85: =P85+R85+S85+T85+V85+W85+X85+Y85+Z85+AA85+AB85 -> 1947.6705 | AD85: =AF85-AC85 -> -78.670495 | AE85: =AD85/AF85 -> -0.042092293 | AF85: 1869 | AI85: 3999 | AJ85: =(AF85-P85)-Z85 -> 786.82951 | AK85: =AJ85/AF85 -> 0.42098957 | AL85: 8904422505889 | AN85: B0D842173P | AO85: 699
D86: Live | E86: FBA79692 | F86: B0DVC58QPZ | G86: AP-03 | H86: Home & Kitchen | J86: NexLev Air Purifier Mini | K86: 84213920 | L86: =VLOOKUP(E86,'Margin Calculation'!F:U,16,0) -> 17.5 | M86: =VLOOKUP(E86,'Margin Calculation'!F:V,17,0) -> 0 | N86: =L86*2% -> 0.35 | O86: =VLOOKUP(E86,'Margin Calculation'!F:X,19,0) -> 1.9635 | P86: =(L86+N86+O86)*$B$2 -> 1743.588 | Q86: =P86*1.18 -> 2057.4338 | R86: =VLOOKUP(E86,'Margin Calculation'!F:AA,22,0) -> 299.925 | S86: 50 | T86: 191 | U86: 546.8 | V86: =AF86*10% -> 359.9 | W86: =AF86*$B$18 -> 35.99 | X86: =AF86*$B$15 -> 179.95 | Y86: =AF86*$B$21 -> 71.98 | Z86: =AF86-(AF86/1.18) -> 549 | AA86: =AF86*$B$16 -> 179.95 | AB86: =AF86*$B$17 -> 107.97 | AC86: =P86+R86+S86+T86+V86+W86+X86+Y86+Z86+AA86+AB86 -> 3769.253 | AD86: =AF86-AC86 -> -170.253 | AE86: =AD86/AF86 -> -0.04730564 | AF86: 3599 | AI86: 6499 | AJ86: =(AF86-P86)-Z86 -> 1306.412 | AK86: =AJ86/AF86 -> 0.36299305 | AL86: 8904422505896 | AN86: B0D9KFQG8Q | AO86: 1799
D87: Live | E87: FBA79693 | F87: B0DVC91Q7J | G87: TM-05 | H87: HPC | J87: Vacuum Trimmer | K87: 85101000 | L87: =VLOOKUP(E87,'Margin Calculation'!F:U,16,0) -> 9 | M87: =VLOOKUP(E87,'Margin Calculation'!F:V,17,0) -> 0 | N87: =L87*2% -> 0.18 | O87: =VLOOKUP(E87,'Margin Calculation'!F:X,19,0) -> 2.0196 | P87: =(L87+N87+O87)*$B$2 -> 985.5648 | Q87: =P87*1.18 -> 1162.9665 | R87: =VLOOKUP(E87,'Margin Calculation'!F:AA,22,0) -> 246.905 | S87: 50 | T87: 60 | U87: 384.9 | V87: =AF87*20% -> 499.8 | W87: =AF87*$B$18 -> 24.99 | X87: =AF87*$B$15 -> 124.95 | Y87: =AF87*$B$21 -> 49.98 | Z87: =AF87-(AF87/1.18) -> 381.20339 | AA87: =AF87*$B$16 -> 124.95 | AB87: =AF87*$B$17 -> 74.97 | AC87: =P87+R87+S87+T87+V87+W87+X87+Y87+Z87+AA87+AB87 -> 2623.3132 | AD87: =AF87-AC87 -> -124.31319 | AE87: =AD87/AF87 -> -0.049745174 | AF87: =VLOOKUP(F87,AN:AO,2,0) -> 2499 | AI87: 3499 | AJ87: =(AF87-P87)-Z87 -> 1132.2318 | AK87: =AJ87/AF87 -> 0.45307395 | AL87: 8904422505919 | AN87: B0D9KFP4MG | AO87: 1997
